Workbook
Name _Toc209908: BP_Pres!#REF!
Name _Toc209939: BP_Pres!$A$157
Name _Toc209949: BP_Pres!$A$165
Name _Toc209956: BP_Pres!$A$223
Name _Toc209961: BP_Pres!$A$297
Name _Toc209965: BP_Pres!$A$369
Name _Toc3199075: BP_Pres!$A$98
Name _Toc3199076: BP_Pres!$A$125
Name _Toc3199077: BP_Pres!$A$126
Name _Toc3199078: BP_Pres!$A$130
Name _Toc3199080: BP_Pres!$A$160
Name _Toc3199082: BP_Pres!#REF!
Name _Toc3199083: BP_Pres!$A$167
Name _Toc3199084: BP_Pres!$A$199
Name _Toc3199085: BP_Pres!$A$200
Name _Toc3199086: BP_Pres!$A$211
Name _Toc3199088: BP_Pres!$A$224
Name _Toc3199089: BP_Pres!$A$252
Name _Toc3199090: BP_Pres!$A$269
Name _Toc3199091: BP_Pres!$A$297
Name _Toc3199092: BP_Pres!$A$298
Name _Toc3199093: BP_Pres!$A$346
Name _Toc959083: BP_Pres!$A$262
Name Debt_Choice: #REF!
Name jj: #REF!
Name valuevx: 42.314159

Sheet BP_Pres
A2: Instructions:
A3: 1. Remplir les données concernant les "variables principales". Les calculs se font automatiquement.
A4: 2. Remplir les informations sur le promoteur aux pages 1 et 3.
A5: 3. Imprimer
A9: Variables principales pour le client final
A10: Type de produit | B10: Nom | C10: Qté | D10: Prix
A11: Ventes de marchandises | B11: {var_1} | C11: {var_5} | D11: {var_9}
A12: Ventes de marchandises | B12: {var_2} | C12: {var_6} | D12: {var_10}
A13: Ventes de marchandises | B13: {var_3} | C13: {var_7} | D13: {var_12}
A14: Ventes de marchandises | B14: {var_4} | C14: {var_8} | D14: {var_13} | E14: {var_11}
A76: Table des matières
A77: RÉSUMÉ DU PROJET | G77: 3
A78: 1. | B78: DESCRIPTION DU PROJET | G78: 4
A79: 2. | B79: MOYENS MATÉRIELS ET HUMAINS | G79: 4
A80: 3. | B80: PROGRAMME DE RÉALISATION | G80: 4
A81: 4. | B81: DESCRIPTION DU MARCHE | G81: 5
A82: 5. | B82: ÉTUDE FINANCIÈRE ET PLAN DE FINANCEMENT | G82: 5
A83: 5.1 | B83: Investissements | G83: 5
A84: 5.2 | B84: Fonds de Roulement | G84: 5
A85: 5.3 | B85: Récapitulatif des besoins de financement | G85: 6
A86: 5.4 | B86: Prévision des recettes | G86: 7
A87: 6. | B87: LES CHARGES D’EXPLOITATION | G87: 8
A88: 6.1 | B88: Achats, services extérieurs et autres charges | G88: 8
A89: 6.2 | B89: Impôts annuels et frais financiers | G89: 9
... A95: 7.4 | B95: Bilan annuel prévisionnel | G95: 14
A98: RÉSUMÉ DU PROJET
A100: NOM DU BÉNÉFICIAIRE :
A101: Ce simulateur de business plan s'adresse principalement aux promotteurs qui souhaitent vendre en gros des vêtements, des matériaux de construction, des voitures… Il reprend un circuit classique d'importation par container et de revente du contenu du container aux clients grossistes.
A102: Ø Nom et prénoms :
A103: Ø Date et lieu de naissance :
A104: Ø Sexe :
A105: Ø Situation Matrimoniale :
A106: Ø Niveau d’étude et diplôme :
A107: Ø Téléphone :
A108: Ø Adresse géographique :
B109: Année 1 | C109: Année 2 | D109: Année 3 | E109: Année 4 | F109: Année 5 | G109: Total
A110: Financement total requis | B110: =SUM(B111,B112,B116) -> 3775000.9 | C110: =SUM(C111,C112,C116) -> 3698500.9 | D110: =SUM(D111,D112,D116) -> 0 | E110: =SUM(E111,E112,E116) -> 0 | F110: =SUM(F111,F112,F116) -> 0 | G110: =SUM(B110:F110) -> 7473501.7
A111: Capital initial | B111: ='1.Var.Fin'!B17 -> 0 | C111: ='1.Var.Fin'!C17 -> 0 | D111: ='1.Var.Fin'!D17 -> 0 | E111: ='1.Var.Fin'!E17 -> 0 | F111: ='1.Var.Fin'!F17 -> 0 | G111: =SUM(B111:F111) -> 0
A112: Emprunt à court terme (BFR, achat…) | B112: ='1.Var.Fin'!B11 -> 3698500.9 | C112: ='1.Var.Fin'!C11 -> 0 | D112: ='1.Var.Fin'!D11 -> 0 | E112: ='1.Var.Fin'!E11 -> 0 | F112: ='1.Var.Fin'!F11 -> 0 | G112: =SUM(B112:F112) -> 3698500.9
A113: Durée (mois) | B113: ='1.Var.Fin'!B14 -> 12 | C113: ='1.Var.Fin'!C14 -> 12 | D113: ='1.Var.Fin'!D14 -> 12 | E113: ='1.Var.Fin'!E14 -> 0 | F113: ='1.Var.Fin'!F14 -> 0 | G113: =AVERAGE(B113:F113) -> 7.2
A114: Taux | B114: ='1.Var.Fin'!B13 -> 0.14 | C114: ='1.Var.Fin'!C13 -> 0.14 | D114: ='1.Var.Fin'!D13 -> 0.14 | E114: ='1.Var.Fin'!E13 -> 0 | F114: ='1.Var.Fin'!F13 -> 0 | G114: =AVERAGE(B114:F114) -> 0.084
A115: Mensualité | B115: =IF(B112>1,IFERROR((B112*(B114/12)/((1-(1+(B114/12))^(-(B113))))),""),0) -> 332077.73 | C115: =IF(C112>1,IFERROR((C112*(C114/12)/((1-(1+(C114/12))^(-(C113))))),""),0) -> 0 | D115: =IF(D112>1,IFERROR((D112*(D114/12)/((1-(1+(D114/12))^(-(D113))))),""),0) -> 0 | E115: =IF(E112>1,IFERROR((E112*(E114/12)/((1-(1+(E114/12))^(-(E113))))),""),0) -> 0 | F115: =IF(F112>1,IFERROR((F112*(F114/12)/((1-(1+(F114/12))^(-(F113))))),""),0) -> 0 | G115: =AVERAGE(B115:F115) -> 66415.547
A116: Emprunt à long terme à solliciter | B116: ='1.Var.Fin'!B5 -> 76500 | C116: ='1.Var.Fin'!C5 -> 3698500.9 | D116: ='1.Var.Fin'!D5 -> 0 | E116: ='1.Var.Fin'!E5 -> 0 | F116: ='1.Var.Fin'!F5 -> 0 | G116: =SUM(B116:F116) -> 3775000.9
A117: Durée (année) | B117: =ROUNDUP('1.Var.Fin'!B8/12,0) -> 3 | C117: =ROUNDUP('1.Var.Fin'!C8/12,0) -> 3 | D117: =ROUNDUP('1.Var.Fin'!D8/12,0) -> 3 | E117: =ROUNDUP('1.Var.Fin'!E8/12,0) -> 0 | F117: =ROUNDUP('1.Var.Fin'!F8/12,0) -> 0 | G117: =AVERAGE(B117:F117) -> 1.8
A118: Taux | B118: ='1.Var.Fin'!B7 -> 0.09 | C118: ='1.Var.Fin'!C7 -> 0.11 | D118: ='1.Var.Fin'!D7 -> 0.1 | E118: ='1.Var.Fin'!E7 -> 0 | F118: ='1.Var.Fin'!F7 -> 0 | G118: =AVERAGE(B118:F118) -> 0.06
A119: Annuité | B119: =IF(B116>1,IFERROR((B116*(B118)/((1-(1+(B118))^(-(B117))))),""),0) -> 30221.689 | C119: =IF(C116>1,IFERROR((C116*(C118)/((1-(1+(C118))^(-(C117))))),""),0) -> 1513474.9 | D119: =IF(D116>1,IFERROR((D116*(D118)/((1-(1+(D118))^(-(D117))))),""),0) -> 0 | E119: =IF(E116>1,IFERROR((E116*(E118)/((1-(1+(E118))^(-(E117))))),""),0) -> 0 | F119: =IF(F116>1,IFERROR((F116*(F118)/((1-(1+(F118))^(-(F117))))),""),0) -> 0 | G119: =AVERAGE(B119:F119) -> 308739.32
A120: CA Estimé | B120: ='10.Vente'!P12 -> #VALUE! | C120: ='10.Vente'!Q12 -> #VALUE! | D120: ='10.Vente'!R12 -> #VALUE! | E120: ='10.Vente'!S12 -> 0 | F120: ='10.Vente'!T12 -> 0 | G120: =SUM(B120:F120) -> #VALUE!
A121: Profit | B121: ='16.CR'!C43 -> #VALUE! | C121: ='16.CR'!D43 -> #VALUE! | D121: ='16.CR'!E43 -> #VALUE! | E121: ='16.CR'!F43 -> 0 | F121: ='16.CR'!G43 -> 0 | G121: =SUM(B121:F121) -> #VALUE!
A122: Taux de profitabilité | B122: ='16.CR'!C44 -> #VALUE! | C122: ='16.CR'!D44 -> #VALUE! | D122: ='16.CR'!E44 -> #VALUE! | E122: ='16.CR'!F44 -> 0 | F122: ='16.CR'!G44 -> 0 | G122: =SUM(B122:F122) -> #VALUE!
A123: VAN sur 5 ans | G123: ='18.Van'!F11 -> #VALUE!
A124: TRI sur 5 ans | G124: ='18.Van'!F12 -> #VALUE!
A126: 1. DESCRIPTION DU PROJET
A127: A compléter.
A129: 2. MOYENS MATÉRIELS & HUMAINS
A130: 2.1 MOYENS MATÉRIELS
A132: Les investissements prévus dans cadre de ce projet sont les suivants :
A134: ='7.Bud.Inv.'!C3 -> Immobilisation | C134: Montant Un. | D134: Nb | E134: N+1 | F134: N+2 | G134: N+2
A135: ='7.Bud.Inv.'!C4 -> Aménagement et batiments | C135: ='5.Inv'!F4 -> {var_48} | D135: ='5.Inv'!E4 -> {var_31} | E135: ='7.Bud.Inv.'!Q4 -> #VALUE! | F135: ='7.Bud.Inv.'!S4 -> #VALUE! | G135: ='7.Bud.Inv.'!T4 -> 0
A136: ='7.Bud.Inv.'!C6 -> Aménagement entrepôt | C136: ='5.Inv'!F5 -> {var_49} | D136: ='5.Inv'!E5 -> {var_32} | E136: ='7.Bud.Inv.'!Q6 -> #VALUE! | F136: ='7.Bud.Inv.'!S6 -> #VALUE! | G136: ='7.Bud.Inv.'!T6 -> 0
A137: ='7.Bud.Inv.'!C7 -> Véhicules de liaison | C137: ='5.Inv'!F6 -> {var_50} | D137: ='5.Inv'!E6 -> {var_33} | E137: ='7.Bud.Inv.'!Q7 -> #VALUE! | F137: ='7.Bud.Inv.'!S7 -> #VALUE! | G137: ='7.Bud.Inv.'!T7 -> 0
A138: ='7.Bud.Inv.'!C8 -> Véhicules de bureau | C138: ='5.Inv'!F7 -> {var_51} | D138: ='5.Inv'!E7 -> {var_34} | E138: ='7.Bud.Inv.'!Q8 -> #VALUE! | F138: ='7.Bud.Inv.'!S8 -> #VALUE! | G138: ='7.Bud.Inv.'!T8 -> 0
A139: ='7.Bud.Inv.'!C9 -> Véhicule administratif | C139: ='5.Inv'!F8 -> {var_52} | D139: ='5.Inv'!E8 -> {var_35} | E139: ='7.Bud.Inv.'!Q9 -> #VALUE! | F139: ='7.Bud.Inv.'!S9 -> #VALUE! | G139: ='7.Bud.Inv.'!T9 -> 0
A140: ='7.Bud.Inv.'!C10 -> Bureau (Fauteuil + table) | C140: ='5.Inv'!F9 -> {var_53} | D140: ='5.Inv'!E9 -> {var_36} | E140: ='7.Bud.Inv.'!Q10 -> #VALUE! | F140: ='7.Bud.Inv.'!S10 -> #VALUE! | G140: ='7.Bud.Inv.'!T10 -> 0
A141: ='7.Bud.Inv.'!C11 -> Mobilier et matériel de bureau | C141: ='5.Inv'!F10 -> {var_54} | D141: ='5.Inv'!E10 -> {var_37} | E141: ='7.Bud.Inv.'!Q11 -> #VALUE! | F141: ='7.Bud.Inv.'!S11 -> #VALUE! | G141: ='7.Bud.Inv.'!T11 -> 0
A142: ='7.Bud.Inv.'!C12 -> Bureau (Fauteuil + table) | C142: ='5.Inv'!F11 -> {var_55} | D142: ='5.Inv'!E11 -> {var_38} | E142: ='7.Bud.Inv.'!Q12 -> #VALUE! | F142: ='7.Bud.Inv.'!S12 -> #VALUE! | G142: ='7.Bud.Inv.'!T12 -> 0
A143: ='7.Bud.Inv.'!C13 -> Ordinateur PRO | C143: ='5.Inv'!F12 -> {var_56} | D143: ='5.Inv'!E12 -> {var_39} | E143: ='7.Bud.Inv.'!Q13 -> #VALUE! | F143: ='7.Bud.Inv.'!S13 -> #VALUE! | G143: ='7.Bud.Inv.'!T13 -> 0
A144: ='7.Bud.Inv.'!C15 -> CANON EOS 80 D + objectif 18-135mm IS USM | C144: ='5.Inv'!F13 -> {var_57} | D144: ='5.Inv'!E13 -> {var_40} | E144: ='7.Bud.Inv.'!Q15 -> #VALUE! | F144: ='7.Bud.Inv.'!S15 -> #VALUE! | G144: ='7.Bud.Inv.'!T15 -> 0
A145: ='7.Bud.Inv.'!C16 -> Boîtier Canon EOS 5D Mark IV | C145: ='5.Inv'!F14 -> {var_58} | D145: ='5.Inv'!E14 -> {var_41} | E145: ='7.Bud.Inv.'!Q16 -> #VALUE! | F145: ='7.Bud.Inv.'!S16 -> #VALUE! | G145: ='7.Bud.Inv.'!T16 -> 0
A146: ='7.Bud.Inv.'!C17 -> Photocopieuse + Imprimante | C146: ='5.Inv'!F16 -> {var_60} | D146: ='5.Inv'!E16 -> {var_43} | E146: ='7.Bud.Inv.'!Q17 -> #VALUE! | F146: ='7.Bud.Inv.'!S17 -> #VALUE! | G146: ='7.Bud.Inv.'!T17 -> 0
A147: ='7.Bud.Inv.'!C18 -> Caution et avance loyer | C147: ='5.Inv'!F17 -> {var_61} | D147: ='5.Inv'!E17 -> {var_44} | E147: ='7.Bud.Inv.'!Q18 -> #VALUE! | F147: ='7.Bud.Inv.'!S18 -> #VALUE! | G147: ='7.Bud.Inv.'!T18 -> 0
A148: ='7.Bud.Inv.'!C19 -> Branchement Téléphone et internet | C148: ='5.Inv'!F18 -> {var_62} | D148: ='5.Inv'!E18 -> {var_45} | E148: ='7.Bud.Inv.'!Q19 -> #VALUE! | F148: ='7.Bud.Inv.'!S19 -> #VALUE! | G148: ='7.Bud.Inv.'!T19 -> 0
A149: ='7.Bud.Inv.'!C20 -> Branchement CIE et SODECI | C149: ='5.Inv'!F19 -> {var_63} | D149: ='5.Inv'!E19 -> {var_46} | E149: ='7.Bud.Inv.'!Q20 -> #VALUE! | F149: ='7.Bud.Inv.'!S20 -> #VALUE! | G149: ='7.Bud.Inv.'!T20 -> 0
A150: ='7.Bud.Inv.'!C21 -> Bail foncier | C150: ='5.Inv'!F20 -> {var_64} | D150: ='5.Inv'!E20 -> {var_47} | E150: ='7.Bud.Inv.'!Q21 -> #VALUE! | F150: ='7.Bud.Inv.'!S21 -> #VALUE! | G150: ='7.Bud.Inv.'!T21 -> 0
A152: 2.2 MOYENS HUMAINS
A153: Les ressources humaines necessaires à la réalisation du projet seront composée de :
A154: Indiquer tous les types de ressources humaines, leur postes, leur catégorie socio professionnel, leur salaire
A157: 3. PROGRAMME DE RÉALISATION
A158: A compléter.
A160: 4. DESCRIPTION DU MARCHE
A161: A compléter.
A165: 5. ÉTUDE FINANCIÈRE ET PLAN DE FINANCEMENT
A167: 5.1 Fonds de Roulement
A169: Rubrique | E169: Nb mois | F169: Montant Un. | G169: Total
A171: Chiffre d'affaires | E171: =E173 -> 3 mois
A173: Dépenses d'exploitation | E173: =_xlfn.CONCAT(E174," mois") -> 3 mois | F173: =SUM(F174:F180) -> 6200 | G173: =SUM(G174:G180) -> 18600
A174: ='21.BFR'!B4 -> Achat de Tenue de luxe Homme | E174: ='21.BFR'!E4 -> 3 | F174: ='21.BFR'!D4 -> 6000 | G174: ='21.BFR'!G4 -> 18000
A175: ='21.BFR'!B9 -> 0 | E175: ='21.BFR'!E9 -> 3 | F175: ='21.BFR'!D9 -> 0 | G175: ='21.BFR'!G9 -> 0
A176: ='21.BFR'!B10 -> 0 | E176: ='21.BFR'!E10 -> 3 | F176: ='21.BFR'!D10 -> 0 | G176: ='21.BFR'!G10 -> 0
A177: ='21.BFR'!B11 -> 0 | E177: ='21.BFR'!E11 -> 3 | F177: ='21.BFR'!D11 -> 0 | G177: ='21.BFR'!G11 -> 0
A178: ='21.BFR'!B12 -> 0 | E178: ='21.BFR'!E12 -> 3 | F178: ='21.BFR'!D12 -> 0 | G178: ='21.BFR'!G12 -> 0
A179: ='21.BFR'!B13 -> 0 | E179: ='21.BFR'!E13 -> 3 | F179: ='21.BFR'!D13 -> 0 | G179: ='21.BFR'!G13 -> 0
A180: ='21.BFR'!B14 -> Logistique Tenue de luxe Homme | E180: ='21.BFR'!E14 -> 3 | F180: ='21.BFR'!D14 -> 200 | G180: ='21.BFR'!G14 -> 600
A181: ='21.BFR'!B26 -> 0 | E181: ='21.BFR'!E26 -> 3 | F181: ='21.BFR'!D26 -> 0 | G181: ='21.BFR'!G26 -> 0
A182: ='21.BFR'!B27 -> Salaire personnel | E182: ='21.BFR'!E27 -> 3 | F182: ='21.BFR'!D27 -> 0.22 | G182: ='21.BFR'!G27 -> 0.66
A183: ='21.BFR'!B28 -> Timbre | E183: ='21.BFR'!E28 -> 3 | F183: ='21.BFR'!D28 -> 0.0048 | G183: ='21.BFR'!G28 -> 0.0144
A184: ='21.BFR'!B29 -> BIC | E184: ='21.BFR'!E29 -> 3 | F184: ='21.BFR'!D29 -> 0.0307 | G184: ='21.BFR'!G29 -> 0.0921
A185: ='21.BFR'!B30 -> Sponsoring page réseaux sociaux | E185: ='21.BFR'!E30 -> 1 | F185: ='21.BFR'!D30 -> 1900000 | G185: ='21.BFR'!G30 -> 1900000
A186: ='21.BFR'!B31 -> Frais administration | E186: ='21.BFR'!E31 -> 3 | F186: ='21.BFR'!D31 -> 25000 | G186: ='21.BFR'!G31 -> 75000
A187: ='21.BFR'!B32 -> Eau | E187: ='21.BFR'!E32 -> 3 | F187: ='21.BFR'!D32 -> 82500 | G187: ='21.BFR'!G32 -> 247500
A188: ='21.BFR'!B33 -> Carburant | E188: ='21.BFR'!E33 -> 3 | F188: ='21.BFR'!D33 -> 50000 | G188: ='21.BFR'!G33 -> 150000
...

Sheet LiensFeuilles
A1: Liens entre les feuilles de calcul

Sheet 1.Var.Fin
A1: FACTEURS DE VARIATION AMORTISSEMENT FINANCIER
A2: Variables financières
B3: Année 1 | C3: Année 2 | D3: Année 3
A4: Emprunt à long terme
A5: Montant | B5: =SUMIF('21.BFR'!$F$3:$F$41,'1.Var.Fin'!B6,'21.BFR'!$G$3:$G$41)+SUMIF('7.Bud.Inv.'!$D$3:$D$22,'1.Var.Fin'!B6,'7.Bud.Inv.'!$Q$3:$Q$22) -> 76500 | C5: =SUMIF('21.BFR'!$F$3:$F$41,'1.Var.Fin'!C6,'21.BFR'!$G$3:$G$41)+SUMIF('7.Bud.Inv.'!$D$3:$D$22,'1.Var.Fin'!C6,'7.Bud.Inv.'!$Q$3:$Q$22) -> 3698500.9 | D5: =SUMIF('21.BFR'!$F$3:$F$41,'1.Var.Fin'!D6,'21.BFR'!$G$3:$G$41)+SUMIF('7.Bud.Inv.'!$D$3:$D$22,'1.Var.Fin'!D6,'7.Bud.Inv.'!$Q$3:$Q$22) -> 0
A6: Code financement | B6: EMP1 | C6: EMP2 | D6: EMP3
A7: Taux d'intérêt | B7: 0.09 | C7: 0.11 | D7: 0.1
A8: Nb de mois | B8: 36 | C8: 36 | D8: 36
A9: TOB | B9: 0.1 | C9: 1.1 | D9: 2.1
A10: Emprunt à court terme
A11: Montant | B11: =SUMIF('21.BFR'!$F$3:$F$41,'1.Var.Fin'!B12,'21.BFR'!$G$3:$G$41)+SUMIF('7.Bud.Inv.'!$D$3:$D$22,'1.Var.Fin'!B12,'7.Bud.Inv.'!$Q$3:$Q$22) -> 3698500.9 | C11: =SUMIF('21.BFR'!$F$3:$F$41,'1.Var.Fin'!C12,'21.BFR'!$G$3:$G$41)+SUMIF('7.Bud.Inv.'!$D$3:$D$22,'1.Var.Fin'!C12,'7.Bud.Inv.'!$Q$3:$Q$22) -> 0 | D11: =SUMIF('21.BFR'!$F$3:$F$41,'1.Var.Fin'!D12,'21.BFR'!$G$3:$G$41)+SUMIF('7.Bud.Inv.'!$D$3:$D$22,'1.Var.Fin'!D12,'7.Bud.Inv.'!$Q$3:$Q$22) -> 0
A12: Code financement | B12: EMP2 | C12: EMP3 | D12: EMP4
A13: Taux d'intérêt | B13: 0.14 | C13: 0.14 | D13: 0.14
A14: Nb de mois | B14: 12 | C14: 12 | D14: 12
A15: TOB | B15: 0.1 | C15: 0.1 | D15: 0.1
A16: Apport initial (Compte courant)
A17: Montant | B17: =SUMIF('21.BFR'!$F$3:$F$41,'1.Var.Fin'!B18,'21.BFR'!$G$3:$G$41)+SUMIF('7.Bud.Inv.'!$D$3:$D$22,'1.Var.Fin'!B18,'7.Bud.Inv.'!$Q$3:$Q$22) -> 0 | C17: =SUMIF('21.BFR'!$F$3:$F$41,'1.Var.Fin'!C18,'21.BFR'!$G$3:$G$41)+SUMIF('7.Bud.Inv.'!$D$3:$D$22,'1.Var.Fin'!C18,'7.Bud.Inv.'!$Q$3:$Q$22) -> 0 | D17: =SUMIF('21.BFR'!$F$3:$F$41,'1.Var.Fin'!D18,'21.BFR'!$G$3:$G$41)+SUMIF('7.Bud.Inv.'!$D$3:$D$22,'1.Var.Fin'!D18,'7.Bud.Inv.'!$Q$3:$Q$22) -> 0
A18: Code financement | B18: EMP3 | C18: EMP3 | D18: EMP3
A19: Taux d'intérêt | B19: 0 | C19: 0 | D19: 0
A20: Nb de mois | B20: 36 | C20: 36 | D20: 36
A21: TOB | B21: 0.1 | C21: 0.1 | D21: 0.1

Sheet 2.Cal.Amo.CT
A1: TABLEAU D'AMORTISSEMENT EMPRUNT A COURT TERME
A3: Année 1
A4: Emprunt | B4: ='1.Var.Fin'!B11 -> 3698500.9
A5: Taux Annuel | B5: =+'1.Var.Fin'!B13 -> 0.14
A6: Taux effectif mensuel | B6: =B5/12 -> 0.011666667
A7: TOB | B7: ='1.Var.Fin'!B9 -> 0.1 | E7: Montant (FCFA)
A8: Durée | B8: ='1.Var.Fin'!B14 -> 12 | C8: Mois
A9: Mois | B9: Capital restant | C9: INTERET | D9: TOB | E9: Amortissement | F9: Mensualité | G9: ANNEE
A10: 1 | B10: =B4 -> 3698500.9 | C10: =B10*$B$6 -> 43149.177 | D10: =C10*$B$7 -> 4314.9177 | E10: =IFERROR(F10-C10,"") -> 288928.56 | F10: =IF(B10>1,IFERROR(($B$4*$B$6/((1-(1+$B$6)^(-$B$8)))),""),0) -> 332077.73 | G10: N
A11: 2 | B11: =IFERROR(B10-E10, "") -> 3409572.3 | C11: =B11*$B$6 -> 39778.344 | D11: =C11*$B$7 -> 3977.8344 | E11: =IFERROR(F11-C11,"") -> 292299.39 | F11: =IF(B11>1,IFERROR(($B$4*$B$6/((1-(1+$B$6)^(-$B$8)))),""),0) -> 332077.73 | G11: N
A12: 3 | B12: =IFERROR(B11-E11, "") -> 3117272.9 | C12: =B12*$B$6 -> 36368.184 | D12: =C12*$B$7 -> 3636.8184 | E12: =IFERROR(F12-C12,"") -> 295709.55 | F12: =IF(B12>1,IFERROR(($B$4*$B$6/((1-(1+$B$6)^(-$B$8)))),""),0) -> 332077.73 | G12: N
A13: 4 | B13: =IFERROR(B12-E12, "") -> 2821563.4 | C13: =B13*$B$6 -> 32918.239 | D13: =C13*$B$7 -> 3291.8239 | E13: =IFERROR(F13-C13,"") -> 299159.49 | F13: =IF(B13>1,IFERROR(($B$4*$B$6/((1-(1+$B$6)^(-$B$8)))),""),0) -> 332077.73 | G13: N
A14: 5 | B14: =IFERROR(B13-E13, "") -> 2522403.9 | C14: =B14*$B$6 -> 29428.045 | D14: =C14*$B$7 -> 2942.8045 | E14: =IFERROR(F14-C14,"") -> 302649.69 | F14: =IF(B14>1,IFERROR(($B$4*$B$6/((1-(1+$B$6)^(-$B$8)))),""),0) -> 332077.73 | G14: N
A15: 6 | B15: =IFERROR(B14-E14, "") -> 2219754.2 | C15: =B15*$B$6 -> 25897.132 | D15: =C15*$B$7 -> 2589.7132 | E15: =IFERROR(F15-C15,"") -> 306180.6 | F15: =IF(B15>1,IFERROR(($B$4*$B$6/((1-(1+$B$6)^(-$B$8)))),""),0) -> 332077.73 | G15: N
A16: 7 | B16: =IFERROR(B15-E15, "") -> 1913573.6 | C16: =B16*$B$6 -> 22325.025 | D16: =C16*$B$7 -> 2232.5025 | E16: =IFERROR(F16-C16,"") -> 309752.71 | F16: =IF(B16>1,IFERROR(($B$4*$B$6/((1-(1+$B$6)^(-$B$8)))),""),0) -> 332077.73 | G16: N
A17: 8 | B17: =IFERROR(B16-E16, "") -> 1603820.9 | C17: =B17*$B$6 -> 18711.244 | D17: =C17*$B$7 -> 1871.1244 | E17: =IFERROR(F17-C17,"") -> 313366.49 | F17: =IF(B17>1,IFERROR(($B$4*$B$6/((1-(1+$B$6)^(-$B$8)))),""),0) -> 332077.73 | G17: N
A18: 9 | B18: =IFERROR(B17-E17, "") -> 1290454.4 | C18: =B18*$B$6 -> 15055.301 | D18: =C18*$B$7 -> 1505.5301 | E18: =IFERROR(F18-C18,"") -> 317022.43 | F18: =IF(B18>1,IFERROR(($B$4*$B$6/((1-(1+$B$6)^(-$B$8)))),""),0) -> 332077.73 | G18: N
A19: 10 | B19: =IFERROR(B18-E18, "") -> 973431.97 | C19: =B19*$B$6 -> 11356.706 | D19: =C19*$B$7 -> 1135.6706 | E19: =IFERROR(F19-C19,"") -> 320721.03 | F19: =IF(B19>1,IFERROR(($B$4*$B$6/((1-(1+$B$6)^(-$B$8)))),""),0) -> 332077.73 | G19: N
A20: 11 | B20: =IFERROR(B19-E19, "") -> 652710.94 | C20: =B20*$B$6 -> 7614.961 | D20: =C20*$B$7 -> 761.4961 | E20: =IFERROR(F20-C20,"") -> 324462.77 | F20: =IF(B20>1,IFERROR(($B$4*$B$6/((1-(1+$B$6)^(-$B$8)))),""),0) -> 332077.73 | G20: N
A21: 12 | B21: =IFERROR(B20-E20, "") -> 328248.17 | C21: =B21*$B$6 -> 3829.562 | D21: =C21*$B$7 -> 382.9562 | E21: =IFERROR(F21-C21,"") -> 328248.17 | F21: =IF(B21>1,IFERROR(($B$4*$B$6/((1-(1+$B$6)^(-$B$8)))),""),0) -> 332077.73 | G21: N
A22: Année 2
A23: Emprunt | B23: ='1.Var.Fin'!C11 -> 0
A24: Taux Annuel | B24: =+'1.Var.Fin'!C13 -> 0.14
A25: Taux effectif mensuel | B25: =B24/12 -> 0.011666667
A26: TOB | B26: ='1.Var.Fin'!C9 -> 1.1 | E26: Montant (FCFA)
A27: Durée | B27: ='1.Var.Fin'!C14 -> 12 | C27: Mois
A28: Mois | B28: Capital restant | C28: INTERET | D28: TOB | E28: Amortissement | F28: Mensualité | G28: ANNEE
A29: 1 | B29: =H23 -> 0 | C29: =B29*$B$6 -> 0 | D29: =C29*$B$7 -> 0 | E29: =IFERROR(F29-C29,"") -> 0 | F29: =IF(B29>1,IFERROR(($B$4*$B$6/((1-(1+$B$6)^(-$B$8)))),""),0) -> 0 | G29: N+1
A30: 2 | B30: =IFERROR(B29-E29, "") -> 0 | C30: =B30*$B$6 -> 0 | D30: =C30*$B$7 -> 0 | E30: =IFERROR(F30-C30,"") -> 0 | F30: =IF(B30>1,IFERROR(($B$4*$B$6/((1-(1+$B$6)^(-$B$8)))),""),0) -> 0 | G30: N+1
A31: 3 | B31: =IFERROR(B30-E30, "") -> 0 | C31: =B31*$B$6 -> 0 | D31: =C31*$B$7 -> 0 | E31: =IFERROR(F31-C31,"") -> 0 | F31: =IF(B31>1,IFERROR(($B$4*$B$6/((1-(1+$B$6)^(-$B$8)))),""),0) -> 0 | G31: N+1
A32: 4 | B32: =IFERROR(B31-E31, "") -> 0 | C32: =B32*$B$6 -> 0 | D32: =C32*$B$7 -> 0 | E32: =IFERROR(F32-C32,"") -> 0 | F32: =IF(B32>1,IFERROR(($B$4*$B$6/((1-(1+$B$6)^(-$B$8)))),""),0) -> 0 | G32: N+1
A33: 5 | B33: =IFERROR(B32-E32, "") -> 0 | C33: =B33*$B$6 -> 0 | D33: =C33*$B$7 -> 0 | E33: =IFERROR(F33-C33,"") -> 0 | F33: =IF(B33>1,IFERROR(($B$4*$B$6/((1-(1+$B$6)^(-$B$8)))),""),0) -> 0 | G33: N+1
A34: 6 | B34: =IFERROR(B33-E33, "") -> 0 | C34: =B34*$B$6 -> 0 | D34: =C34*$B$7 -> 0 | E34: =IFERROR(F34-C34,"") -> 0 | F34: =IF(B34>1,IFERROR(($B$4*$B$6/((1-(1+$B$6)^(-$B$8)))),""),0) -> 0 | G34: N+1
A35: 7 | B35: =IFERROR(B34-E34, "") -> 0 | C35: =B35*$B$6 -> 0 | D35: =C35*$B$7 -> 0 | E35: =IFERROR(F35-C35,"") -> 0 | F35: =IF(B35>1,IFERROR(($B$4*$B$6/((1-(1+$B$6)^(-$B$8)))),""),0) -> 0 | G35: N+1
A36: 8 | B36: =IFERROR(B35-E35, "") -> 0 | C36: =B36*$B$6 -> 0 | D36: =C36*$B$7 -> 0 | E36: =IFERROR(F36-C36,"") -> 0 | F36: =IF(B36>1,IFERROR(($B$4*$B$6/((1-(1+$B$6)^(-$B$8)))),""),0) -> 0 | G36: N+1
A37: 9 | B37: =IFERROR(B36-E36, "") -> 0 | C37: =B37*$B$6 -> 0 | D37: =C37*$B$7 -> 0 | E37: =IFERROR(F37-C37,"") -> 0 | F37: =IF(B37>1,IFERROR(($B$4*$B$6/((1-(1+$B$6)^(-$B$8)))),""),0) -> 0 | G37: N+1
A38: 10 | B38: =IFERROR(B37-E37, "") -> 0 | C38: =B38*$B$6 -> 0 | D38: =C38*$B$7 -> 0 | E38: =IFERROR(F38-C38,"") -> 0 | F38: =IF(B38>1,IFERROR(($B$4*$B$6/((1-(1+$B$6)^(-$B$8)))),""),0) -> 0 | G38: N+1
A39: 11 | B39: =IFERROR(B38-E38, "") -> 0 | C39: =B39*$B$6 -> 0 | D39: =C39*$B$7 -> 0 | E39: =IFERROR(F39-C39,"") -> 0 | F39: =IF(B39>1,IFERROR(($B$4*$B$6/((1-(1+$B$6)^(-$B$8)))),""),0) -> 0 | G39: N+1
A40: 12 | B40: =IFERROR(B39-E39, "") -> 0 | C40: =B40*$B$6 -> 0 | D40: =C40*$B$7 -> 0 | E40: =IFERROR(F40-C40,"") -> 0 | F40: =IF(B40>1,IFERROR(($B$4*$B$6/((1-(1+$B$6)^(-$B$8)))),""),0) -> 0 | G40: N+1
A41: Année 3
A42: Emprunt | B42: ='1.Var.Fin'!D11 -> 0
A43: Taux Annuel | B43: =+'1.Var.Fin'!D13 -> 0.14
A44: Taux effectif mensuel | B44: =B43/12 -> 0.011666667
A45: TOB | B45: ='1.Var.Fin'!D9 -> 2.1 | E45: Montant (FCFA)
A46: Durée | B46: ='1.Var.Fin'!D14 -> 12 | C46: Mois
A47: Mois | B47: Capital restant | C47: INTERET | D47: TOB | E47: Amortissement | F47: Mensualité | G47: ANNEE
A48: 1 | B48: =H42 -> 0 | C48: =B48*$B$6 -> 0 | D48: =C48*$B$7 -> 0 | E48: =IFERROR(F48-C48,"") -> 0 | F48: =IF(B48>1,IFERROR(($B$4*$B$6/((1-(1+$B$6)^(-$B$8)))),""),0) -> 0 | G48: N+2
A49: 2 | B49: =IFERROR(B48-E48, "") -> 0 | C49: =B49*$B$6 -> 0 | D49: =C49*$B$7 -> 0 | E49: =IFERROR(F49-C49,"") -> 0 | F49: =IF(B49>1,IFERROR(($B$4*$B$6/((1-(1+$B$6)^(-$B$8)))),""),0) -> 0 | G49: N+2
A50: 3 | B50: =IFERROR(B49-E49, "") -> 0 | C50: =B50*$B$6 -> 0 | D50: =C50*$B$7 -> 0 | E50: =IFERROR(F50-C50,"") -> 0 | F50: =IF(B50>1,IFERROR(($B$4*$B$6/((1-(1+$B$6)^(-$B$8)))),""),0) -> 0 | G50: N+2
A51: 4 | B51: =IFERROR(B50-E50, "") -> 0 | C51: =B51*$B$6 -> 0 | D51: =C51*$B$7 -> 0 | E51: =IFERROR(F51-C51,"") -> 0 | F51: =IF(B51>1,IFERROR(($B$4*$B$6/((1-(1+$B$6)^(-$B$8)))),""),0) -> 0 | G51: N+2
A52: 5 | B52: =IFERROR(B51-E51, "") -> 0 | C52: =B52*$B$6 -> 0 | D52: =C52*$B$7 -> 0 | E52: =IFERROR(F52-C52,"") -> 0 | F52: =IF(B52>1,IFERROR(($B$4*$B$6/((1-(1+$B$6)^(-$B$8)))),""),0) -> 0 | G52: N+2
A53: 6 | B53: =IFERROR(B52-E52, "") -> 0 | C53: =B53*$B$6 -> 0 | D53: =C53*$B$7 -> 0 | E53: =IFERROR(F53-C53,"") -> 0 | F53: =IF(B53>1,IFERROR(($B$4*$B$6/((1-(1+$B$6)^(-$B$8)))),""),0) -> 0 | G53: N+2
A54: 7 | B54: =IFERROR(B53-E53, "") -> 0 | C54: =B54*$B$6 -> 0 | D54: =C54*$B$7 -> 0 | E54: =IFERROR(F54-C54,"") -> 0 | F54: =IF(B54>1,IFERROR(($B$4*$B$6/((1-(1+$B$6)^(-$B$8)))),""),0) -> 0 | G54: N+2
A55: 8 | B55: =IFERROR(B54-E54, "") -> 0 | C55: =B55*$B$6 -> 0 | D55: =C55*$B$7 -> 0 | E55: =IFERROR(F55-C55,"") -> 0 | F55: =IF(B55>1,IFERROR(($B$4*$B$6/((1-(1+$B$6)^(-$B$8)))),""),0) -> 0 | G55: N+2
A56: 9 | B56: =IFERROR(B55-E55, "") -> 0 | C56: =B56*$B$6 -> 0 | D56: =C56*$B$7 -> 0 | E56: =IFERROR(F56-C56,"") -> 0 | F56: =IF(B56>1,IFERROR(($B$4*$B$6/((1-(1+$B$6)^(-$B$8)))),""),0) -> 0 | G56: N+2
A57: 10 | B57: =IFERROR(B56-E56, "") -> 0 | C57: =B57*$B$6 -> 0 | D57: =C57*$B$7 -> 0 | E57: =IFERROR(F57-C57,"") -> 0 | F57: =IF(B57>1,IFERROR(($B$4*$B$6/((1-(1+$B$6)^(-$B$8)))),""),0) -> 0 | G57: N+2
A58: 11 | B58: =IFERROR(B57-E57, "") -> 0 | C58: =B58*$B$6 -> 0 | D58: =C58*$B$7 -> 0 | E58: =IFERROR(F58-C58,"") -> 0 | F58: =IF(B58>1,IFERROR(($B$4*$B$6/((1-(1+$B$6)^(-$B$8)))),""),0) -> 0 | G58: N+2
A59: 12 | B59: =IFERROR(B58-E58, "") -> 0 | C59: =B59*$B$6 -> 0 | D59: =C59*$B$7 -> 0 | E59: =IFERROR(F59-C59,"") -> 0 | F59: =IF(B59>1,IFERROR(($B$4*$B$6/((1-(1+$B$6)^(-$B$8)))),""),0) -> 0 | G59: N+2

Sheet 3.Cal.Amo.LT
A1: TABLEAU D'AMORTISSEMENT EMPRUNT A COURT TERME
A3: Année 1
A4: Emprunt | B4: ='1.Var.Fin'!B5 -> 76500 | E4: Montant (FCFA)
A5: Taux Annuel | B5: ='1.Var.Fin'!B7 -> 0.09
A6: TOB | B6: ='1.Var.Fin'!B15 -> 0.1
A7: DUREE | B7: =ROUNDUP('1.Var.Fin'!B8/12,0) -> 3 | C7: ANS
A8: Année | B8: CAPITAL RESTANT DU | C8: INTERET | D8: TOB | E8: Amortissement | F8: Annuité
A9: N | B9: =B4 -> 76500 | C9: =B9*$B$5 -> 6885 | D9: =B9*$B$6 -> 7650 | E9: =F9-C9 -> 23336.689 | F9: =IF(B9>=1,IFERROR($B$4*$B$5/((1-(1+$B$5)^(-$B$7))),0),0) -> 30221.689
A10: N+1 | B10: =B9-E9 -> 53163.311 | C10: =B10*$B$5 -> 4784.698 | D10: =B10*$B$6 -> 5316.3311 | E10: =F10-C10 -> 25436.991 | F10: =IF(B10>=1,IFERROR($B$4*$B$5/((1-(1+$B$5)^(-$B$7))),0),0) -> 30221.689
A11: N+2 | B11: =B10-E10 -> 27726.32 | C11: =B11*$B$5 -> 2495.3688 | D11: =B11*$B$6 -> 2772.632 | E11: =F11-C11 -> 27726.32 | F11: =IF(B11>=1,IFERROR($B$4*$B$5/((1-(1+$B$5)^(-$B$7))),0),0) -> 30221.689
A12: N+3 | B12: =B11-E11 -> 3.2741809e-11 | C12: =B12*$B$5 -> 2.9467628e-12 | D12: =B12*$B$6 -> 3.2741809e-12 | E12: =F12-C12 -> -2.9467628e-12 | F12: =IF(B12>=1,IFERROR($B$4*$B$5/((1-(1+$B$5)^(-$B$7))),0),0) -> 0
A13: N+4 | B13: =B12-E12 -> 3.5688572e-11 | C13: =B13*$B$5 -> 3.2119715e-12 | D13: =B13*$B$6 -> 3.5688572e-12 | E13: =F13-C13 -> -3.2119715e-12 | F13: =IF(B13>=1,IFERROR($B$4*$B$5/((1-(1+$B$5)^(-$B$7))),0),0) -> 0
A14: Année 2
A15: Emprunt | B15: ='1.Var.Fin'!C5 -> 3698500.9 | E15: Montant (FCFA)
A16: Taux Annuel | B16: ='1.Var.Fin'!C7 -> 0.11
A17: TOB | B17: ='1.Var.Fin'!C15 -> 0.1
A18: DUREE | B18: =ROUNDUP('1.Var.Fin'!C8/12,0) -> 3 | C18: ANS
A19: Année | B19: CAPITAL RESTANT DU | C19: INTERET | D19: TOB | E19: Amortissement | F19: Annuité
A20: N+1 | B20: =H15 -> 0 | C20: =B20*$B$5 -> 0 | D20: =B20*$B$6 -> 0 | E20: =F20-C20 -> 0 | F20: =IF(B20>=1,IFERROR($B$4*$B$5/((1-(1+$B$5)^(-$B$7))),0),0) -> 0
A21: N+2 | B21: =B20-E20 -> 0 | C21: =B21*$B$5 -> 0 | D21: =B21*$B$6 -> 0 | E21: =F21-C21 -> 0 | F21: =IF(B21>=1,IFERROR($B$4*$B$5/((1-(1+$B$5)^(-$B$7))),0),0) -> 0
A22: N+3 | B22: =B21-E21 -> 0 | C22: =B22*$B$5 -> 0 | D22: =B22*$B$6 -> 0 | E22: =F22-C22 -> 0 | F22: =IF(B22>=1,IFERROR($B$4*$B$5/((1-(1+$B$5)^(-$B$7))),0),0) -> 0
A23: N+4 | B23: =B22-E22 -> 0 | C23: =B23*$B$5 -> 0 | D23: =B23*$B$6 -> 0 | E23: =F23-C23 -> 0 | F23: =IF(B23>=1,IFERROR($B$4*$B$5/((1-(1+$B$5)^(-$B$7))),0),0) -> 0
A24: N+5 | B24: =B23-E23 -> 0 | C24: =B24*$B$5 -> 0 | D24: =B24*$B$6 -> 0 | E24: =F24-C24 -> 0 | F24: =IF(B24>=1,IFERROR($B$4*$B$5/((1-(1+$B$5)^(-$B$7))),0),0) -> 0
A25: Année 3
A26: Emprunt | B26: ='1.Var.Fin'!D5 -> 0 | E26: Montant (FCFA)
A27: Taux Annuel | B27: ='1.Var.Fin'!D7 -> 0.1
A28: TOB | B28: ='1.Var.Fin'!D15 -> 0.1
A29: DUREE | B29: =ROUNDUP('1.Var.Fin'!D8/12,0) -> 3 | C29: ANS
A30: Année | B30: CAPITAL RESTANT DU | C30: INTERET | D30: TOB | E30: Amortissement | F30: Annuité
A31: N+2 | B31: =H26 -> 0 | C31: =B31*$B$5 -> 0 | D31: =B31*$B$6 -> 0 | E31: =F31-C31 -> 0 | F31: =IF(B31>=1,IFERROR($B$4*$B$5/((1-(1+$B$5)^(-$B$7))),0),0) -> 0
A32: N+3 | B32: =B31-E31 -> 0 | C32: =B32*$B$5 -> 0 | D32: =B32*$B$6 -> 0 | E32: =F32-C32 -> 0 | F32: =IF(B32>=1,IFERROR($B$4*$B$5/((1-(1+$B$5)^(-$B$7))),0),0) -> 0
A33: N+4 | B33: =B32-E32 -> 0 | C33: =B33*$B$5 -> 0 | D33: =B33*$B$6 -> 0 | E33: =F33-C33 -> 0 | F33: =IF(B33>=1,IFERROR($B$4*$B$5/((1-(1+$B$5)^(-$B$7))),0),0) -> 0
A34: N+5 | B34: =B33-E33 -> 0 | C34: =B34*$B$5 -> 0 | D34: =B34*$B$6 -> 0 | E34: =F34-C34 -> 0 | F34: =IF(B34>=1,IFERROR($B$4*$B$5/((1-(1+$B$5)^(-$B$7))),0),0) -> 0
A35: N+6 | B35: =B34-E34 -> 0 | C35: =B35*$B$5 -> 0 | D35: =B35*$B$6 -> 0 | E35: =F35-C35 -> 0 | F35: =IF(B35>=1,IFERROR($B$4*$B$5/((1-(1+$B$5)^(-$B$7))),0),0) -> 0

Sheet 4.Cal.Amo.AI
A1: TABLEAU D'AMORTISSEMENT APPORT INITIAL
A3: Année 1
A4: Emprunt | B4: ='1.Var.Fin'!B17 -> 0 | E4: Montant (FCFA)
A5: Taux Annuel | B5: ='1.Var.Fin'!B19 -> 0
A6: TOB | B6: ='1.Var.Fin'!B21 -> 0.1
A7: DUREE | B7: =ROUNDUP('1.Var.Fin'!B8/12,0) -> 3 | C7: ANS
A8: Année | B8: CAPITAL RESTANT DU | C8: INTERET | D8: TOB | E8: Amortissement | F8: Annuité
A9: N | B9: =B4 -> 0 | C9: =B9*$B$5 -> 0 | D9: =B9*$B$6 -> 0 | E9: =F9-C9 -> 0 | F9: =IF(B9>=1,IFERROR($B$4*$B$5/((1-(1+$B$5)^(-$B$7))),0),0) -> 0
A10: N+1 | B10: =B9-E9 -> 0 | C10: =B10*$B$5 -> 0 | D10: =B10*$B$6 -> 0 | E10: =F10-C10 -> 0 | F10: =IF(B10>=1,IFERROR($B$4*$B$5/((1-(1+$B$5)^(-$B$7))),0),0) -> 0
A11: N+2 | B11: =B10-E10 -> 0 | C11: =B11*$B$5 -> 0 | D11: =B11*$B$6 -> 0 | E11: =F11-C11 -> 0 | F11: =IF(B11>=1,IFERROR($B$4*$B$5/((1-(1+$B$5)^(-$B$7))),0),0) -> 0
A12: N+3 | B12: =B11-E11 -> 0 | C12: =B12*$B$5 -> 0 | D12: =B12*$B$6 -> 0 | E12: =F12-C12 -> 0 | F12: =IF(B12>=1,IFERROR($B$4*$B$5/((1-(1+$B$5)^(-$B$7))),0),0) -> 0
A13: N+4 | B13: =B12-E12 -> 0 | C13: =B13*$B$5 -> 0 | D13: =B13*$B$6 -> 0 | E13: =F13-C13 -> 0 | F13: =IF(B13>=1,IFERROR($B$4*$B$5/((1-(1+$B$5)^(-$B$7))),0),0) -> 0
A14: Année 2
A15: Emprunt | B15: ='1.Var.Fin'!C17 -> 0 | E15: Montant (FCFA)
A16: Taux Annuel | B16: ='1.Var.Fin'!C19 -> 0
A17: TOB | B17: ='1.Var.Fin'!C21 -> 0.1
A18: DUREE | B18: =ROUNDUP('1.Var.Fin'!C8/12,0) -> 3 | C18: ANS
A19: Année | B19: CAPITAL RESTANT DU | C19: INTERET | D19: TOB | E19: Amortissement | F19: Annuité
A20: N | B20: =H15 -> 0 | C20: =B20*$B$5 -> 0 | D20: =B20*$B$6 -> 0 | E20: =F20-C20 -> 0 | F20: =IF(B20>=1,IFERROR($B$4*$B$5/((1-(1+$B$5)^(-$B$7))),0),0) -> 0
A21: N+1 | B21: =B20-E20 -> 0 | C21: =B21*$B$5 -> 0 | D21: =B21*$B$6 -> 0 | E21: =F21-C21 -> 0 | F21: =IF(B21>=1,IFERROR($B$4*$B$5/((1-(1+$B$5)^(-$B$7))),0),0) -> 0
A22: N+2 | B22: =B21-E21 -> 0 | C22: =B22*$B$5 -> 0 | D22: =B22*$B$6 -> 0 | E22: =F22-C22 -> 0 | F22: =IF(B22>=1,IFERROR($B$4*$B$5/((1-(1+$B$5)^(-$B$7))),0),0) -> 0
A23: N+3 | B23: =B22-E22 -> 0 | C23: =B23*$B$5 -> 0 | D23: =B23*$B$6 -> 0 | E23: =F23-C23 -> 0 | F23: =IF(B23>=1,IFERROR($B$4*$B$5/((1-(1+$B$5)^(-$B$7))),0),0) -> 0
A24: N+4 | B24: =B23-E23 -> 0 | C24: =B24*$B$5 -> 0 | D24: =B24*$B$6 -> 0 | E24: =F24-C24 -> 0 | F24: =IF(B24>=1,IFERROR($B$4*$B$5/((1-(1+$B$5)^(-$B$7))),0),0) -> 0
A25: Année 3
A26: Emprunt | B26: ='1.Var.Fin'!D17 -> 0 | E26: Montant (FCFA)
A27: Taux Annuel | B27: ='1.Var.Fin'!D19 -> 0
A28: TOB | B28: ='1.Var.Fin'!D21 -> 0.1
A29: DUREE | B29: =ROUNDUP('1.Var.Fin'!D8/12,0) -> 3 | C29: ANS
A30: Année | B30: CAPITAL RESTANT DU | C30: INTERET | D30: TOB | E30: Amortissement | F30: Annuité
A31: N | B31: =H26 -> 0 | C31: =B31*$B$5 -> 0 | D31: =B31*$B$6 -> 0 | E31: =F31-C31 -> 0 | F31: =IF(B31>=1,IFERROR($B$4*$B$5/((1-(1+$B$5)^(-$B$7))),0),0) -> 0
A32: N+1 | B32: =B31-E31 -> 0 | C32: =B32*$B$5 -> 0 | D32: =B32*$B$6 -> 0 | E32: =F32-C32 -> 0 | F32: =IF(B32>=1,IFERROR($B$4*$B$5/((1-(1+$B$5)^(-$B$7))),0),0) -> 0
A33: N+2 | B33: =B32-E32 -> 0 | C33: =B33*$B$5 -> 0 | D33: =B33*$B$6 -> 0 | E33: =F33-C33 -> 0 | F33: =IF(B33>=1,IFERROR($B$4*$B$5/((1-(1+$B$5)^(-$B$7))),0),0) -> 0
A34: N+3 | B34: =B33-E33 -> 0 | C34: =B34*$B$5 -> 0 | D34: =B34*$B$6 -> 0 | E34: =F34-C34 -> 0 | F34: =IF(B34>=1,IFERROR($B$4*$B$5/((1-(1+$B$5)^(-$B$7))),0),0) -> 0
A35: N+4 | B35: =B34-E34 -> 0 | C35: =B35*$B$5 -> 0 | D35: =B35*$B$6 -> 0 | E35: =F35-C35 -> 0 | F35: =IF(B35>=1,IFERROR($B$4*$B$5/((1-(1+$B$5)^(-$B$7))),0),0) -> 0

Sheet 5.Inv
A1: LISTE DES INVESTISSEMENTS
B3: Type d'immobilisation | C3: Dénomination | D3: CODE FINANCEMENT | E3: Nb | F3: Montant
A4: 1. | B4: Immobilisations corporelles bâtiment | C4: Aménagement et batiments | D4: {var_14} | E4: {var_31} | F4: {var_48}
C5: Aménagement entrepôt | D5: {var_15} | E5: {var_32} | F5: {var_49}
A6: 2. | B6: Immobilisation corporelle véhicules | C6: Véhicules de liaison | D6: {var_16} | E6: {var_33} | F6: {var_50}
C7: Véhicules de bureau | D7: {var_17} | E7: {var_34} | F7: {var_51}
C8: Véhicule administratif | D8: {var_18} | E8: {var_35} | F8: {var_52}
A9: 3. | B9: Autres immobilisations corporelles matériel de travail | C9: Bureau (Fauteuil + table) | D9: {var_19} | E9: {var_36} | F9: {var_53}
C10: Mobilier et matériel de bureau | D10: {var_20} | E10: {var_37} | F10: {var_54}
C11: Bureau (Fauteuil + table) | D11: {var_21} | E11: {var_38} | F11: {var_55}
C12: Ordinateur PRO | D12: {var_22} | E12: {var_39} | F12: {var_56}
C13: Serveur | D13: {var_23} | E13: {var_40} | F13: {var_57}
C14: CANON EOS 80 D + objectif 18-135mm IS USM | D14: {var_24} | E14: {var_41} | F14: {var_58}
C15: Boîtier Canon EOS 5D Mark IV | D15: {var_25} | E15: {var_42} | F15: {var_59}
C16: Photocopieuse + Imprimante | D16: {var_26} | E16: {var_43} | F16: {var_60}
A17: 4. | B17: Immobilisation incorporelles | C17: Caution et avance loyer | D17: {var_27} | E17: {var_44} | F17: {var_61}
C18: Branchement Téléphone et internet | D18: {var_28} | E18: {var_45} | F18: {var_62}
C19: Branchement CIE et SODECI | D19: {var_29} | E19: {var_46} | F19: {var_63}
C20: Bail foncier | D20: {var_30} | E20: {var_47} | F20: {var_64}

Sheet 6.Var.Inv
A1: FACTEURS DE VARIATION INVESTISSEMENT
B3: Type d'immobilisation | C3: Dénomination | D3: CODE FINANCEMENT | E3: 1 | F3: 2 | G3: 3 | H3: 4 | I3: 5 | J3: 6 | K3: 7 | L3: 8 | M3: 9 | N3: 10 | O3: 11 | P3: 12 | Q3: N | R3: N+1 | S3: N+2
A4: ='5.Inv'!A4 -> 1. | B4: ='5.Inv'!B4 -> Immobilisations corporelles bâtiment | C4: ='5.Inv'!C4 -> Aménagement et batiments | D4: ='5.Inv'!D4 -> {var_14} | E4: 1 | Q4: =SUM(E4:P4) -> 1
A5: ='5.Inv'!A5 -> 0 | B5: ='5.Inv'!B5 -> 0 | C5: ='5.Inv'!C5 -> Aménagement entrepôt | D5: ='5.Inv'!D5 -> {var_15} | E5: 1 | Q5: =SUM(E5:P5) -> 1
A6: ='5.Inv'!A6 -> 2. | B6: ='5.Inv'!B6 -> Immobilisation corporelle véhicules | C6: ='5.Inv'!C6 -> Véhicules de liaison | D6: ='5.Inv'!D6 -> {var_16} | E6: 1 | Q6: =SUM(E6:P6) -> 1
A7: ='5.Inv'!A7 -> 0 | B7: ='5.Inv'!B7 -> 0 | C7: ='5.Inv'!C7 -> Véhicules de bureau | D7: ='5.Inv'!D7 -> {var_17} | E7: 1 | Q7: =SUM(E7:P7) -> 1
A8: ='5.Inv'!A8 -> 0 | B8: ='5.Inv'!B8 -> 0 | C8: ='5.Inv'!C8 -> Véhicule administratif | D8: ='5.Inv'!D8 -> {var_18} | E8: 1 | Q8: =SUM(E8:P8) -> 1
A9: ='5.Inv'!A9 -> 3. | B9: ='5.Inv'!B9 -> Autres immobilisations corporelles matériel de travail | C9: ='5.Inv'!C9 -> Bureau (Fauteuil + table) | D9: ='5.Inv'!D9 -> {var_19} | E9: 1 | Q9: =SUM(E9:P9) -> 1
A10: ='5.Inv'!A10 -> 0 | B10: ='5.Inv'!B10 -> 0 | C10: ='5.Inv'!C10 -> Mobilier et matériel de bureau | D10: ='5.Inv'!D10 -> {var_20} | E10: 1 | Q10: =SUM(E10:P10) -> 1
A11: ='5.Inv'!A11 -> 0 | B11: ='5.Inv'!B11 -> 0 | C11: ='5.Inv'!C11 -> Bureau (Fauteuil + table) | D11: ='5.Inv'!D11 -> {var_21} | E11: 1 | Q11: =SUM(E11:P11) -> 1
A12: ='5.Inv'!A12 -> 0 | B12: ='5.Inv'!B12 -> 0 | C12: ='5.Inv'!C12 -> Ordinateur PRO | D12: ='5.Inv'!D12 -> {var_22} | E12: 1 | Q12: =SUM(E12:P12) -> 1
A13: ='5.Inv'!A13 -> 0 | B13: ='5.Inv'!B13 -> 0 | C13: ='5.Inv'!C13 -> Serveur | D13: ='5.Inv'!D13 -> {var_23} | E13: 1 | Q13: =SUM(E13:P13) -> 1
A14: ='5.Inv'!A14 -> 0 | B14: ='5.Inv'!B14 -> 0 | C14: ='5.Inv'!C14 -> CANON EOS 80 D + objectif 18-135mm IS USM | D14: ='5.Inv'!D14 -> {var_24} | E14: 1 | Q14: =SUM(E14:P14) -> 1
C15: ='5.Inv'!C15 -> Boîtier Canon EOS 5D Mark IV | D15: ='5.Inv'!D15 -> {var_25} | E15: 1
A16: ='5.Inv'!A16 -> 0 | B16: ='5.Inv'!B16 -> 0 | C16: ='5.Inv'!C16 -> Photocopieuse + Imprimante | D16: ='5.Inv'!D16 -> {var_26} | E16: 1 | Q16: =SUM(E16:P16) -> 1
A17: ='5.Inv'!A17 -> 4. | B17: ='5.Inv'!B17 -> Immobilisation incorporelles | C17: ='5.Inv'!C17 -> Caution et avance loyer | D17: ='5.Inv'!D17 -> {var_27} | E17: 1 | Q17: =SUM(E17:P17) -> 1
A18: ='5.Inv'!A18 -> 0 | B18: ='5.Inv'!B18 -> 0 | C18: ='5.Inv'!C18 -> Branchement Téléphone et internet | D18: ='5.Inv'!D18 -> {var_28} | E18: 1 | Q18: =SUM(E18:P18) -> 1
A19: ='5.Inv'!A19 -> 0 | B19: ='5.Inv'!B19 -> 0 | C19: ='5.Inv'!C19 -> Branchement CIE et SODECI | D19: ='5.Inv'!D19 -> {var_29} | Q19: =SUM(E19:P19) -> 0
A20: ='5.Inv'!A20 -> 0 | B20: ='5.Inv'!B20 -> 0 | C20: ='5.Inv'!C20 -> Bail foncier | D20: ='5.Inv'!D20 -> {var_30} | Q20: =SUM(E20:P20) -> 0
B21: Total | E21: =AVERAGE(E4:E20) -> 1 | F21: =AVERAGE(F4:F20) -> #DIV/0! | G21: =AVERAGE(G4:G20) -> #DIV/0! | H21: =AVERAGE(H4:H20) -> #DIV/0! | I21: =AVERAGE(I4:I20) -> #DIV/0! | J21: =AVERAGE(J4:J20) -> #DIV/0! | K21: =AVERAGE(K4:K20) -> #DIV/0! | L21: =AVERAGE(L4:L20) -> #DIV/0! | ... S21: =AVERAGE(S4:S20) -> #DIV/0!

Sheet 7.Bud.Inv.
A1: INVESTISSEMENTS
B3: Type d'immobilisation | C3: Immobilisation | D3: CODE FINANCEMENT | E3: 1 | F3: 2 | G3: 3 | H3: 4 | I3: 5 | J3: 6 | K3: 7 | L3: 8 | M3: 9 | N3: 10 | O3: 11 | P3: 12 | Q3: N | R3: N+1 | S3: N+2
A4: ='5.Inv'!A4 -> 1. | B4: ='5.Inv'!B4 -> Immobilisations corporelles bâtiment | C4: ='5.Inv'!C4 -> Aménagement et batiments | D4: ='5.Inv'!D4 -> {var_14} | E4: ='5.Inv'!$E4*'5.Inv'!$F4*'6.Var.Inv'!E4 -> #VALUE! | F4: ='5.Inv'!$E4*'5.Inv'!$F4*'6.Var.Inv'!F4 -> #VALUE! | G4: ='5.Inv'!$E4*'5.Inv'!$F4*'6.Var.Inv'!G4 -> #VALUE! | H4: ='5.Inv'!$E4*'5.Inv'!$F4*'6.Var.Inv'!H4 -> #VALUE! | I4: ='5.Inv'!$E4*'5.Inv'!$F4*'6.Var.Inv'!I4 -> #VALUE! | J4: ='5.Inv'!$E4*'5.Inv'!$F4*'6.Var.Inv'!J4 -> #VALUE! | K4: ='5.Inv'!$E4*'5.Inv'!$F4*'6.Var.Inv'!K4 -> #VALUE! | L4: ='5.Inv'!$E4*'5.Inv'!$F4*'6.Var.Inv'!L4 -> #VALUE! | ... P4: ='5.Inv'!$E4*'5.Inv'!$F4*'6.Var.Inv'!P4 -> #VALUE! | Q4: =SUM(E4:P4) -> #VALUE! | R4: ='5.Inv'!$E4*'5.Inv'!$F4*'6.Var.Inv'!R4 -> #VALUE! | S4: ='5.Inv'!$E4*'5.Inv'!$F4*'6.Var.Inv'!S4 -> #VALUE!
A6: ='5.Inv'!A5 -> 0 | B6: ='5.Inv'!B5 -> 0 | C6: ='5.Inv'!C5 -> Aménagement entrepôt | D6: ='5.Inv'!D5 -> {var_15} | E6: ='5.Inv'!$E5*'5.Inv'!$F5*'6.Var.Inv'!E5 -> #VALUE! | F6: ='5.Inv'!$E5*'5.Inv'!$F5*'6.Var.Inv'!F5 -> #VALUE! | G6: ='5.Inv'!$E5*'5.Inv'!$F5*'6.Var.Inv'!G5 -> #VALUE! | H6: ='5.Inv'!$E5*'5.Inv'!$F5*'6.Var.Inv'!H5 -> #VALUE! | I6: ='5.Inv'!$E5*'5.Inv'!$F5*'6.Var.Inv'!I5 -> #VALUE! | J6: ='5.Inv'!$E5*'5.Inv'!$F5*'6.Var.Inv'!J5 -> #VALUE! | K6: ='5.Inv'!$E5*'5.Inv'!$F5*'6.Var.Inv'!K5 -> #VALUE! | L6: ='5.Inv'!$E5*'5.Inv'!$F5*'6.Var.Inv'!L5 -> #VALUE! | ... P6: ='5.Inv'!$E5*'5.Inv'!$F5*'6.Var.Inv'!P5 -> #VALUE! | Q6: =SUM(E6:P6) -> #VALUE! | R6: ='5.Inv'!$E5*'5.Inv'!$F5*'6.Var.Inv'!R5 -> #VALUE! | S6: ='5.Inv'!$E5*'5.Inv'!$F5*'6.Var.Inv'!S5 -> #VALUE!
A7: ='5.Inv'!A6 -> 2. | B7: ='5.Inv'!B6 -> Immobilisation corporelle véhicules | C7: ='5.Inv'!C6 -> Véhicules de liaison | D7: ='5.Inv'!D6 -> {var_16} | E7: ='5.Inv'!$E6*'5.Inv'!$F6*'6.Var.Inv'!E6 -> #VALUE! | F7: ='5.Inv'!$E6*'5.Inv'!$F6*'6.Var.Inv'!F6 -> #VALUE! | G7: ='5.Inv'!$E6*'5.Inv'!$F6*'6.Var.Inv'!G6 -> #VALUE! | H7: ='5.Inv'!$E6*'5.Inv'!$F6*'6.Var.Inv'!H6 -> #VALUE! | I7: ='5.Inv'!$E6*'5.Inv'!$F6*'6.Var.Inv'!I6 -> #VALUE! | J7: ='5.Inv'!$E6*'5.Inv'!$F6*'6.Var.Inv'!J6 -> #VALUE! | K7: ='5.Inv'!$E6*'5.Inv'!$F6*'6.Var.Inv'!K6 -> #VALUE! | L7: ='5.Inv'!$E6*'5.Inv'!$F6*'6.Var.Inv'!L6 -> #VALUE! | ... P7: ='5.Inv'!$E6*'5.Inv'!$F6*'6.Var.Inv'!P6 -> #VALUE! | Q7: =SUM(E7:P7) -> #VALUE! | R7: ='5.Inv'!$E6*'5.Inv'!$F6*'6.Var.Inv'!R6 -> #VALUE! | S7: ='5.Inv'!$E6*'5.Inv'!$F6*'6.Var.Inv'!S6 -> #VALUE!
A8: ='5.Inv'!A7 -> 0 | B8: ='5.Inv'!B7 -> 0 | C8: ='5.Inv'!C7 -> Véhicules de bureau | D8: ='5.Inv'!D7 -> {var_17} | E8: ='5.Inv'!$E7*'5.Inv'!$F7*'6.Var.Inv'!E7 -> #VALUE! | F8: ='5.Inv'!$E7*'5.Inv'!$F7*'6.Var.Inv'!F7 -> #VALUE! | G8: ='5.Inv'!$E7*'5.Inv'!$F7*'6.Var.Inv'!G7 -> #VALUE! | H8: ='5.Inv'!$E7*'5.Inv'!$F7*'6.Var.Inv'!H7 -> #VALUE! | I8: ='5.Inv'!$E7*'5.Inv'!$F7*'6.Var.Inv'!I7 -> #VALUE! | J8: ='5.Inv'!$E7*'5.Inv'!$F7*'6.Var.Inv'!J7 -> #VALUE! | K8: ='5.Inv'!$E7*'5.Inv'!$F7*'6.Var.Inv'!K7 -> #VALUE! | L8: ='5.Inv'!$E7*'5.Inv'!$F7*'6.Var.Inv'!L7 -> #VALUE! | ... P8: ='5.Inv'!$E7*'5.Inv'!$F7*'6.Var.Inv'!P7 -> #VALUE! | Q8: =SUM(E8:P8) -> #VALUE! | R8: ='5.Inv'!$E7*'5.Inv'!$F7*'6.Var.Inv'!R7 -> #VALUE! | S8: ='5.Inv'!$E7*'5.Inv'!$F7*'6.Var.Inv'!S7 -> #VALUE!
A9: ='5.Inv'!A8 -> 0 | B9: ='5.Inv'!B8 -> 0 | C9: ='5.Inv'!C8 -> Véhicule administratif | D9: ='5.Inv'!D8 -> {var_18} | E9: ='5.Inv'!$E8*'5.Inv'!$F8*'6.Var.Inv'!E8 -> #VALUE! | F9: ='5.Inv'!$E8*'5.Inv'!$F8*'6.Var.Inv'!F8 -> #VALUE! | G9: ='5.Inv'!$E8*'5.Inv'!$F8*'6.Var.Inv'!G8 -> #VALUE! | H9: ='5.Inv'!$E8*'5.Inv'!$F8*'6.Var.Inv'!H8 -> #VALUE! | I9: ='5.Inv'!$E8*'5.Inv'!$F8*'6.Var.Inv'!I8 -> #VALUE! | J9: ='5.Inv'!$E8*'5.Inv'!$F8*'6.Var.Inv'!J8 -> #VALUE! | K9: ='5.Inv'!$E8*'5.Inv'!$F8*'6.Var.Inv'!K8 -> #VALUE! | L9: ='5.Inv'!$E8*'5.Inv'!$F8*'6.Var.Inv'!L8 -> #VALUE! | ... P9: ='5.Inv'!$E8*'5.Inv'!$F8*'6.Var.Inv'!P8 -> #VALUE! | Q9: =SUM(E9:P9) -> #VALUE! | R9: ='5.Inv'!$E8*'5.Inv'!$F8*'6.Var.Inv'!R8 -> #VALUE! | S9: ='5.Inv'!$E8*'5.Inv'!$F8*'6.Var.Inv'!S8 -> #VALUE!
A10: ='5.Inv'!A9 -> 3. | B10: ='5.Inv'!B9 -> Autres immobilisations corporelles matériel de travail | C10: ='5.Inv'!C9 -> Bureau (Fauteuil + table) | D10: ='5.Inv'!D9 -> {var_19} | E10: ='5.Inv'!$E9*'5.Inv'!$F9*'6.Var.Inv'!E9 -> #VALUE! | F10: ='5.Inv'!$E9*'5.Inv'!$F9*'6.Var.Inv'!F9 -> #VALUE! | G10: ='5.Inv'!$E9*'5.Inv'!$F9*'6.Var.Inv'!G9 -> #VALUE! | H10: ='5.Inv'!$E9*'5.Inv'!$F9*'6.Var.Inv'!H9 -> #VALUE! | I10: ='5.Inv'!$E9*'5.Inv'!$F9*'6.Var.Inv'!I9 -> #VALUE! | J10: ='5.Inv'!$E9*'5.Inv'!$F9*'6.Var.Inv'!J9 -> #VALUE! | K10: ='5.Inv'!$E9*'5.Inv'!$F9*'6.Var.Inv'!K9 -> #VALUE! | L10: ='5.Inv'!$E9*'5.Inv'!$F9*'6.Var.Inv'!L9 -> #VALUE! | ... P10: ='5.Inv'!$E9*'5.Inv'!$F9*'6.Var.Inv'!P9 -> #VALUE! | Q10: =SUM(E10:P10) -> #VALUE! | R10: ='5.Inv'!$E9*'5.Inv'!$F9*'6.Var.Inv'!R9 -> #VALUE! | S10: ='5.Inv'!$E9*'5.Inv'!$F9*'6.Var.Inv'!S9 -> #VALUE!
A11: ='5.Inv'!A10 -> 0 | B11: ='5.Inv'!B10 -> 0 | C11: ='5.Inv'!C10 -> Mobilier et matériel de bureau | D11: ='5.Inv'!D10 -> {var_20} | E11: ='5.Inv'!$E10*'5.Inv'!$F10*'6.Var.Inv'!E10 -> #VALUE! | F11: ='5.Inv'!$E10*'5.Inv'!$F10*'6.Var.Inv'!F10 -> #VALUE! | G11: ='5.Inv'!$E10*'5.Inv'!$F10*'6.Var.Inv'!G10 -> #VALUE! | H11: ='5.Inv'!$E10*'5.Inv'!$F10*'6.Var.Inv'!H10 -> #VALUE! | I11: ='5.Inv'!$E10*'5.Inv'!$F10*'6.Var.Inv'!I10 -> #VALUE! | J11: ='5.Inv'!$E10*'5.Inv'!$F10*'6.Var.Inv'!J10 -> #VALUE! | K11: ='5.Inv'!$E10*'5.Inv'!$F10*'6.Var.Inv'!K10 -> #VALUE! | L11: ='5.Inv'!$E10*'5.Inv'!$F10*'6.Var.Inv'!L10 -> #VALUE! | ... P11: ='5.Inv'!$E10*'5.Inv'!$F10*'6.Var.Inv'!P10 -> #VALUE! | Q11: =SUM(E11:P11) -> #VALUE! | R11: ='5.Inv'!$E10*'5.Inv'!$F10*'6.Var.Inv'!R10 -> #VALUE! | S11: ='5.Inv'!$E10*'5.Inv'!$F10*'6.Var.Inv'!S10 -> #VALUE!
A12: ='5.Inv'!A11 -> 0 | B12: ='5.Inv'!B11 -> 0 | C12: ='5.Inv'!C11 -> Bureau (Fauteuil + table) | D12: ='5.Inv'!D11 -> {var_21} | E12: ='5.Inv'!$E11*'5.Inv'!$F11*'6.Var.Inv'!E11 -> #VALUE! | F12: ='5.Inv'!$E11*'5.Inv'!$F11*'6.Var.Inv'!F11 -> #VALUE! | G12: ='5.Inv'!$E11*'5.Inv'!$F11*'6.Var.Inv'!G11 -> #VALUE! | H12: ='5.Inv'!$E11*'5.Inv'!$F11*'6.Var.Inv'!H11 -> #VALUE! | I12: ='5.Inv'!$E11*'5.Inv'!$F11*'6.Var.Inv'!I11 -> #VALUE! | J12: ='5.Inv'!$E11*'5.Inv'!$F11*'6.Var.Inv'!J11 -> #VALUE! | K12: ='5.Inv'!$E11*'5.Inv'!$F11*'6.Var.Inv'!K11 -> #VALUE! | L12: ='5.Inv'!$E11*'5.Inv'!$F11*'6.Var.Inv'!L11 -> #VALUE! | ... P12: ='5.Inv'!$E11*'5.Inv'!$F11*'6.Var.Inv'!P11 -> #VALUE! | Q12: =SUM(E12:P12) -> #VALUE! | R12: ='5.Inv'!$E11*'5.Inv'!$F11*'6.Var.Inv'!R11 -> #VALUE! | S12: ='5.Inv'!$E11*'5.Inv'!$F11*'6.Var.Inv'!S11 -> #VALUE!
A13: ='5.Inv'!A12 -> 0 | B13: ='5.Inv'!B12 -> 0 | C13: ='5.Inv'!C12 -> Ordinateur PRO | D13: ='5.Inv'!D12 -> {var_22} | E13: ='5.Inv'!$E12*'5.Inv'!$F12*'6.Var.Inv'!E12 -> #VALUE! | F13: ='5.Inv'!$E12*'5.Inv'!$F12*'6.Var.Inv'!F12 -> #VALUE! | G13: ='5.Inv'!$E12*'5.Inv'!$F12*'6.Var.Inv'!G12 -> #VALUE! | H13: ='5.Inv'!$E12*'5.Inv'!$F12*'6.Var.Inv'!H12 -> #VALUE! | I13: ='5.Inv'!$E12*'5.Inv'!$F12*'6.Var.Inv'!I12 -> #VALUE! | J13: ='5.Inv'!$E12*'5.Inv'!$F12*'6.Var.Inv'!J12 -> #VALUE! | K13: ='5.Inv'!$E12*'5.Inv'!$F12*'6.Var.Inv'!K12 -> #VALUE! | L13: ='5.Inv'!$E12*'5.Inv'!$F12*'6.Var.Inv'!L12 -> #VALUE! | ... P13: ='5.Inv'!$E12*'5.Inv'!$F12*'6.Var.Inv'!P12 -> #VALUE! | Q13: =SUM(E13:P13) -> #VALUE! | R13: ='5.Inv'!$E12*'5.Inv'!$F12*'6.Var.Inv'!R12 -> #VALUE! | S13: ='5.Inv'!$E12*'5.Inv'!$F12*'6.Var.Inv'!S12 -> #VALUE!
C14: ='5.Inv'!C13 -> Serveur | D14: ='5.Inv'!D13 -> {var_23} | E14: ='5.Inv'!$E13*'5.Inv'!$F13*'6.Var.Inv'!E13 -> #VALUE! | F14: ='5.Inv'!$E13*'5.Inv'!$F13*'6.Var.Inv'!F13 -> #VALUE! | G14: ='5.Inv'!$E13*'5.Inv'!$F13*'6.Var.Inv'!G13 -> #VALUE! | H14: ='5.Inv'!$E13*'5.Inv'!$F13*'6.Var.Inv'!H13 -> #VALUE! | I14: ='5.Inv'!$E13*'5.Inv'!$F13*'6.Var.Inv'!I13 -> #VALUE! | J14: ='5.Inv'!$E13*'5.Inv'!$F13*'6.Var.Inv'!J13 -> #VALUE! | K14: ='5.Inv'!$E13*'5.Inv'!$F13*'6.Var.Inv'!K13 -> #VALUE! | L14: ='5.Inv'!$E13*'5.Inv'!$F13*'6.Var.Inv'!L13 -> #VALUE! | ... P14: ='5.Inv'!$E13*'5.Inv'!$F13*'6.Var.Inv'!P13 -> #VALUE! | Q14: =SUM(E14:P14) -> #VALUE! | R14: ='5.Inv'!$E13*'5.Inv'!$F13*'6.Var.Inv'!R13 -> #VALUE! | S14: ='5.Inv'!$E13*'5.Inv'!$F13*'6.Var.Inv'!S13 -> #VALUE!
A15: ='5.Inv'!A13 -> 0 | B15: ='5.Inv'!B13 -> 0 | C15: ='5.Inv'!C14 -> CANON EOS 80 D + objectif 18-135mm IS USM | D15: ='5.Inv'!D14 -> {var_24} | E15: ='5.Inv'!$E14*'5.Inv'!$F14*'6.Var.Inv'!E14 -> #VALUE! | F15: ='5.Inv'!$E14*'5.Inv'!$F14*'6.Var.Inv'!F14 -> #VALUE! | G15: ='5.Inv'!$E14*'5.Inv'!$F14*'6.Var.Inv'!G14 -> #VALUE! | H15: ='5.Inv'!$E14*'5.Inv'!$F14*'6.Var.Inv'!H14 -> #VALUE! | I15: ='5.Inv'!$E14*'5.Inv'!$F14*'6.Var.Inv'!I14 -> #VALUE! | J15: ='5.Inv'!$E14*'5.Inv'!$F14*'6.Var.Inv'!J14 -> #VALUE! | K15: ='5.Inv'!$E14*'5.Inv'!$F14*'6.Var.Inv'!K14 -> #VALUE! | L15: ='5.Inv'!$E14*'5.Inv'!$F14*'6.Var.Inv'!L14 -> #VALUE! | ... P15: ='5.Inv'!$E14*'5.Inv'!$F14*'6.Var.Inv'!P14 -> #VALUE! | Q15: =SUM(E15:P15) -> #VALUE! | R15: ='5.Inv'!$E14*'5.Inv'!$F14*'6.Var.Inv'!R14 -> #VALUE! | S15: ='5.Inv'!$E14*'5.Inv'!$F14*'6.Var.Inv'!S14 -> #VALUE!
A16: ='5.Inv'!A14 -> 0 | B16: ='5.Inv'!B14 -> 0 | C16: ='5.Inv'!C15 -> Boîtier Canon EOS 5D Mark IV | D16: ='5.Inv'!D15 -> {var_25} | E16: ='5.Inv'!$E15*'5.Inv'!$F15*'6.Var.Inv'!E15 -> #VALUE! | F16: ='5.Inv'!$E15*'5.Inv'!$F15*'6.Var.Inv'!F15 -> #VALUE! | G16: ='5.Inv'!$E15*'5.Inv'!$F15*'6.Var.Inv'!G15 -> #VALUE! | H16: ='5.Inv'!$E15*'5.Inv'!$F15*'6.Var.Inv'!H15 -> #VALUE! | I16: ='5.Inv'!$E15*'5.Inv'!$F15*'6.Var.Inv'!I15 -> #VALUE! | J16: ='5.Inv'!$E15*'5.Inv'!$F15*'6.Var.Inv'!J15 -> #VALUE! | K16: ='5.Inv'!$E15*'5.Inv'!$F15*'6.Var.Inv'!K15 -> #VALUE! | L16: ='5.Inv'!$E15*'5.Inv'!$F15*'6.Var.Inv'!L15 -> #VALUE! | ... P16: ='5.Inv'!$E15*'5.Inv'!$F15*'6.Var.Inv'!P15 -> #VALUE! | Q16: =SUM(E16:P16) -> #VALUE! | R16: ='5.Inv'!$E15*'5.Inv'!$F15*'6.Var.Inv'!R15 -> #VALUE! | S16: ='5.Inv'!$E15*'5.Inv'!$F15*'6.Var.Inv'!S15 -> #VALUE!
A17: ='5.Inv'!A16 -> 0 | B17: ='5.Inv'!B16 -> 0 | C17: ='5.Inv'!C16 -> Photocopieuse + Imprimante | D17: ='5.Inv'!D16 -> {var_26} | E17: ='5.Inv'!$E16*'5.Inv'!$F16*'6.Var.Inv'!E16 -> #VALUE! | F17: ='5.Inv'!$E16*'5.Inv'!$F16*'6.Var.Inv'!F16 -> #VALUE! | G17: ='5.Inv'!$E16*'5.Inv'!$F16*'6.Var.Inv'!G16 -> #VALUE! | H17: ='5.Inv'!$E16*'5.Inv'!$F16*'6.Var.Inv'!H16 -> #VALUE! | I17: ='5.Inv'!$E16*'5.Inv'!$F16*'6.Var.Inv'!I16 -> #VALUE! | J17: ='5.Inv'!$E16*'5.Inv'!$F16*'6.Var.Inv'!J16 -> #VALUE! | K17: ='5.Inv'!$E16*'5.Inv'!$F16*'6.Var.Inv'!K16 -> #VALUE! | L17: ='5.Inv'!$E16*'5.Inv'!$F16*'6.Var.Inv'!L16 -> #VALUE! | ... P17: ='5.Inv'!$E16*'5.Inv'!$F16*'6.Var.Inv'!P16 -> #VALUE! | Q17: =SUM(E17:P17) -> #VALUE! | R17: ='5.Inv'!$E16*'5.Inv'!$F16*'6.Var.Inv'!R16 -> #VALUE! | S17: ='5.Inv'!$E16*'5.Inv'!$F16*'6.Var.Inv'!S16 -> #VALUE!
A18: ='5.Inv'!A17 -> 4. | B18: ='5.Inv'!B17 -> Immobilisation incorporelles | C18: ='5.Inv'!C17 -> Caution et avance loyer | D18: ='5.Inv'!D17 -> {var_27} | E18: ='5.Inv'!$E17*'5.Inv'!$F17*'6.Var.Inv'!E17 -> #VALUE! | F18: ='5.Inv'!$E17*'5.Inv'!$F17*'6.Var.Inv'!F17 -> #VALUE! | G18: ='5.Inv'!$E17*'5.Inv'!$F17*'6.Var.Inv'!G17 -> #VALUE! | H18: ='5.Inv'!$E17*'5.Inv'!$F17*'6.Var.Inv'!H17 -> #VALUE! | I18: ='5.Inv'!$E17*'5.Inv'!$F17*'6.Var.Inv'!I17 -> #VALUE! | J18: ='5.Inv'!$E17*'5.Inv'!$F17*'6.Var.Inv'!J17 -> #VALUE! | K18: ='5.Inv'!$E17*'5.Inv'!$F17*'6.Var.Inv'!K17 -> #VALUE! | L18: ='5.Inv'!$E17*'5.Inv'!$F17*'6.Var.Inv'!L17 -> #VALUE! | ... P18: ='5.Inv'!$E17*'5.Inv'!$F17*'6.Var.Inv'!P17 -> #VALUE! | Q18: =SUM(E18:P18) -> #VALUE! | R18: ='5.Inv'!$E17*'5.Inv'!$F17*'6.Var.Inv'!R17 -> #VALUE! | S18: ='5.Inv'!$E17*'5.Inv'!$F17*'6.Var.Inv'!S17 -> #VALUE!
A19: ='5.Inv'!A18 -> 0 | B19: ='5.Inv'!B18 -> 0 | C19: ='5.Inv'!C18 -> Branchement Téléphone et internet | D19: ='5.Inv'!D18 -> {var_28} | E19: ='5.Inv'!$E18*'5.Inv'!$F18*'6.Var.Inv'!E18 -> #VALUE! | F19: ='5.Inv'!$E18*'5.Inv'!$F18*'6.Var.Inv'!F18 -> #VALUE! | G19: ='5.Inv'!$E18*'5.Inv'!$F18*'6.Var.Inv'!G18 -> #VALUE! | H19: ='5.Inv'!$E18*'5.Inv'!$F18*'6.Var.Inv'!H18 -> #VALUE! | I19: ='5.Inv'!$E18*'5.Inv'!$F18*'6.Var.Inv'!I18 -> #VALUE! | J19: ='5.Inv'!$E18*'5.Inv'!$F18*'6.Var.Inv'!J18 -> #VALUE! | K19: ='5.Inv'!$E18*'5.Inv'!$F18*'6.Var.Inv'!K18 -> #VALUE! | L19: ='5.Inv'!$E18*'5.Inv'!$F18*'6.Var.Inv'!L18 -> #VALUE! | ... P19: ='5.Inv'!$E18*'5.Inv'!$F18*'6.Var.Inv'!P18 -> #VALUE! | Q19: =SUM(E19:P19) -> #VALUE! | R19: ='5.Inv'!$E18*'5.Inv'!$F18*'6.Var.Inv'!R18 -> #VALUE! | S19: ='5.Inv'!$E18*'5.Inv'!$F18*'6.Var.Inv'!S18 -> #VALUE!
A20: ='5.Inv'!A19 -> 0 | B20: ='5.Inv'!B19 -> 0 | C20: ='5.Inv'!C19 -> Branchement CIE et SODECI | D20: ='5.Inv'!D19 -> {var_29} | E20: ='5.Inv'!$E19*'5.Inv'!$F19*'6.Var.Inv'!E19 -> #VALUE! | F20: ='5.Inv'!$E19*'5.Inv'!$F19*'6.Var.Inv'!F19 -> #VALUE! | G20: ='5.Inv'!$E19*'5.Inv'!$F19*'6.Var.Inv'!G19 -> #VALUE! | H20: ='5.Inv'!$E19*'5.Inv'!$F19*'6.Var.Inv'!H19 -> #VALUE! | I20: ='5.Inv'!$E19*'5.Inv'!$F19*'6.Var.Inv'!I19 -> #VALUE! | J20: ='5.Inv'!$E19*'5.Inv'!$F19*'6.Var.Inv'!J19 -> #VALUE! | K20: ='5.Inv'!$E19*'5.Inv'!$F19*'6.Var.Inv'!K19 -> #VALUE! | L20: ='5.Inv'!$E19*'5.Inv'!$F19*'6.Var.Inv'!L19 -> #VALUE! | ... P20: ='5.Inv'!$E19*'5.Inv'!$F19*'6.Var.Inv'!P19 -> #VALUE! | Q20: =SUM(E20:P20) -> #VALUE! | R20: ='5.Inv'!$E19*'5.Inv'!$F19*'6.Var.Inv'!R19 -> #VALUE! | S20: ='5.Inv'!$E19*'5.Inv'!$F19*'6.Var.Inv'!S19 -> #VALUE!
A21: ='5.Inv'!A20 -> 0 | B21: ='5.Inv'!B20 -> 0 | C21: ='5.Inv'!C20 -> Bail foncier | D21: ='5.Inv'!D20 -> {var_30} | E21: ='5.Inv'!$E20*'5.Inv'!$F20*'6.Var.Inv'!E20 -> #VALUE! | F21: ='5.Inv'!$E20*'5.Inv'!$F20*'6.Var.Inv'!F20 -> #VALUE! | G21: ='5.Inv'!$E20*'5.Inv'!$F20*'6.Var.Inv'!G20 -> #VALUE! | H21: ='5.Inv'!$E20*'5.Inv'!$F20*'6.Var.Inv'!H20 -> #VALUE! | I21: ='5.Inv'!$E20*'5.Inv'!$F20*'6.Var.Inv'!I20 -> #VALUE! | J21: ='5.Inv'!$E20*'5.Inv'!$F20*'6.Var.Inv'!J20 -> #VALUE! | K21: ='5.Inv'!$E20*'5.Inv'!$F20*'6.Var.Inv'!K20 -> #VALUE! | L21: ='5.Inv'!$E20*'5.Inv'!$F20*'6.Var.Inv'!L20 -> #VALUE! | ... P21: ='5.Inv'!$E20*'5.Inv'!$F20*'6.Var.Inv'!P20 -> #VALUE! | Q21: =SUM(E21:P21) -> #VALUE! | R21: ='5.Inv'!$E20*'5.Inv'!$F20*'6.Var.Inv'!R20 -> #VALUE! | S21: ='5.Inv'!$E20*'5.Inv'!$F20*'6.Var.Inv'!S20 -> #VALUE!
B22: Total | C22: Total | E22: =SUM(E4:E21) -> #VALUE! | F22: =SUM(F4:F21) -> #VALUE! | G22: =SUM(G4:G21) -> #VALUE! | H22: =SUM(H4:H21) -> #VALUE! | I22: =SUM(I4:I21) -> #VALUE! | J22: =SUM(J4:J21) -> #VALUE! | K22: =SUM(K4:K21) -> #VALUE! | L22: =SUM(L4:L21) -> #VALUE! | ... S22: =SUM(S4:S21) -> #VALUE!

Sheet 8.Prod
A1: LISTES DES VENTES
A3: Type de produit | B3: Nom | C3: CODE | D3: Qté | E3: Prix
A4: Ventes de marchandises | B4: CA de Tenue de luxe Homme | C4: VEN1 | D4: =BP_Pres!C11 -> {var_5} | E4: =BP_Pres!D11 -> {var_9}
A5: Ventes de marchandises | B5: CA de Tenue de luxe Femme | C5: VEN1 | D5: =BP_Pres!C12 -> {var_6} | E5: =BP_Pres!D12 -> {var_10}
A6: Ventes de marchandises | B6: CA de Prêt-à-porter homme | C6: VEN1 | D6: =BP_Pres!C13 -> {var_7} | E6: =BP_Pres!D13 -> {var_12}
A7: Ventes de marchandises | B7: CA de Prêt-à-porter femme | C7: VEN1 | D7: =BP_Pres!C14 -> {var_8} | E7: =BP_Pres!D14 -> {var_13}
A8: Ventes de produits fabriqués | C8: VEN2
A9: Vente de services | C9: VEN3
A10: Ventes d'autre produits | C10: VEN4

Sheet 9.Var.Vente1
A1: FACTEURS DE VARIATION VENTES
D2: Ventes mensuelles | P2: Ventes Annuelles
A4: Type de produit | B4: Produit | C4: CODE | D4: 1 | E4: 2 | F4: 3 | G4: 4 | H4: 5 | I4: 6 | J4: 7 | K4: 8 | L4: 9 | M4: 10 | N4: 11 | O4: 12 | P4: N | Q4: N+1 | R4: N+2
A5: ='8.Prod'!A4 -> Ventes de marchandises | B5: ='8.Prod'!B4 -> CA de Tenue de luxe Homme | C5: ='8.Prod'!C4 -> VEN1 | D5: 60 | E5: 60 | F5: 60 | G5: 60 | H5: 60 | I5: 60 | J5: 60 | K5: 60 | L5: 60 | M5: 60 | N5: 60 | O5: 60 | P5: 720 | Q5: 792 | R5: 871.2
A6: ='8.Prod'!A5 -> Ventes de marchandises | B6: ='8.Prod'!B5 -> CA de Tenue de luxe Femme | C6: ='8.Prod'!C5 -> VEN1 | D6: 114 | E6: 114 | F6: 114 | G6: 114 | H6: 114 | I6: 114 | J6: 114 | K6: 114 | L6: 114 | M6: 114 | N6: 114 | O6: 114 | P6: 1368 | Q6: 1504.8 | R6: 1655.28
A7: ='8.Prod'!A6 -> Ventes de marchandises | B7: ='8.Prod'!B6 -> CA de Prêt-à-porter homme | C7: ='8.Prod'!C6 -> VEN1 | D7: 240 | E7: 240 | F7: 240 | G7: 240 | H7: 240 | I7: 240 | J7: 240 | K7: 240 | L7: 240 | M7: 240 | N7: 240 | O7: 240 | P7: 2880 | Q7: 3168 | R7: 3484.8
A8: ='8.Prod'!A7 -> Ventes de marchandises | B8: ='8.Prod'!B7 -> CA de Prêt-à-porter femme | C8: ='8.Prod'!C7 -> VEN1 | D8: 456 | E8: 456 | F8: 456 | G8: 456 | H8: 456 | I8: 456 | J8: 456 | K8: 456 | L8: 456 | M8: 456 | N8: 456 | O8: 456 | P8: 5472 | Q8: 6019.2 | R8: 6621.12
A9: ='8.Prod'!A8 -> Ventes de produits fabriqués | B9: ='8.Prod'!B8 -> 0 | C9: ='8.Prod'!C8 -> VEN2 | Q9: 1.1 | R9: 1.1
A10: ='8.Prod'!A9 -> Vente de services | B10: ='8.Prod'!B9 -> 0 | C10: ='8.Prod'!C9 -> VEN3 | Q10: 1.1 | R10: 1.1
A11: ='8.Prod'!A10 -> Ventes d'autre produits | B11: ='8.Prod'!B10 -> 0 | C11: ='8.Prod'!C10 -> VEN4 | Q11: 1.1 | R11: 1.1
A12: Total | D12: =AVERAGE(D5:D11) -> 217.5 | E12: =AVERAGE(E5:E11) -> 217.5 | F12: =AVERAGE(F5:F11) -> 217.5 | G12: =AVERAGE(G5:G11) -> 217.5 | H12: =AVERAGE(H5:H11) -> 217.5 | I12: =AVERAGE(I5:I11) -> 217.5 | J12: =AVERAGE(J5:J11) -> 217.5 | K12: =AVERAGE(K5:K11) -> 217.5 | ... R12: =AVERAGE(R5:R11) -> 1805.1

Sheet 10.Vente
A1: VENTES
D2: Ventes mensuelles | P2: Ventes Annuelles
A4: Type de produit | B4: Produit | C4: CODE | D4: 1 | E4: 2 | F4: 3 | G4: 4 | H4: 5 | I4: 6 | J4: 7 | K4: 8 | L4: 9 | M4: 10 | N4: 11 | O4: 12 | P4: N | Q4: N+1 | R4: N+2
A5: ='8.Prod'!A4 -> Ventes de marchandises | B5: ='8.Prod'!B4 -> CA de Tenue de luxe Homme | C5: ='8.Prod'!C4 -> VEN1 | D5: ='8.Prod'!$D4*'8.Prod'!$E4*'9.Var.Vente1'!D5 -> #VALUE! | E5: ='8.Prod'!$D4*'8.Prod'!$E4*'9.Var.Vente1'!E5 -> #VALUE! | F5: ='8.Prod'!$D4*'8.Prod'!$E4*'9.Var.Vente1'!F5 -> #VALUE! | G5: ='8.Prod'!$D4*'8.Prod'!$E4*'9.Var.Vente1'!G5 -> #VALUE! | H5: ='8.Prod'!$D4*'8.Prod'!$E4*'9.Var.Vente1'!H5 -> #VALUE! | I5: ='8.Prod'!$D4*'8.Prod'!$E4*'9.Var.Vente1'!I5 -> #VALUE! | J5: ='8.Prod'!$D4*'8.Prod'!$E4*'9.Var.Vente1'!J5 -> #VALUE! | K5: ='8.Prod'!$D4*'8.Prod'!$E4*'9.Var.Vente1'!K5 -> #VALUE! | ... R5: ='8.Prod'!$D4*'8.Prod'!$E4*'9.Var.Vente1'!R5 -> #VALUE!
A6: ='8.Prod'!A5 -> Ventes de marchandises | B6: ='8.Prod'!B5 -> CA de Tenue de luxe Femme | C6: ='8.Prod'!C5 -> VEN1 | D6: ='8.Prod'!$D5*'8.Prod'!$E5*'9.Var.Vente1'!D6 -> #VALUE! | E6: ='8.Prod'!$D5*'8.Prod'!$E5*'9.Var.Vente1'!E6 -> #VALUE! | F6: ='8.Prod'!$D5*'8.Prod'!$E5*'9.Var.Vente1'!F6 -> #VALUE! | G6: ='8.Prod'!$D5*'8.Prod'!$E5*'9.Var.Vente1'!G6 -> #VALUE! | H6: ='8.Prod'!$D5*'8.Prod'!$E5*'9.Var.Vente1'!H6 -> #VALUE! | I6: ='8.Prod'!$D5*'8.Prod'!$E5*'9.Var.Vente1'!I6 -> #VALUE! | J6: ='8.Prod'!$D5*'8.Prod'!$E5*'9.Var.Vente1'!J6 -> #VALUE! | K6: ='8.Prod'!$D5*'8.Prod'!$E5*'9.Var.Vente1'!K6 -> #VALUE! | ... R6: ='8.Prod'!$D5*'8.Prod'!$E5*'9.Var.Vente1'!R6 -> #VALUE!
A7: ='8.Prod'!A6 -> Ventes de marchandises | B7: ='8.Prod'!B6 -> CA de Prêt-à-porter homme | C7: ='8.Prod'!C6 -> VEN1 | D7: ='8.Prod'!$D6*'8.Prod'!$E6*'9.Var.Vente1'!D7 -> #VALUE! | E7: ='8.Prod'!$D6*'8.Prod'!$E6*'9.Var.Vente1'!E7 -> #VALUE! | F7: ='8.Prod'!$D6*'8.Prod'!$E6*'9.Var.Vente1'!F7 -> #VALUE! | G7: ='8.Prod'!$D6*'8.Prod'!$E6*'9.Var.Vente1'!G7 -> #VALUE! | H7: ='8.Prod'!$D6*'8.Prod'!$E6*'9.Var.Vente1'!H7 -> #VALUE! | I7: ='8.Prod'!$D6*'8.Prod'!$E6*'9.Var.Vente1'!I7 -> #VALUE! | J7: ='8.Prod'!$D6*'8.Prod'!$E6*'9.Var.Vente1'!J7 -> #VALUE! | K7: ='8.Prod'!$D6*'8.Prod'!$E6*'9.Var.Vente1'!K7 -> #VALUE! | ... R7: ='8.Prod'!$D6*'8.Prod'!$E6*'9.Var.Vente1'!R7 -> #VALUE!
A8: ='8.Prod'!A7 -> Ventes de marchandises | B8: ='8.Prod'!B7 -> CA de Prêt-à-porter femme | C8: ='8.Prod'!C7 -> VEN1 | D8: ='8.Prod'!$D7*'8.Prod'!$E7*'9.Var.Vente1'!D8 -> #VALUE! | E8: ='8.Prod'!$D7*'8.Prod'!$E7*'9.Var.Vente1'!E8 -> #VALUE! | F8: ='8.Prod'!$D7*'8.Prod'!$E7*'9.Var.Vente1'!F8 -> #VALUE! | G8: ='8.Prod'!$D7*'8.Prod'!$E7*'9.Var.Vente1'!G8 -> #VALUE! | H8: ='8.Prod'!$D7*'8.Prod'!$E7*'9.Var.Vente1'!H8 -> #VALUE! | I8: ='8.Prod'!$D7*'8.Prod'!$E7*'9.Var.Vente1'!I8 -> #VALUE! | J8: ='8.Prod'!$D7*'8.Prod'!$E7*'9.Var.Vente1'!J8 -> #VALUE! | K8: ='8.Prod'!$D7*'8.Prod'!$E7*'9.Var.Vente1'!K8 -> #VALUE! | ... R8: ='8.Prod'!$D7*'8.Prod'!$E7*'9.Var.Vente1'!R8 -> #VALUE!
A9: ='8.Prod'!A8 -> Ventes de produits fabriqués | B9: ='8.Prod'!B8 -> 0 | C9: ='8.Prod'!C8 -> VEN2 | D9: ='8.Prod'!$D8*'8.Prod'!$E8*'9.Var.Vente1'!D9 -> 0 | E9: ='8.Prod'!$D8*'8.Prod'!$E8*'9.Var.Vente1'!E9 -> 0 | F9: ='8.Prod'!$D8*'8.Prod'!$E8*'9.Var.Vente1'!F9 -> 0 | G9: ='8.Prod'!$D8*'8.Prod'!$E8*'9.Var.Vente1'!G9 -> 0 | H9: ='8.Prod'!$D8*'8.Prod'!$E8*'9.Var.Vente1'!H9 -> 0 | I9: ='8.Prod'!$D8*'8.Prod'!$E8*'9.Var.Vente1'!I9 -> 0 | J9: ='8.Prod'!$D8*'8.Prod'!$E8*'9.Var.Vente1'!J9 -> 0 | K9: ='8.Prod'!$D8*'8.Prod'!$E8*'9.Var.Vente1'!K9 -> 0 | ... R9: ='8.Prod'!$D8*'8.Prod'!$E8*'9.Var.Vente1'!R9 -> 0
A10: ='8.Prod'!A9 -> Vente de services | B10: ='8.Prod'!B9 -> 0 | C10: ='8.Prod'!C9 -> VEN3 | D10: ='8.Prod'!$D9*'8.Prod'!$E9*'9.Var.Vente1'!D10 -> 0 | E10: ='8.Prod'!$D9*'8.Prod'!$E9*'9.Var.Vente1'!E10 -> 0 | F10: ='8.Prod'!$D9*'8.Prod'!$E9*'9.Var.Vente1'!F10 -> 0 | G10: ='8.Prod'!$D9*'8.Prod'!$E9*'9.Var.Vente1'!G10 -> 0 | H10: ='8.Prod'!$D9*'8.Prod'!$E9*'9.Var.Vente1'!H10 -> 0 | I10: ='8.Prod'!$D9*'8.Prod'!$E9*'9.Var.Vente1'!I10 -> 0 | J10: ='8.Prod'!$D9*'8.Prod'!$E9*'9.Var.Vente1'!J10 -> 0 | K10: ='8.Prod'!$D9*'8.Prod'!$E9*'9.Var.Vente1'!K10 -> 0 | ... R10: ='8.Prod'!$D9*'8.Prod'!$E9*'9.Var.Vente1'!R10 -> 0
A11: ='8.Prod'!A10 -> Ventes d'autre produits | B11: ='8.Prod'!B10 -> 0 | C11: ='8.Prod'!C10 -> VEN4 | D11: ='8.Prod'!$D10*'8.Prod'!$E10*'9.Var.Vente1'!D11 -> 0 | E11: ='8.Prod'!$D10*'8.Prod'!$E10*'9.Var.Vente1'!E11 -> 0 | F11: ='8.Prod'!$D10*'8.Prod'!$E10*'9.Var.Vente1'!F11 -> 0 | G11: ='8.Prod'!$D10*'8.Prod'!$E10*'9.Var.Vente1'!G11 -> 0 | H11: ='8.Prod'!$D10*'8.Prod'!$E10*'9.Var.Vente1'!H11 -> 0 | I11: ='8.Prod'!$D10*'8.Prod'!$E10*'9.Var.Vente1'!I11 -> 0 | J11: ='8.Prod'!$D10*'8.Prod'!$E10*'9.Var.Vente1'!J11 -> 0 | K11: ='8.Prod'!$D10*'8.Prod'!$E10*'9.Var.Vente1'!K11 -> 0 | ... R11: ='8.Prod'!$D10*'8.Prod'!$E10*'9.Var.Vente1'!R11 -> 0
A12: Total | D12: =SUM(D5:D11) -> #VALUE! | E12: =SUM(E5:E11) -> #VALUE! | F12: =SUM(F5:F11) -> #VALUE! | G12: =SUM(G5:G11) -> #VALUE! | H12: =SUM(H5:H11) -> #VALUE! | I12: =SUM(I5:I11) -> #VALUE! | J12: =SUM(J5:J11) -> #VALUE! | K12: =SUM(K5:K11) -> #VALUE! | ... R12: =SUM(R5:R11) -> #VALUE!

Sheet 11.Charges
A1: LISTE DES CHARGES DIRECTES ET INDIRECTES
A3: Type de charges | B3: Nom | C3: CODE | D3: Quantité | E3: Montant
A4: Achat de marchandises | B4: Achat de Tenue de luxe Homme | C4: AMA1 | D4: 1 | E4: 6000
A5: Achat de marchandises | B5: Achat de Tenue de luxe Femme | C5: AMA1 | D5: 1 | E5: 12000
A6: Achat de marchandises | B6: Achat de Prêt-à-porter homme | C6: AMA1 | D6: 1 | E6: 3000
A7: Achat de marchandises | B7: Achat de Prêt-à-porter femme | C7: AMA1 | D7: 1 | E7: 1500
A8: Achat de MP | C8: AMA2 | D8: 1
A9: Main d'œuvre directe vente | C9: MOD1 | D9: 1
A10: Main d'œuvre directe transformation | C10: MOD2 | D10: 1
A11: Main d'œuvre directe vente de services | C11: MOD3 | D11: 1
A12: Frais indirects de transformation | C12: FIF1 | D12: 1
A13: Frais indirects de vente | B13: Logistique Tenue de luxe Homme | C13: FIF2 | D13: 1 | E13: 200
A14: Frais indirects de vente | B14: Logistique Tenue de luxe Femme | C14: FIF2 | D14: 1 | E14: 400
A15: Frais indirects de vente | B15: Logistique Prêt-à-porter homme | C15: FIF2 | D15: 1 | E15: 100
A16: Frais indirects de vente | B16: Logistique Prêt-à-porter femme | C16: FIF2 | D16: 1 | E16: 50
A17: Frais indirects de vente | B17: Stockage Tenue de luxe Homme | C17: FIF2 | D17: 1 | E17: 400
A18: Frais indirects de vente | B18: Stockage Tenue de luxe Femme | C18: FIF2 | D18: 1 | E18: 800
A19: Frais indirects de vente | B19: Stockage Prêt-à-porter homme | C19: FIF2 | D19: 1 | E19: 200
A20: Frais indirects de vente | B20: Stockage Prêt-à-porter femme | C20: FIF2 | D20: 1 | E20: 100
A21: Frais indirects de vente | B21: Commission MP Tenue de luxe Homme | C21: FIF2 | D21: 1 | E21: 200
A22: Frais indirects de vente | B22: Commission MP Tenue de luxe Femme | C22: FIF2 | D22: 1 | E22: 400
A23: Frais indirects de vente | B23: Commission MP Prêt-à-porter homme | C23: FIF2 | D23: 1 | E23: 100
A24: Frais indirects de vente | B24: Commission MP Prêt-à-porter femme | C24: FIF2 | D24: 1 | E24: 50
A25: Frais indirects de vente de services | C25: FIF3 | D25: 1
A26: Salaires et Avantages | B26: Salaire personnel | C26: SAV1 | D26: 1 | E26: 0.22
A27: Taxe et redevance | B27: Timbre | C27: TXR1 | D27: 1 | E27: 0.0048
A28: Impôt sur les entreprises | B28: BIC | C28: IMP1 | D28: 1 | E28: 0.0307
A29: Action commerciale | B29: Sponsoring page réseaux sociaux | C29: MKT1 | D29: 1 | E29: 1900000
A30: Frais Généraux | B30: Frais administration | C30: FG1 | D30: 1 | E30: =15000+10000 -> 25000
A31: Energie/Electricité/ Eau | B31: Eau | C31: EEE1 | D31: 1 | E31: 82500
A32: Frais de transport | B32: Carburant | C32: FT1 | D32: 1 | E32: 50000
A33: Frais de communication | B33: Telephone / Internet | C33: MKT2 | D33: 1 | E33: =50000 -> 50000
A34: Publicité et Marketing | C34: FKT3 | D34: 1
A35: Location | B35: Loyer | C35: LOC1 | D35: 1 | E35: 250000
A36: Assurance | B36: Assurance voiture | C36: ASS1 | D36: 1 | E36: 12000
A37: Prestations et Honoraires | B37: Frais Infogérance | C37: PH1 | D37: 1 | E37: =370000+10000 -> 380000
A38: Autres provisions | C38: APR1 | D38: 1
A39: Amortissement Bureau | C39: AMR2 | D39: 1
A40: Amortissement Exploitation | B40: Amortissement équipement. | C40: AMR1 | D40: 1 | E40: 0.0351

Sheet 12.Char.Dir
A1: CHARGES INDIRECTES
D2: Charges mensuelles | P2: Charges annuelles
A3: Type de charges | B3: Charge | C3: CODE | D3: 1 | E3: 2 | F3: 3 | G3: 4 | H3: 5 | I3: 6 | J3: 7 | K3: 8 | L3: 9 | M3: 10 | N3: 11 | O3: 12 | P3: N | Q3: N+1 | R3: N+2
A4: ='11.Charges'!A4 -> Achat de marchandises | B4: ='11.Charges'!B4 -> Achat de Tenue de luxe Homme | C4: ='11.Charges'!C4 -> AMA1 | D4: ='11.Charges'!$D4*'11.Charges'!$E4*'9.Var.Vente1'!D$5 -> 360000 | E4: ='11.Charges'!$D4*'11.Charges'!$E4*'9.Var.Vente1'!E$5 -> 360000 | F4: ='11.Charges'!$D4*'11.Charges'!$E4*'9.Var.Vente1'!F$5 -> 360000 | G4: ='11.Charges'!$D4*'11.Charges'!$E4*'9.Var.Vente1'!G$5 -> 360000 | H4: ='11.Charges'!$D4*'11.Charges'!$E4*'9.Var.Vente1'!H$5 -> 360000 | I4: ='11.Charges'!$D4*'11.Charges'!$E4*'9.Var.Vente1'!I$5 -> 360000 | J4: ='11.Charges'!$D4*'11.Charges'!$E4*'9.Var.Vente1'!J$5 -> 360000 | K4: ='11.Charges'!$D4*'11.Charges'!$E4*'9.Var.Vente1'!K$5 -> 360000 | ... R4: ='11.Charges'!$D4*'11.Charges'!$E4*'9.Var.Vente1'!R$5 -> 5227200
A5: ='11.Charges'!A5 -> Achat de marchandises | B5: ='11.Charges'!B5 -> Achat de Tenue de luxe Femme | C5: ='11.Charges'!C5 -> AMA1 | D5: ='11.Charges'!$D5*'11.Charges'!$E5*'9.Var.Vente1'!D$5 -> 720000 | E5: ='11.Charges'!$D5*'11.Charges'!$E5*'9.Var.Vente1'!E$5 -> 720000 | F5: ='11.Charges'!$D5*'11.Charges'!$E5*'9.Var.Vente1'!F$5 -> 720000 | G5: ='11.Charges'!$D5*'11.Charges'!$E5*'9.Var.Vente1'!G$5 -> 720000 | H5: ='11.Charges'!$D5*'11.Charges'!$E5*'9.Var.Vente1'!H$5 -> 720000 | I5: ='11.Charges'!$D5*'11.Charges'!$E5*'9.Var.Vente1'!I$5 -> 720000 | J5: ='11.Charges'!$D5*'11.Charges'!$E5*'9.Var.Vente1'!J$5 -> 720000 | K5: ='11.Charges'!$D5*'11.Charges'!$E5*'9.Var.Vente1'!K$5 -> 720000 | ... R5: ='11.Charges'!$D5*'11.Charges'!$E5*'9.Var.Vente1'!R$5 -> 10454400
A6: ='11.Charges'!A6 -> Achat de marchandises | B6: ='11.Charges'!B6 -> Achat de Prêt-à-porter homme | C6: ='11.Charges'!C6 -> AMA1 | D6: ='11.Charges'!$D6*'11.Charges'!$E6*'9.Var.Vente1'!D$5 -> 180000 | E6: ='11.Charges'!$D6*'11.Charges'!$E6*'9.Var.Vente1'!E$5 -> 180000 | F6: ='11.Charges'!$D6*'11.Charges'!$E6*'9.Var.Vente1'!F$5 -> 180000 | G6: ='11.Charges'!$D6*'11.Charges'!$E6*'9.Var.Vente1'!G$5 -> 180000 | H6: ='11.Charges'!$D6*'11.Charges'!$E6*'9.Var.Vente1'!H$5 -> 180000 | I6: ='11.Charges'!$D6*'11.Charges'!$E6*'9.Var.Vente1'!I$5 -> 180000 | J6: ='11.Charges'!$D6*'11.Charges'!$E6*'9.Var.Vente1'!J$5 -> 180000 | K6: ='11.Charges'!$D6*'11.Charges'!$E6*'9.Var.Vente1'!K$5 -> 180000 | ... R6: ='11.Charges'!$D6*'11.Charges'!$E6*'9.Var.Vente1'!R$5 -> 2613600
A7: ='11.Charges'!A7 -> Achat de marchandises | B7: ='11.Charges'!B7 -> Achat de Prêt-à-porter femme | C7: ='11.Charges'!C7 -> AMA1 | D7: ='11.Charges'!$D7*'11.Charges'!$E7*'9.Var.Vente1'!D$5 -> 90000 | E7: ='11.Charges'!$D7*'11.Charges'!$E7*'9.Var.Vente1'!E$5 -> 90000 | F7: ='11.Charges'!$D7*'11.Charges'!$E7*'9.Var.Vente1'!F$5 -> 90000 | G7: ='11.Charges'!$D7*'11.Charges'!$E7*'9.Var.Vente1'!G$5 -> 90000 | H7: ='11.Charges'!$D7*'11.Charges'!$E7*'9.Var.Vente1'!H$5 -> 90000 | I7: ='11.Charges'!$D7*'11.Charges'!$E7*'9.Var.Vente1'!I$5 -> 90000 | J7: ='11.Charges'!$D7*'11.Charges'!$E7*'9.Var.Vente1'!J$5 -> 90000 | K7: ='11.Charges'!$D7*'11.Charges'!$E7*'9.Var.Vente1'!K$5 -> 90000 | ... R7: ='11.Charges'!$D7*'11.Charges'!$E7*'9.Var.Vente1'!R$5 -> 1306800
A8: ='11.Charges'!A8 -> Achat de MP | B8: ='11.Charges'!B8 -> 0 | C8: ='11.Charges'!C8 -> AMA2 | D8: ='11.Charges'!$E$8*'11.Charges'!$D$8*'9.Var.Vente1'!D9 -> 0 | E8: ='11.Charges'!$E$8*'11.Charges'!$D$8*'9.Var.Vente1'!E9 -> 0 | F8: ='11.Charges'!$E$8*'11.Charges'!$D$8*'9.Var.Vente1'!F9 -> 0 | G8: ='11.Charges'!$E$8*'11.Charges'!$D$8*'9.Var.Vente1'!G9 -> 0 | H8: ='11.Charges'!$E$8*'11.Charges'!$D$8*'9.Var.Vente1'!H9 -> 0 | I8: ='11.Charges'!$E$8*'11.Charges'!$D$8*'9.Var.Vente1'!I9 -> 0 | J8: ='11.Charges'!$E$8*'11.Charges'!$D$8*'9.Var.Vente1'!J9 -> 0 | K8: ='11.Charges'!$E$8*'11.Charges'!$D$8*'9.Var.Vente1'!K9 -> 0 | ... O8: ='11.Charges'!$E$8*'11.Charges'!$D$8*'9.Var.Vente1'!O9 -> 0 | P8: ='11.Charges'!$D8*'11.Charges'!$E8*'9.Var.Vente1'!P$5 -> 0 | Q8: ='11.Charges'!$D8*'11.Charges'!$E8*'9.Var.Vente1'!Q$5 -> 0 | R8: ='11.Charges'!$D8*'11.Charges'!$E8*'9.Var.Vente1'!R$5 -> 0
A9: ='11.Charges'!A9 -> Main d'œuvre directe vente | B9: ='11.Charges'!B9 -> 0 | C9: ='11.Charges'!C9 -> MOD1 | D9: ='11.Charges'!$E$9*'11.Charges'!$D$9*'9.Var.Vente1'!D5 -> 0 | E9: ='11.Charges'!$E$9*'11.Charges'!$D$9*'9.Var.Vente1'!E5 -> 0 | F9: ='11.Charges'!$E$9*'11.Charges'!$D$9*'9.Var.Vente1'!F5 -> 0 | G9: ='11.Charges'!$E$9*'11.Charges'!$D$9*'9.Var.Vente1'!G5 -> 0 | H9: ='11.Charges'!$E$9*'11.Charges'!$D$9*'9.Var.Vente1'!H5 -> 0 | I9: ='11.Charges'!$E$9*'11.Charges'!$D$9*'9.Var.Vente1'!I5 -> 0 | J9: ='11.Charges'!$E$9*'11.Charges'!$D$9*'9.Var.Vente1'!J5 -> 0 | K9: ='11.Charges'!$E$9*'11.Charges'!$D$9*'9.Var.Vente1'!K5 -> 0 | ... O9: ='11.Charges'!$E$9*'11.Charges'!$D$9*'9.Var.Vente1'!O5 -> 0 | P9: ='11.Charges'!$D9*'11.Charges'!$E9*'9.Var.Vente1'!P$5 -> 0 | Q9: ='11.Charges'!$D9*'11.Charges'!$E9*'9.Var.Vente1'!Q$5 -> 0 | R9: ='11.Charges'!$D9*'11.Charges'!$E9*'9.Var.Vente1'!R$5 -> 0
A10: ='11.Charges'!A10 -> Main d'œuvre directe transformation | B10: ='11.Charges'!B10 -> 0 | C10: ='11.Charges'!C10 -> MOD2 | D10: ='11.Charges'!$E$10*'11.Charges'!$D$10*'9.Var.Vente1'!D9 -> 0 | E10: ='11.Charges'!$E$10*'11.Charges'!$D$10*'9.Var.Vente1'!E9 -> 0 | F10: ='11.Charges'!$E$10*'11.Charges'!$D$10*'9.Var.Vente1'!F9 -> 0 | G10: ='11.Charges'!$E$10*'11.Charges'!$D$10*'9.Var.Vente1'!G9 -> 0 | H10: ='11.Charges'!$E$10*'11.Charges'!$D$10*'9.Var.Vente1'!H9 -> 0 | I10: ='11.Charges'!$E$10*'11.Charges'!$D$10*'9.Var.Vente1'!I9 -> 0 | J10: ='11.Charges'!$E$10*'11.Charges'!$D$10*'9.Var.Vente1'!J9 -> 0 | K10: ='11.Charges'!$E$10*'11.Charges'!$D$10*'9.Var.Vente1'!K9 -> 0 | ... O10: ='11.Charges'!$E$10*'11.Charges'!$D$10*'9.Var.Vente1'!O9 -> 0 | P10: ='11.Charges'!$D10*'11.Charges'!$E10*'9.Var.Vente1'!P$5 -> 0 | Q10: ='11.Charges'!$D10*'11.Charges'!$E10*'9.Var.Vente1'!Q$5 -> 0 | R10: ='11.Charges'!$D10*'11.Charges'!$E10*'9.Var.Vente1'!R$5 -> 0
A11: ='11.Charges'!A11 -> Main d'œuvre directe vente de services | B11: ='11.Charges'!B11 -> 0 | C11: ='11.Charges'!C11 -> MOD3 | D11: ='11.Charges'!$D$11*'11.Charges'!$E$11*'9.Var.Vente1'!D10 -> 0 | E11: ='11.Charges'!$D$11*'11.Charges'!$E$11*'9.Var.Vente1'!E10 -> 0 | F11: ='11.Charges'!$D$11*'11.Charges'!$E$11*'9.Var.Vente1'!F10 -> 0 | G11: ='11.Charges'!$D$11*'11.Charges'!$E$11*'9.Var.Vente1'!G10 -> 0 | H11: ='11.Charges'!$D$11*'11.Charges'!$E$11*'9.Var.Vente1'!H10 -> 0 | I11: ='11.Charges'!$D$11*'11.Charges'!$E$11*'9.Var.Vente1'!I10 -> 0 | J11: ='11.Charges'!$D$11*'11.Charges'!$E$11*'9.Var.Vente1'!J10 -> 0 | K11: ='11.Charges'!$D$11*'11.Charges'!$E$11*'9.Var.Vente1'!K10 -> 0 | ... O11: ='11.Charges'!$D$11*'11.Charges'!$E$11*'9.Var.Vente1'!O10 -> 0 | P11: ='11.Charges'!$D11*'11.Charges'!$E11*'9.Var.Vente1'!P$5 -> 0 | Q11: ='11.Charges'!$D11*'11.Charges'!$E11*'9.Var.Vente1'!Q$5 -> 0 | R11: ='11.Charges'!$D11*'11.Charges'!$E11*'9.Var.Vente1'!R$5 -> 0
A12: ='11.Charges'!A12 -> Frais indirects de transformation | B12: ='11.Charges'!B12 -> 0 | C12: ='11.Charges'!C12 -> FIF1 | D12: ='11.Charges'!$D$12*'11.Charges'!$E$12*'9.Var.Vente1'!D9 -> 0 | E12: ='11.Charges'!$D$12*'11.Charges'!$E$12*'9.Var.Vente1'!E9 -> 0 | F12: ='11.Charges'!$D$12*'11.Charges'!$E$12*'9.Var.Vente1'!F9 -> 0 | G12: ='11.Charges'!$D$12*'11.Charges'!$E$12*'9.Var.Vente1'!G9 -> 0 | H12: ='11.Charges'!$D$12*'11.Charges'!$E$12*'9.Var.Vente1'!H9 -> 0 | I12: ='11.Charges'!$D$12*'11.Charges'!$E$12*'9.Var.Vente1'!I9 -> 0 | J12: ='11.Charges'!$D$12*'11.Charges'!$E$12*'9.Var.Vente1'!J9 -> 0 | K12: ='11.Charges'!$D$12*'11.Charges'!$E$12*'9.Var.Vente1'!K9 -> 0 | ... O12: ='11.Charges'!$D$12*'11.Charges'!$E$12*'9.Var.Vente1'!O9 -> 0 | P12: ='11.Charges'!$D12*'11.Charges'!$E12*'9.Var.Vente1'!P$5 -> 0 | Q12: ='11.Charges'!$D12*'11.Charges'!$E12*'9.Var.Vente1'!Q$5 -> 0 | R12: ='11.Charges'!$D12*'11.Charges'!$E12*'9.Var.Vente1'!R$5 -> 0
A13: ='11.Charges'!A13 -> Frais indirects de vente | B13: ='11.Charges'!B13 -> Logistique Tenue de luxe Homme | C13: ='11.Charges'!C13 -> FIF2 | D13: ='11.Charges'!$D$13*'11.Charges'!$E$13*'9.Var.Vente1'!D5 -> 12000 | E13: ='11.Charges'!$D$13*'11.Charges'!$E$13*'9.Var.Vente1'!E5 -> 12000 | F13: ='11.Charges'!$D$13*'11.Charges'!$E$13*'9.Var.Vente1'!F5 -> 12000 | G13: ='11.Charges'!$D$13*'11.Charges'!$E$13*'9.Var.Vente1'!G5 -> 12000 | H13: ='11.Charges'!$D$13*'11.Charges'!$E$13*'9.Var.Vente1'!H5 -> 12000 | I13: ='11.Charges'!$D$13*'11.Charges'!$E$13*'9.Var.Vente1'!I5 -> 12000 | J13: ='11.Charges'!$D$13*'11.Charges'!$E$13*'9.Var.Vente1'!J5 -> 12000 | K13: ='11.Charges'!$D$13*'11.Charges'!$E$13*'9.Var.Vente1'!K5 -> 12000 | ... O13: ='11.Charges'!$D$13*'11.Charges'!$E$13*'9.Var.Vente1'!O5 -> 12000 | P13: ='11.Charges'!$D13*'11.Charges'!$E13*'9.Var.Vente1'!P$5 -> 144000 | Q13: ='11.Charges'!$D13*'11.Charges'!$E13*'9.Var.Vente1'!Q$5 -> 158400 | R13: ='11.Charges'!$D13*'11.Charges'!$E13*'9.Var.Vente1'!R$5 -> 174240
A14: ='11.Charges'!A14 -> Frais indirects de vente | B14: ='11.Charges'!B14 -> Logistique Tenue de luxe Femme | C14: ='11.Charges'!C14 -> FIF2 | D14: ='11.Charges'!$D$13*'11.Charges'!$E$13*'9.Var.Vente1'!D6 -> 22800 | E14: ='11.Charges'!$D$13*'11.Charges'!$E$13*'9.Var.Vente1'!E6 -> 22800 | F14: ='11.Charges'!$D$13*'11.Charges'!$E$13*'9.Var.Vente1'!F6 -> 22800 | G14: ='11.Charges'!$D$13*'11.Charges'!$E$13*'9.Var.Vente1'!G6 -> 22800 | H14: ='11.Charges'!$D$13*'11.Charges'!$E$13*'9.Var.Vente1'!H6 -> 22800 | I14: ='11.Charges'!$D$13*'11.Charges'!$E$13*'9.Var.Vente1'!I6 -> 22800 | J14: ='11.Charges'!$D$13*'11.Charges'!$E$13*'9.Var.Vente1'!J6 -> 22800 | K14: ='11.Charges'!$D$13*'11.Charges'!$E$13*'9.Var.Vente1'!K6 -> 22800 | ... O14: ='11.Charges'!$D$13*'11.Charges'!$E$13*'9.Var.Vente1'!O6 -> 22800 | P14: ='11.Charges'!$D14*'11.Charges'!$E14*'9.Var.Vente1'!P$5 -> 288000 | Q14: ='11.Charges'!$D14*'11.Charges'!$E14*'9.Var.Vente1'!Q$5 -> 316800 | R14: ='11.Charges'!$D14*'11.Charges'!$E14*'9.Var.Vente1'!R$5 -> 348480
A15: ='11.Charges'!A15 -> Frais indirects de vente | B15: ='11.Charges'!B15 -> Logistique Prêt-à-porter homme | C15: ='11.Charges'!C15 -> FIF2 | D15: ='11.Charges'!$D$13*'11.Charges'!$E$13*'9.Var.Vente1'!D7 -> 48000 | E15: ='11.Charges'!$D$13*'11.Charges'!$E$13*'9.Var.Vente1'!E7 -> 48000 | F15: ='11.Charges'!$D$13*'11.Charges'!$E$13*'9.Var.Vente1'!F7 -> 48000 | G15: ='11.Charges'!$D$13*'11.Charges'!$E$13*'9.Var.Vente1'!G7 -> 48000 | H15: ='11.Charges'!$D$13*'11.Charges'!$E$13*'9.Var.Vente1'!H7 -> 48000 | I15: ='11.Charges'!$D$13*'11.Charges'!$E$13*'9.Var.Vente1'!I7 -> 48000 | J15: ='11.Charges'!$D$13*'11.Charges'!$E$13*'9.Var.Vente1'!J7 -> 48000 | K15: ='11.Charges'!$D$13*'11.Charges'!$E$13*'9.Var.Vente1'!K7 -> 48000 | ... O15: ='11.Charges'!$D$13*'11.Charges'!$E$13*'9.Var.Vente1'!O7 -> 48000 | P15: ='11.Charges'!$D15*'11.Charges'!$E15*'9.Var.Vente1'!P$5 -> 72000 | Q15: ='11.Charges'!$D15*'11.Charges'!$E15*'9.Var.Vente1'!Q$5 -> 79200 | R15: ='11.Charges'!$D15*'11.Charges'!$E15*'9.Var.Vente1'!R$5 -> 87120
A16: ='11.Charges'!A16 -> Frais indirects de vente | B16: ='11.Charges'!B16 -> Logistique Prêt-à-porter femme | C16: ='11.Charges'!C16 -> FIF2 | D16: ='11.Charges'!$D$13*'11.Charges'!$E$13*'9.Var.Vente1'!D8 -> 91200 | E16: ='11.Charges'!$D$13*'11.Charges'!$E$13*'9.Var.Vente1'!E8 -> 91200 | F16: ='11.Charges'!$D$13*'11.Charges'!$E$13*'9.Var.Vente1'!F8 -> 91200 | G16: ='11.Charges'!$D$13*'11.Charges'!$E$13*'9.Var.Vente1'!G8 -> 91200 | H16: ='11.Charges'!$D$13*'11.Charges'!$E$13*'9.Var.Vente1'!H8 -> 91200 | I16: ='11.Charges'!$D$13*'11.Charges'!$E$13*'9.Var.Vente1'!I8 -> 91200 | J16: ='11.Charges'!$D$13*'11.Charges'!$E$13*'9.Var.Vente1'!J8 -> 91200 | K16: ='11.Charges'!$D$13*'11.Charges'!$E$13*'9.Var.Vente1'!K8 -> 91200 | ... O16: ='11.Charges'!$D$13*'11.Charges'!$E$13*'9.Var.Vente1'!O8 -> 91200 | P16: ='11.Charges'!$D16*'11.Charges'!$E16*'9.Var.Vente1'!P$5 -> 36000 | Q16: ='11.Charges'!$D16*'11.Charges'!$E16*'9.Var.Vente1'!Q$5 -> 39600 | R16: ='11.Charges'!$D16*'11.Charges'!$E16*'9.Var.Vente1'!R$5 -> 43560
A17: ='11.Charges'!A17 -> Frais indirects de vente | B17: ='11.Charges'!B17 -> Stockage Tenue de luxe Homme | C17: ='11.Charges'!C17 -> FIF2 | D17: ='11.Charges'!$D$13*'11.Charges'!$E$13*'9.Var.Vente1'!D9 -> 0 | E17: ='11.Charges'!$D$13*'11.Charges'!$E$13*'9.Var.Vente1'!E9 -> 0 | F17: ='11.Charges'!$D$13*'11.Charges'!$E$13*'9.Var.Vente1'!F9 -> 0 | G17: ='11.Charges'!$D$13*'11.Charges'!$E$13*'9.Var.Vente1'!G9 -> 0 | H17: ='11.Charges'!$D$13*'11.Charges'!$E$13*'9.Var.Vente1'!H9 -> 0 | I17: ='11.Charges'!$D$13*'11.Charges'!$E$13*'9.Var.Vente1'!I9 -> 0 | J17: ='11.Charges'!$D$13*'11.Charges'!$E$13*'9.Var.Vente1'!J9 -> 0 | K17: ='11.Charges'!$D$13*'11.Charges'!$E$13*'9.Var.Vente1'!K9 -> 0 | ... O17: ='11.Charges'!$D$13*'11.Charges'!$E$13*'9.Var.Vente1'!O9 -> 0 | P17: ='11.Charges'!$D17*'11.Charges'!$E17*'9.Var.Vente1'!P$5 -> 288000 | Q17: ='11.Charges'!$D17*'11.Charges'!$E17*'9.Var.Vente1'!Q$5 -> 316800 | R17: ='11.Charges'!$D17*'11.Charges'!$E17*'9.Var.Vente1'!R$5 -> 348480
A18: ='11.Charges'!A18 -> Frais indirects de vente | B18: ='11.Charges'!B18 -> Stockage Tenue de luxe Femme | C18: ='11.Charges'!C18 -> FIF2 | D18: ='11.Charges'!$D$13*'11.Charges'!$E$13*'9.Var.Vente1'!D10 -> 0 | E18: ='11.Charges'!$D$13*'11.Charges'!$E$13*'9.Var.Vente1'!E10 -> 0 | F18: ='11.Charges'!$D$13*'11.Charges'!$E$13*'9.Var.Vente1'!F10 -> 0 | G18: ='11.Charges'!$D$13*'11.Charges'!$E$13*'9.Var.Vente1'!G10 -> 0 | H18: ='11.Charges'!$D$13*'11.Charges'!$E$13*'9.Var.Vente1'!H10 -> 0 | I18: ='11.Charges'!$D$13*'11.Charges'!$E$13*'9.Var.Vente1'!I10 -> 0 | J18: ='11.Charges'!$D$13*'11.Charges'!$E$13*'9.Var.Vente1'!J10 -> 0 | K18: ='11.Charges'!$D$13*'11.Charges'!$E$13*'9.Var.Vente1'!K10 -> 0 | ... O18: ='11.Charges'!$D$13*'11.Charges'!$E$13*'9.Var.Vente1'!O10 -> 0 | P18: ='11.Charges'!$D18*'11.Charges'!$E18*'9.Var.Vente1'!P$5 -> 576000 | Q18: ='11.Charges'!$D18*'11.Charges'!$E18*'9.Var.Vente1'!Q$5 -> 633600 | R18: ='11.Charges'!$D18*'11.Charges'!$E18*'9.Var.Vente1'!R$5 -> 696960
A19: ='11.Charges'!A19 -> Frais indirects de vente | B19: ='11.Charges'!B19 -> Stockage Prêt-à-porter homme | C19: ='11.Charges'!C19 -> FIF2 | D19: ='11.Charges'!$D$13*'11.Charges'!$E$13*'9.Var.Vente1'!D11 -> 0 | E19: ='11.Charges'!$D$13*'11.Charges'!$E$13*'9.Var.Vente1'!E11 -> 0 | F19: ='11.Charges'!$D$13*'11.Charges'!$E$13*'9.Var.Vente1'!F11 -> 0 | G19: ='11.Charges'!$D$13*'11.Charges'!$E$13*'9.Var.Vente1'!G11 -> 0 | H19: ='11.Charges'!$D$13*'11.Charges'!$E$13*'9.Var.Vente1'!H11 -> 0 | I19: ='11.Charges'!$D$13*'11.Charges'!$E$13*'9.Var.Vente1'!I11 -> 0 | J19: ='11.Charges'!$D$13*'11.Charges'!$E$13*'9.Var.Vente1'!J11 -> 0 | K19: ='11.Charges'!$D$13*'11.Charges'!$E$13*'9.Var.Vente1'!K11 -> 0 | ... O19: ='11.Charges'!$D$13*'11.Charges'!$E$13*'9.Var.Vente1'!O11 -> 0 | P19: ='11.Charges'!$D19*'11.Charges'!$E19*'9.Var.Vente1'!P$5 -> 144000 | Q19: ='11.Charges'!$D19*'11.Charges'!$E19*'9.Var.Vente1'!Q$5 -> 158400 | R19: ='11.Charges'!$D19*'11.Charges'!$E19*'9.Var.Vente1'!R$5 -> 174240
A20: ='11.Charges'!A20 -> Frais indirects de vente | B20: ='11.Charges'!B20 -> Stockage Prêt-à-porter femme | C20: ='11.Charges'!C20 -> FIF2 | D20: ='11.Charges'!$D$13*'11.Charges'!$E$13*'9.Var.Vente1'!D12 -> 43500 | E20: ='11.Charges'!$D$13*'11.Charges'!$E$13*'9.Var.Vente1'!E12 -> 43500 | F20: ='11.Charges'!$D$13*'11.Charges'!$E$13*'9.Var.Vente1'!F12 -> 43500 | G20: ='11.Charges'!$D$13*'11.Charges'!$E$13*'9.Var.Vente1'!G12 -> 43500 | H20: ='11.Charges'!$D$13*'11.Charges'!$E$13*'9.Var.Vente1'!H12 -> 43500 | I20: ='11.Charges'!$D$13*'11.Charges'!$E$13*'9.Var.Vente1'!I12 -> 43500 | J20: ='11.Charges'!$D$13*'11.Charges'!$E$13*'9.Var.Vente1'!J12 -> 43500 | K20: ='11.Charges'!$D$13*'11.Charges'!$E$13*'9.Var.Vente1'!K12 -> 43500 | ... O20: ='11.Charges'!$D$13*'11.Charges'!$E$13*'9.Var.Vente1'!O12 -> 43500 | P20: ='11.Charges'!$D20*'11.Charges'!$E20*'9.Var.Vente1'!P$5 -> 72000 | Q20: ='11.Charges'!$D20*'11.Charges'!$E20*'9.Var.Vente1'!Q$5 -> 79200 | R20: ='11.Charges'!$D20*'11.Charges'!$E20*'9.Var.Vente1'!R$5 -> 87120
A21: ='11.Charges'!A21 -> Frais indirects de vente | B21: ='11.Charges'!B21 -> Commission MP Tenue de luxe Homme | C21: ='11.Charges'!C21 -> FIF2 | D21: ='11.Charges'!$D$13*'11.Charges'!$E$13*'9.Var.Vente1'!D13 -> 0 | E21: ='11.Charges'!$D$13*'11.Charges'!$E$13*'9.Var.Vente1'!E13 -> 0 | F21: ='11.Charges'!$D$13*'11.Charges'!$E$13*'9.Var.Vente1'!F13 -> 0 | G21: ='11.Charges'!$D$13*'11.Charges'!$E$13*'9.Var.Vente1'!G13 -> 0 | H21: ='11.Charges'!$D$13*'11.Charges'!$E$13*'9.Var.Vente1'!H13 -> 0 | I21: ='11.Charges'!$D$13*'11.Charges'!$E$13*'9.Var.Vente1'!I13 -> 0 | J21: ='11.Charges'!$D$13*'11.Charges'!$E$13*'9.Var.Vente1'!J13 -> 0 | K21: ='11.Charges'!$D$13*'11.Charges'!$E$13*'9.Var.Vente1'!K13 -> 0 | ... O21: ='11.Charges'!$D$13*'11.Charges'!$E$13*'9.Var.Vente1'!O13 -> 0 | P21: ='11.Charges'!$D21*'11.Charges'!$E21*'9.Var.Vente1'!P$5 -> 144000 | Q21: ='11.Charges'!$D21*'11.Charges'!$E21*'9.Var.Vente1'!Q$5 -> 158400 | R21: ='11.Charges'!$D21*'11.Charges'!$E21*'9.Var.Vente1'!R$5 -> 174240
A22: ='11.Charges'!A22 -> Frais indirects de vente | B22: ='11.Charges'!B22 -> Commission MP Tenue de luxe Femme | C22: ='11.Charges'!C22 -> FIF2 | D22: ='11.Charges'!$D$13*'11.Charges'!$E$13*'9.Var.Vente1'!D14 -> 0 | E22: ='11.Charges'!$D$13*'11.Charges'!$E$13*'9.Var.Vente1'!E14 -> 0 | F22: ='11.Charges'!$D$13*'11.Charges'!$E$13*'9.Var.Vente1'!F14 -> 0 | G22: ='11.Charges'!$D$13*'11.Charges'!$E$13*'9.Var.Vente1'!G14 -> 0 | H22: ='11.Charges'!$D$13*'11.Charges'!$E$13*'9.Var.Vente1'!H14 -> 0 | I22: ='11.Charges'!$D$13*'11.Charges'!$E$13*'9.Var.Vente1'!I14 -> 0 | J22: ='11.Charges'!$D$13*'11.Charges'!$E$13*'9.Var.Vente1'!J14 -> 0 | K22: ='11.Charges'!$D$13*'11.Charges'!$E$13*'9.Var.Vente1'!K14 -> 0 | ... O22: ='11.Charges'!$D$13*'11.Charges'!$E$13*'9.Var.Vente1'!O14 -> 0 | P22: ='11.Charges'!$D22*'11.Charges'!$E22*'9.Var.Vente1'!P$5 -> 288000 | Q22: ='11.Charges'!$D22*'11.Charges'!$E22*'9.Var.Vente1'!Q$5 -> 316800 | R22: ='11.Charges'!$D22*'11.Charges'!$E22*'9.Var.Vente1'!R$5 -> 348480
A23: ='11.Charges'!A23 -> Frais indirects de vente | B23: ='11.Charges'!B23 -> Commission MP Prêt-à-porter homme | C23: ='11.Charges'!C23 -> FIF2 | D23: ='11.Charges'!$D$13*'11.Charges'!$E$13*'9.Var.Vente1'!D15 -> 0 | E23: ='11.Charges'!$D$13*'11.Charges'!$E$13*'9.Var.Vente1'!E15 -> 0 | F23: ='11.Charges'!$D$13*'11.Charges'!$E$13*'9.Var.Vente1'!F15 -> 0 | G23: ='11.Charges'!$D$13*'11.Charges'!$E$13*'9.Var.Vente1'!G15 -> 0 | H23: ='11.Charges'!$D$13*'11.Charges'!$E$13*'9.Var.Vente1'!H15 -> 0 | I23: ='11.Charges'!$D$13*'11.Charges'!$E$13*'9.Var.Vente1'!I15 -> 0 | J23: ='11.Charges'!$D$13*'11.Charges'!$E$13*'9.Var.Vente1'!J15 -> 0 | K23: ='11.Charges'!$D$13*'11.Charges'!$E$13*'9.Var.Vente1'!K15 -> 0 | ... O23: ='11.Charges'!$D$13*'11.Charges'!$E$13*'9.Var.Vente1'!O15 -> 0 | P23: ='11.Charges'!$D23*'11.Charges'!$E23*'9.Var.Vente1'!P$5 -> 72000 | Q23: ='11.Charges'!$D23*'11.Charges'!$E23*'9.Var.Vente1'!Q$5 -> 79200 | R23: ='11.Charges'!$D23*'11.Charges'!$E23*'9.Var.Vente1'!R$5 -> 87120
A24: ='11.Charges'!A24 -> Frais indirects de vente | B24: ='11.Charges'!B24 -> Commission MP Prêt-à-porter femme | C24: ='11.Charges'!C24 -> FIF2 | D24: ='11.Charges'!$D$13*'11.Charges'!$E$13*'9.Var.Vente1'!D16 -> 0 | E24: ='11.Charges'!$D$13*'11.Charges'!$E$13*'9.Var.Vente1'!E16 -> 0 | F24: ='11.Charges'!$D$13*'11.Charges'!$E$13*'9.Var.Vente1'!F16 -> 0 | G24: ='11.Charges'!$D$13*'11.Charges'!$E$13*'9.Var.Vente1'!G16 -> 0 | H24: ='11.Charges'!$D$13*'11.Charges'!$E$13*'9.Var.Vente1'!H16 -> 0 | I24: ='11.Charges'!$D$13*'11.Charges'!$E$13*'9.Var.Vente1'!I16 -> 0 | J24: ='11.Charges'!$D$13*'11.Charges'!$E$13*'9.Var.Vente1'!J16 -> 0 | K24: ='11.Charges'!$D$13*'11.Charges'!$E$13*'9.Var.Vente1'!K16 -> 0 | ... O24: ='11.Charges'!$D$13*'11.Charges'!$E$13*'9.Var.Vente1'!O16 -> 0 | P24: ='11.Charges'!$D24*'11.Charges'!$E24*'9.Var.Vente1'!P$5 -> 36000 | Q24: ='11.Charges'!$D24*'11.Charges'!$E24*'9.Var.Vente1'!Q$5 -> 39600 | R24: ='11.Charges'!$D24*'11.Charges'!$E24*'9.Var.Vente1'!R$5 -> 43560
A25: ='11.Charges'!A25 -> Frais indirects de vente de services | B25: ='11.Charges'!B25 -> 0 | C25: ='11.Charges'!C25 -> FIF3 | D25: ='11.Charges'!$D$25*'11.Charges'!$E$25*'9.Var.Vente1'!D10 -> 0 | E25: ='11.Charges'!$D$25*'11.Charges'!$E$25*'9.Var.Vente1'!E10 -> 0 | F25: ='11.Charges'!$D$25*'11.Charges'!$E$25*'9.Var.Vente1'!F10 -> 0 | G25: ='11.Charges'!$D$25*'11.Charges'!$E$25*'9.Var.Vente1'!G10 -> 0 | H25: ='11.Charges'!$D$25*'11.Charges'!$E$25*'9.Var.Vente1'!H10 -> 0 | I25: ='11.Charges'!$D$25*'11.Charges'!$E$25*'9.Var.Vente1'!I10 -> 0 | J25: ='11.Charges'!$D$25*'11.Charges'!$E$25*'9.Var.Vente1'!J10 -> 0 | K25: ='11.Charges'!$D$25*'11.Charges'!$E$25*'9.Var.Vente1'!K10 -> 0 | ... O25: ='11.Charges'!$D$25*'11.Charges'!$E$25*'9.Var.Vente1'!O10 -> 0 | P25: ='11.Charges'!$D25*'11.Charges'!$E25*'9.Var.Vente1'!P$5 -> 0 | Q25: ='11.Charges'!$D25*'11.Charges'!$E25*'9.Var.Vente1'!Q$5 -> 0 | R25: ='11.Charges'!$D25*'11.Charges'!$E25*'9.Var.Vente1'!R$5 -> 0
A26: ='11.Charges'!A26 -> Salaires et Avantages | B26: ='11.Charges'!B26 -> Salaire personnel | C26: ='11.Charges'!C26 -> SAV1 | D26: ='11.Charges'!$D$26*'11.Charges'!$E$26*'10.Vente'!$P$12/12 -> #VALUE! | E26: ='11.Charges'!$D$26*'11.Charges'!$E$26*'10.Vente'!$P$12/12 -> #VALUE! | F26: ='11.Charges'!$D$26*'11.Charges'!$E$26*'10.Vente'!$P$12/12 -> #VALUE! | G26: ='11.Charges'!$D$26*'11.Charges'!$E$26*'10.Vente'!$P$12/12 -> #VALUE! | H26: ='11.Charges'!$D$26*'11.Charges'!$E$26*'10.Vente'!$P$12/12 -> #VALUE! | I26: ='11.Charges'!$D$26*'11.Charges'!$E$26*'10.Vente'!$P$12/12 -> #VALUE! | J26: ='11.Charges'!$D$26*'11.Charges'!$E$26*'10.Vente'!$P$12/12 -> #VALUE! | K26: ='11.Charges'!$D$26*'11.Charges'!$E$26*'10.Vente'!$P$12/12 -> #VALUE! | ... O26: ='11.Charges'!$D$26*'11.Charges'!$E$26*'10.Vente'!$P$12/12 -> #VALUE! | P26: ='11.Charges'!$D$26*'11.Charges'!$E$26*'10.Vente'!P$12 -> #VALUE! | Q26: ='11.Charges'!$D$26*'11.Charges'!$E$26*'10.Vente'!Q$12 -> #VALUE! | R26: ='11.Charges'!$D$26*'11.Charges'!$E$26*'10.Vente'!R$12 -> #VALUE!
A27: ='11.Charges'!A27 -> Taxe et redevance | B27: ='11.Charges'!B27 -> Timbre | C27: ='11.Charges'!C27 -> TXR1 | D27: ='11.Charges'!$D$27*'11.Charges'!$E$27*'10.Vente'!D12 -> #VALUE! | E27: ='11.Charges'!$D$27*'11.Charges'!$E$27*'10.Vente'!E12 -> #VALUE! | F27: ='11.Charges'!$D$27*'11.Charges'!$E$27*'10.Vente'!F12 -> #VALUE! | G27: ='11.Charges'!$D$27*'11.Charges'!$E$27*'10.Vente'!G12 -> #VALUE! | H27: ='11.Charges'!$D$27*'11.Charges'!$E$27*'10.Vente'!H12 -> #VALUE! | I27: ='11.Charges'!$D$27*'11.Charges'!$E$27*'10.Vente'!I12 -> #VALUE! | J27: ='11.Charges'!$D$27*'11.Charges'!$E$27*'10.Vente'!J12 -> #VALUE! | K27: ='11.Charges'!$D$27*'11.Charges'!$E$27*'10.Vente'!K12 -> #VALUE! | ... R27: ='11.Charges'!$D$27*'11.Charges'!$E$27*'10.Vente'!R12 -> #VALUE!
A28: ='11.Charges'!A28 -> Impôt sur les entreprises | B28: ='11.Charges'!B28 -> BIC | C28: ='11.Charges'!C28 -> IMP1 | O28: ='11.Charges'!$D$28*'11.Charges'!$E$28*'10.Vente'!P12 -> #VALUE! | P28: ='11.Charges'!$D$28*'11.Charges'!$E$28*'10.Vente'!P12 -> #VALUE! | Q28: ='11.Charges'!$D$28*'11.Charges'!$E$28*'10.Vente'!Q12 -> #VALUE! | R28: ='11.Charges'!$D$28*'11.Charges'!$E$28*'10.Vente'!R12 -> #VALUE!
A29: ='11.Charges'!A40 -> Amortissement Exploitation | B29: ='11.Charges'!B40 -> Amortissement équipement. | C29: ='11.Charges'!C40 -> AMR1 | O29: ='11.Charges'!$D$40*'11.Charges'!$E$40*'10.Vente'!P$12 -> #VALUE! | P29: ='11.Charges'!$D$40*'11.Charges'!$E$40*'10.Vente'!P$12 -> #VALUE! | Q29: ='11.Charges'!$D$40*'11.Charges'!$E$40*'10.Vente'!Q$12 -> #VALUE! | R29: ='11.Charges'!$D$40*'11.Charges'!$E$40*'10.Vente'!R$12 -> #VALUE!

Sheet 13.Var.Char.Ind
A1: FACTEURS DE VARIATION CHARGES INDIRECTS
D2: Charges mensuelles | P2: Charges annuelles
A3: Type de charges | B3: Charge | C3: CODE | D3: 1 | E3: 2 | F3: 3 | G3: 4 | H3: 5 | I3: 6 | J3: 7 | K3: 8 | L3: 9 | M3: 10 | N3: 11 | O3: 12 | P3: N | Q3: N+1 | R3: N+2
A4: Action commerciale | B4: ='11.Charges'!B29 -> Sponsoring page réseaux sociaux | C4: ='11.Charges'!C29 -> MKT1 | D4: 1 | P4: 1 | Q4: 1 | R4: 1
A5: Frais Généraux | B5: ='11.Charges'!B30 -> Frais administration | C5: ='11.Charges'!C30 -> FG1 | D5: 1 | E5: 1 | F5: 1 | G5: 1 | H5: 1 | I5: 1 | J5: 1 | K5: 1 | L5: 1 | M5: 1 | N5: 1 | O5: 1 | P5: 1 | Q5: 1 | R5: 1
A6: Energie/Electricité/ Eau | B6: ='11.Charges'!B31 -> Eau | C6: ='11.Charges'!C31 -> EEE1 | D6: 1 | E6: 1 | F6: 1 | G6: 1 | H6: 1 | I6: 1 | J6: 1 | K6: 1 | L6: 1 | M6: 1 | N6: 1 | O6: 1 | P6: 1 | Q6: 1 | R6: 1
A7: Frais de transport | B7: ='11.Charges'!B32 -> Carburant | C7: ='11.Charges'!C32 -> FT1 | D7: 1 | E7: 1 | F7: 1 | G7: 1 | H7: 1 | I7: 1 | J7: 1 | K7: 1 | L7: 1 | M7: 1 | N7: 1 | O7: 1 | P7: 1 | Q7: 1 | R7: 1
A8: Frais de communication | B8: ='11.Charges'!B33 -> Telephone / Internet | C8: ='11.Charges'!C33 -> MKT2 | D8: 1 | E8: 1 | F8: 1 | G8: 1 | H8: 1 | I8: 1 | J8: 1 | K8: 1 | L8: 1 | M8: 1 | N8: 1 | O8: 1 | P8: 1 | Q8: 1 | R8: 1
A9: Publicité et Marketing | B9: ='11.Charges'!B34 -> 0 | C9: ='11.Charges'!C34 -> FKT3 | D9: 1 | E9: 1 | F9: 1 | G9: 1 | H9: 1 | I9: 1 | J9: 1 | K9: 1 | L9: 1 | M9: 1 | N9: 1 | O9: 1 | P9: 1 | Q9: 1 | R9: 1
A10: Location | B10: ='11.Charges'!B35 -> Loyer | C10: ='11.Charges'!C35 -> LOC1 | D10: 1 | E10: 1 | F10: 1 | G10: 1 | H10: 1 | I10: 1 | J10: 1 | K10: 1 | L10: 1 | M10: 1 | N10: 1 | O10: 1 | P10: 1 | Q10: 1 | R10: 1
A11: Assurance | B11: ='11.Charges'!B36 -> Assurance voiture | C11: ='11.Charges'!C36 -> ASS1 | D11: 1 | E11: 1 | F11: 1 | G11: 1 | H11: 1 | I11: 1 | J11: 1 | K11: 1 | L11: 1 | M11: 1 | N11: 1 | O11: 1 | P11: 1 | Q11: 1 | R11: 1
A12: Prestations et Honoraires | B12: ='11.Charges'!B37 -> Frais Infogérance | C12: ='11.Charges'!C37 -> PH1 | D12: 1 | P12: 1 | Q12: 1 | R12: 1
A13: Autres provisions | B13: ='11.Charges'!B38 -> 0 | C13: ='11.Charges'!C38 -> APR1 | D13: 1 | P13: 1 | Q13: 1 | R13: 1
A14: Amortissement Bureau | B14: ='11.Charges'!B39 -> 0 | C14: ='11.Charges'!C39 -> AMR2 | O14: 1 | P14: 1 | Q14: 1 | R14: 1

Sheet 14.Char.Ind
A1: CHARGES INDIRECTES
D2: Charges mensuelles | P2: Charges annuelles
A3: Type de charges | B3: Charge | C3: CODE | D3: 1 | E3: 2 | F3: 3 | G3: 4 | H3: 5 | I3: 6 | J3: 7 | K3: 8 | L3: 9 | M3: 10 | N3: 11 | O3: 12 | P3: N | Q3: N+1 | R3: N+2
A4: ='11.Charges'!A29 -> Action commerciale | B4: ='11.Charges'!B29 -> Sponsoring page réseaux sociaux | C4: ='11.Charges'!C29 -> MKT1 | D4: ='11.Charges'!$D29*'11.Charges'!$E29*'13.Var.Char.Ind'!D4 -> 1900000 | E4: ='11.Charges'!$D29*'11.Charges'!$E29*'13.Var.Char.Ind'!E4 -> 0 | F4: ='11.Charges'!$D29*'11.Charges'!$E29*'13.Var.Char.Ind'!F4 -> 0 | G4: ='11.Charges'!$D29*'11.Charges'!$E29*'13.Var.Char.Ind'!G4 -> 0 | H4: ='11.Charges'!$D29*'11.Charges'!$E29*'13.Var.Char.Ind'!H4 -> 0 | I4: ='11.Charges'!$D29*'11.Charges'!$E29*'13.Var.Char.Ind'!I4 -> 0 | J4: ='11.Charges'!$D29*'11.Charges'!$E29*'13.Var.Char.Ind'!J4 -> 0 | K4: ='11.Charges'!$D29*'11.Charges'!$E29*'13.Var.Char.Ind'!K4 -> 0 | ... O4: ='11.Charges'!$D29*'11.Charges'!$E29*'13.Var.Char.Ind'!O4 -> 0 | P4: =SUM(D4:O4) -> 1900000 | Q4: =P4*'13.Var.Char.Ind'!Q4 -> 1900000 | R4: =Q4*'13.Var.Char.Ind'!R4 -> 1900000
A5: ='11.Charges'!A30 -> Frais Généraux | B5: ='11.Charges'!B30 -> Frais administration | C5: ='11.Charges'!C30 -> FG1 | D5: ='11.Charges'!$D30*'11.Charges'!$E30*'13.Var.Char.Ind'!D5 -> 25000 | E5: ='11.Charges'!$D30*'11.Charges'!$E30*'13.Var.Char.Ind'!E5 -> 25000 | F5: ='11.Charges'!$D30*'11.Charges'!$E30*'13.Var.Char.Ind'!F5 -> 25000 | G5: ='11.Charges'!$D30*'11.Charges'!$E30*'13.Var.Char.Ind'!G5 -> 25000 | H5: ='11.Charges'!$D30*'11.Charges'!$E30*'13.Var.Char.Ind'!H5 -> 25000 | I5: ='11.Charges'!$D30*'11.Charges'!$E30*'13.Var.Char.Ind'!I5 -> 25000 | J5: ='11.Charges'!$D30*'11.Charges'!$E30*'13.Var.Char.Ind'!J5 -> 25000 | K5: ='11.Charges'!$D30*'11.Charges'!$E30*'13.Var.Char.Ind'!K5 -> 25000 | ... O5: ='11.Charges'!$D30*'11.Charges'!$E30*'13.Var.Char.Ind'!O5 -> 25000 | P5: =SUM(D5:O5) -> 300000 | Q5: =P5*'13.Var.Char.Ind'!Q5 -> 300000 | R5: =Q5*'13.Var.Char.Ind'!R5 -> 300000
A6: ='11.Charges'!A31 -> Energie/Electricité/ Eau | B6: ='11.Charges'!B31 -> Eau | C6: ='11.Charges'!C31 -> EEE1 | D6: ='11.Charges'!$D31*'11.Charges'!$E31*'13.Var.Char.Ind'!D6 -> 82500 | E6: ='11.Charges'!$D31*'11.Charges'!$E31*'13.Var.Char.Ind'!E6 -> 82500 | F6: ='11.Charges'!$D31*'11.Charges'!$E31*'13.Var.Char.Ind'!F6 -> 82500 | G6: ='11.Charges'!$D31*'11.Charges'!$E31*'13.Var.Char.Ind'!G6 -> 82500 | H6: ='11.Charges'!$D31*'11.Charges'!$E31*'13.Var.Char.Ind'!H6 -> 82500 | I6: ='11.Charges'!$D31*'11.Charges'!$E31*'13.Var.Char.Ind'!I6 -> 82500 | J6: ='11.Charges'!$D31*'11.Charges'!$E31*'13.Var.Char.Ind'!J6 -> 82500 | K6: ='11.Charges'!$D31*'11.Charges'!$E31*'13.Var.Char.Ind'!K6 -> 82500 | ... O6: ='11.Charges'!$D31*'11.Charges'!$E31*'13.Var.Char.Ind'!O6 -> 82500 | P6: =SUM(D6:O6) -> 990000 | Q6: =P6*'13.Var.Char.Ind'!Q6 -> 990000 | R6: =Q6*'13.Var.Char.Ind'!R6 -> 990000
A7: ='11.Charges'!A32 -> Frais de transport | B7: ='11.Charges'!B32 -> Carburant | C7: ='11.Charges'!C32 -> FT1 | D7: ='11.Charges'!$D32*'11.Charges'!$E32*'13.Var.Char.Ind'!D7 -> 50000 | E7: ='11.Charges'!$D32*'11.Charges'!$E32*'13.Var.Char.Ind'!E7 -> 50000 | F7: ='11.Charges'!$D32*'11.Charges'!$E32*'13.Var.Char.Ind'!F7 -> 50000 | G7: ='11.Charges'!$D32*'11.Charges'!$E32*'13.Var.Char.Ind'!G7 -> 50000 | H7: ='11.Charges'!$D32*'11.Charges'!$E32*'13.Var.Char.Ind'!H7 -> 50000 | I7: ='11.Charges'!$D32*'11.Charges'!$E32*'13.Var.Char.Ind'!I7 -> 50000 | J7: ='11.Charges'!$D32*'11.Charges'!$E32*'13.Var.Char.Ind'!J7 -> 50000 | K7: ='11.Charges'!$D32*'11.Charges'!$E32*'13.Var.Char.Ind'!K7 -> 50000 | ... O7: ='11.Charges'!$D32*'11.Charges'!$E32*'13.Var.Char.Ind'!O7 -> 50000 | P7: =SUM(D7:O7) -> 600000 | Q7: =P7*'13.Var.Char.Ind'!Q7 -> 600000 | R7: =Q7*'13.Var.Char.Ind'!R7 -> 600000
A8: ='11.Charges'!A33 -> Frais de communication | B8: ='11.Charges'!B33 -> Telephone / Internet | C8: ='11.Charges'!C33 -> MKT2 | D8: ='11.Charges'!$D33*'11.Charges'!$E33*'13.Var.Char.Ind'!D8 -> 50000 | E8: ='11.Charges'!$D33*'11.Charges'!$E33*'13.Var.Char.Ind'!E8 -> 50000 | F8: ='11.Charges'!$D33*'11.Charges'!$E33*'13.Var.Char.Ind'!F8 -> 50000 | G8: ='11.Charges'!$D33*'11.Charges'!$E33*'13.Var.Char.Ind'!G8 -> 50000 | H8: ='11.Charges'!$D33*'11.Charges'!$E33*'13.Var.Char.Ind'!H8 -> 50000 | I8: ='11.Charges'!$D33*'11.Charges'!$E33*'13.Var.Char.Ind'!I8 -> 50000 | J8: ='11.Charges'!$D33*'11.Charges'!$E33*'13.Var.Char.Ind'!J8 -> 50000 | K8: ='11.Charges'!$D33*'11.Charges'!$E33*'13.Var.Char.Ind'!K8 -> 50000 | ... O8: ='11.Charges'!$D33*'11.Charges'!$E33*'13.Var.Char.Ind'!O8 -> 50000 | P8: =SUM(D8:O8) -> 600000 | Q8: =P8*'13.Var.Char.Ind'!Q8 -> 600000 | R8: =Q8*'13.Var.Char.Ind'!R8 -> 600000
A9: ='11.Charges'!A34 -> Publicité et Marketing | B9: ='11.Charges'!B34 -> 0 | C9: ='11.Charges'!C34 -> FKT3 | D9: ='11.Charges'!$D34*'11.Charges'!$E34*'13.Var.Char.Ind'!D9 -> 0 | E9: ='11.Charges'!$D34*'11.Charges'!$E34*'13.Var.Char.Ind'!E9 -> 0 | F9: ='11.Charges'!$D34*'11.Charges'!$E34*'13.Var.Char.Ind'!F9 -> 0 | G9: ='11.Charges'!$D34*'11.Charges'!$E34*'13.Var.Char.Ind'!G9 -> 0 | H9: ='11.Charges'!$D34*'11.Charges'!$E34*'13.Var.Char.Ind'!H9 -> 0 | I9: ='11.Charges'!$D34*'11.Charges'!$E34*'13.Var.Char.Ind'!I9 -> 0 | J9: ='11.Charges'!$D34*'11.Charges'!$E34*'13.Var.Char.Ind'!J9 -> 0 | K9: ='11.Charges'!$D34*'11.Charges'!$E34*'13.Var.Char.Ind'!K9 -> 0 | ... O9: ='11.Charges'!$D34*'11.Charges'!$E34*'13.Var.Char.Ind'!O9 -> 0 | P9: =SUM(D9:O9) -> 0 | Q9: =P9*'13.Var.Char.Ind'!Q9 -> 0 | R9: =Q9*'13.Var.Char.Ind'!R9 -> 0
A10: ='11.Charges'!A35 -> Location | B10: ='11.Charges'!B35 -> Loyer | C10: ='11.Charges'!C35 -> LOC1 | D10: ='11.Charges'!$D35*'11.Charges'!$E35*'13.Var.Char.Ind'!D10 -> 250000 | E10: ='11.Charges'!$D35*'11.Charges'!$E35*'13.Var.Char.Ind'!E10 -> 250000 | F10: ='11.Charges'!$D35*'11.Charges'!$E35*'13.Var.Char.Ind'!F10 -> 250000 | G10: ='11.Charges'!$D35*'11.Charges'!$E35*'13.Var.Char.Ind'!G10 -> 250000 | H10: ='11.Charges'!$D35*'11.Charges'!$E35*'13.Var.Char.Ind'!H10 -> 250000 | I10: ='11.Charges'!$D35*'11.Charges'!$E35*'13.Var.Char.Ind'!I10 -> 250000 | J10: ='11.Charges'!$D35*'11.Charges'!$E35*'13.Var.Char.Ind'!J10 -> 250000 | K10: ='11.Charges'!$D35*'11.Charges'!$E35*'13.Var.Char.Ind'!K10 -> 250000 | ... O10: ='11.Charges'!$D35*'11.Charges'!$E35*'13.Var.Char.Ind'!O10 -> 250000 | P10: =SUM(D10:O10) -> 3000000 | Q10: =P10*'13.Var.Char.Ind'!Q10 -> 3000000 | R10: =Q10*'13.Var.Char.Ind'!R10 -> 3000000
A11: ='11.Charges'!A36 -> Assurance | B11: ='11.Charges'!B36 -> Assurance voiture | C11: ='11.Charges'!C36 -> ASS1 | D11: ='11.Charges'!$D36*'11.Charges'!$E36*'13.Var.Char.Ind'!D11 -> 12000 | E11: ='11.Charges'!$D36*'11.Charges'!$E36*'13.Var.Char.Ind'!E11 -> 12000 | F11: ='11.Charges'!$D36*'11.Charges'!$E36*'13.Var.Char.Ind'!F11 -> 12000 | G11: ='11.Charges'!$D36*'11.Charges'!$E36*'13.Var.Char.Ind'!G11 -> 12000 | H11: ='11.Charges'!$D36*'11.Charges'!$E36*'13.Var.Char.Ind'!H11 -> 12000 | I11: ='11.Charges'!$D36*'11.Charges'!$E36*'13.Var.Char.Ind'!I11 -> 12000 | J11: ='11.Charges'!$D36*'11.Charges'!$E36*'13.Var.Char.Ind'!J11 -> 12000 | K11: ='11.Charges'!$D36*'11.Charges'!$E36*'13.Var.Char.Ind'!K11 -> 12000 | ... O11: ='11.Charges'!$D36*'11.Charges'!$E36*'13.Var.Char.Ind'!O11 -> 12000 | P11: =SUM(D11:O11) -> 144000 | Q11: =P11*'13.Var.Char.Ind'!Q11 -> 144000 | R11: =Q11*'13.Var.Char.Ind'!R11 -> 144000
A12: ='11.Charges'!A37 -> Prestations et Honoraires | B12: ='11.Charges'!B37 -> Frais Infogérance | C12: ='11.Charges'!C37 -> PH1 | D12: ='11.Charges'!$D37*'11.Charges'!$E37*'13.Var.Char.Ind'!D12 -> 380000 | E12: ='11.Charges'!$D37*'11.Charges'!$E37*'13.Var.Char.Ind'!E12 -> 0 | F12: ='11.Charges'!$D37*'11.Charges'!$E37*'13.Var.Char.Ind'!F12 -> 0 | G12: ='11.Charges'!$D37*'11.Charges'!$E37*'13.Var.Char.Ind'!G12 -> 0 | H12: ='11.Charges'!$D37*'11.Charges'!$E37*'13.Var.Char.Ind'!H12 -> 0 | I12: ='11.Charges'!$D37*'11.Charges'!$E37*'13.Var.Char.Ind'!I12 -> 0 | J12: ='11.Charges'!$D37*'11.Charges'!$E37*'13.Var.Char.Ind'!J12 -> 0 | K12: ='11.Charges'!$D37*'11.Charges'!$E37*'13.Var.Char.Ind'!K12 -> 0 | ... O12: ='11.Charges'!$D37*'11.Charges'!$E37*'13.Var.Char.Ind'!O12 -> 0 | P12: =SUM(D12:O12) -> 380000 | Q12: =P12*'13.Var.Char.Ind'!Q12 -> 380000 | R12: =Q12*'13.Var.Char.Ind'!R12 -> 380000
A13: ='11.Charges'!A38 -> Autres provisions | B13: ='11.Charges'!B38 -> 0 | C13: ='11.Charges'!C38 -> APR1 | D13: ='11.Charges'!$D38*'11.Charges'!$E38*'13.Var.Char.Ind'!D13 -> 0 | E13: ='11.Charges'!$D38*'11.Charges'!$E38*'13.Var.Char.Ind'!E13 -> 0 | F13: ='11.Charges'!$D38*'11.Charges'!$E38*'13.Var.Char.Ind'!F13 -> 0 | G13: ='11.Charges'!$D38*'11.Charges'!$E38*'13.Var.Char.Ind'!G13 -> 0 | H13: ='11.Charges'!$D38*'11.Charges'!$E38*'13.Var.Char.Ind'!H13 -> 0 | I13: ='11.Charges'!$D38*'11.Charges'!$E38*'13.Var.Char.Ind'!I13 -> 0 | J13: ='11.Charges'!$D38*'11.Charges'!$E38*'13.Var.Char.Ind'!J13 -> 0 | K13: ='11.Charges'!$D38*'11.Charges'!$E38*'13.Var.Char.Ind'!K13 -> 0 | ... O13: ='11.Charges'!$D38*'11.Charges'!$E38*'13.Var.Char.Ind'!O13 -> 0 | P13: =SUM(D13:O13) -> 0 | Q13: =P13*'13.Var.Char.Ind'!Q13 -> 0 | R13: =Q13*'13.Var.Char.Ind'!R13 -> 0
A14: ='11.Charges'!A39 -> Amortissement Bureau | B14: ='11.Charges'!B39 -> 0 | C14: ='11.Charges'!C39 -> AMR2 | D14: ='11.Charges'!$D39*'11.Charges'!$E39*'13.Var.Char.Ind'!D14*'7.Bud.Inv.'!E22 -> #VALUE! | E14: ='11.Charges'!$D39*'11.Charges'!$E39*'13.Var.Char.Ind'!E14*'7.Bud.Inv.'!F22 -> #VALUE! | F14: ='11.Charges'!$D39*'11.Charges'!$E39*'13.Var.Char.Ind'!F14*'7.Bud.Inv.'!G22 -> #VALUE! | G14: ='11.Charges'!$D39*'11.Charges'!$E39*'13.Var.Char.Ind'!G14*'7.Bud.Inv.'!H22 -> #VALUE! | H14: ='11.Charges'!$D39*'11.Charges'!$E39*'13.Var.Char.Ind'!H14*'7.Bud.Inv.'!I22 -> #VALUE! | I14: ='11.Charges'!$D39*'11.Charges'!$E39*'13.Var.Char.Ind'!I14*'7.Bud.Inv.'!J22 -> #VALUE! | J14: ='11.Charges'!$D39*'11.Charges'!$E39*'13.Var.Char.Ind'!J14*'7.Bud.Inv.'!K22 -> #VALUE! | K14: ='11.Charges'!$D39*'11.Charges'!$E39*'13.Var.Char.Ind'!K14*'7.Bud.Inv.'!L22 -> #VALUE! | ... O14: ='11.Charges'!$D39*'11.Charges'!$E39*'13.Var.Char.Ind'!O14*'7.Bud.Inv.'!P22 -> #VALUE! | P14: ='11.Charges'!$D39*'11.Charges'!$E39*'13.Var.Char.Ind'!P14 -> 0 | Q14: ='11.Charges'!$D39*'11.Charges'!$E39*'13.Var.Char.Ind'!Q14*'7.Bud.Inv.'!R22+P14 -> #VALUE! | R14: ='11.Charges'!$D39*'11.Charges'!$E39*'13.Var.Char.Ind'!R14*'7.Bud.Inv.'!S22+Q14 -> #VALUE!

Sheet 15.Tre.Men
A1: TRESORERIE MENSUELLE
C3: MOIS
A4: Montant (FCFA) | C4: 1 | D4: 2 | E4: 3 | F4: 4 | G4: 5 | H4: 6 | I4: 7 | J4: 8 | K4: 9 | L4: 10 | M4: 11 | N4: 12
A5: SOLDE DE TRESORERIE AU DÉBUT DE PERIODE (1) | B5: CODE | C5: 0 | D5: =C25 -> #VALUE! | E5: =D25 -> #VALUE! | F5: =E25 -> #VALUE! | G5: =F25 -> #VALUE! | H5: =G25 -> #VALUE! | I5: =H25 -> #VALUE! | J5: =I25 -> #VALUE! | K5: =J25 -> #VALUE! | ... N5: =M25 -> #VALUE!
A6: RECETTES
A7: Emprunt, subvention ou apport personnel obtenus | C7: ='1.Var.Fin'!B5+'1.Var.Fin'!B11+'1.Var.Fin'!B17 -> 3775000.9
A8: CA global | C8: ='10.Vente'!D12 -> #VALUE! | D8: ='10.Vente'!E12 -> #VALUE! | E8: ='10.Vente'!F12 -> #VALUE! | F8: ='10.Vente'!G12 -> #VALUE! | G8: ='10.Vente'!H12 -> #VALUE! | H8: ='10.Vente'!I12 -> #VALUE! | I8: ='10.Vente'!J12 -> #VALUE! | J8: ='10.Vente'!K12 -> #VALUE! | ... N8: ='10.Vente'!O12 -> #VALUE!
A9: TOTAL DES RECETTES (2) | C9: =SUM(C7:C8) -> #VALUE! | D9: =SUM(D7:D8) -> #VALUE! | E9: =SUM(E7:E8) -> #VALUE! | F9: =SUM(F7:F8) -> #VALUE! | G9: =SUM(G7:G8) -> #VALUE! | H9: =SUM(H7:H8) -> #VALUE! | I9: =SUM(I7:I8) -> #VALUE! | J9: =SUM(J7:J8) -> #VALUE! | ... N9: =SUM(N7:N8) -> #VALUE!
A10: INVESTISSEMENT
A11: Total investissement (3) | C11: ='7.Bud.Inv.'!E22 -> #VALUE! | D11: ='7.Bud.Inv.'!F22 -> #VALUE! | E11: ='7.Bud.Inv.'!G22 -> #VALUE! | F11: ='7.Bud.Inv.'!H22 -> #VALUE! | G11: ='7.Bud.Inv.'!I22 -> #VALUE! | H11: ='7.Bud.Inv.'!J22 -> #VALUE! | I11: ='7.Bud.Inv.'!K22 -> #VALUE! | J11: ='7.Bud.Inv.'!L22 -> #VALUE! | ... N11: ='7.Bud.Inv.'!P22 -> #VALUE!
A12: ACHAT ET CHARGES ASSIMILEES
A13: Total des achats et charges assimilées (4) | C13: =SUM('12.Char.Dir'!D4:D25) -> 1567500 | D13: =SUM('12.Char.Dir'!E4:E25) -> 1567500 | E13: =SUM('12.Char.Dir'!F4:F25) -> 1567500 | F13: =SUM('12.Char.Dir'!G4:G25) -> 1567500 | G13: =SUM('12.Char.Dir'!H4:H25) -> 1567500 | H13: =SUM('12.Char.Dir'!I4:I25) -> 1567500 | I13: =SUM('12.Char.Dir'!J4:J25) -> 1567500 | J13: =SUM('12.Char.Dir'!K4:K25) -> 1567500 | ... N13: =SUM('12.Char.Dir'!O4:O25) -> 1567500
A14: SERVICES EXTERIEURS ET AUTRES CHARGES
A15: Services extérieurs | C15: =SUM('14.Char.Ind'!D4:D13) -> 2749500 | D15: =SUM('14.Char.Ind'!E4:E13) -> 469500 | E15: =SUM('14.Char.Ind'!F4:F13) -> 469500 | F15: =SUM('14.Char.Ind'!G4:G13) -> 469500 | G15: =SUM('14.Char.Ind'!H4:H13) -> 469500 | H15: =SUM('14.Char.Ind'!I4:I13) -> 469500 | I15: =SUM('14.Char.Ind'!J4:J13) -> 469500 | J15: =SUM('14.Char.Ind'!K4:K13) -> 469500 | ... N15: =SUM('14.Char.Ind'!O4:O13) -> 469500
A16: Salaires et charges sociales | C16: =SUM('12.Char.Dir'!D26) -> #VALUE! | D16: =SUM('12.Char.Dir'!E26) -> #VALUE! | E16: =SUM('12.Char.Dir'!F26) -> #VALUE! | F16: =SUM('12.Char.Dir'!G26) -> #VALUE! | G16: =SUM('12.Char.Dir'!H26) -> #VALUE! | H16: =SUM('12.Char.Dir'!I26) -> #VALUE! | I16: =SUM('12.Char.Dir'!J26) -> #VALUE! | J16: =SUM('12.Char.Dir'!K26) -> #VALUE! | ... N16: =SUM('12.Char.Dir'!O26) -> #VALUE!
A17: Impôts et Taxes aux entreprises | C17: =SUM('12.Char.Dir'!D27:D28) -> #VALUE! | D17: =SUM('12.Char.Dir'!E27:E28) -> #VALUE! | E17: =SUM('12.Char.Dir'!F27:F28) -> #VALUE! | F17: =SUM('12.Char.Dir'!G27:G28) -> #VALUE! | G17: =SUM('12.Char.Dir'!H27:H28) -> #VALUE! | H17: =SUM('12.Char.Dir'!I27:I28) -> #VALUE! | I17: =SUM('12.Char.Dir'!J27:J28) -> #VALUE! | J17: =SUM('12.Char.Dir'!K27:K28) -> #VALUE! | ... N17: =SUM('12.Char.Dir'!O27:O28) -> #VALUE!
A18: Total des services extérieurs et autres charges (6) | C18: =SUM(C15:C17) -> #VALUE! | D18: =SUM(D15:D17) -> #VALUE! | E18: =SUM(E15:E17) -> #VALUE! | F18: =SUM(F15:F17) -> #VALUE! | G18: =SUM(G15:G17) -> #VALUE! | H18: =SUM(H15:H17) -> #VALUE! | I18: =SUM(I15:I17) -> #VALUE! | J18: =SUM(J15:J17) -> #VALUE! | ... N18: =SUM(N15:N17) -> #VALUE!
A19: Remboursement estimé des emprunts à court terme | C19: =SUMIF('2.Cal.Amo.CT'!$A$10:$A$21,C$4,'2.Cal.Amo.CT'!$E$10:$E$21) -> 288928.56 | D19: =SUMIF('2.Cal.Amo.CT'!$A$10:$A$21,D$4,'2.Cal.Amo.CT'!$E$10:$E$21) -> 292299.39 | E19: =SUMIF('2.Cal.Amo.CT'!$A$10:$A$21,E$4,'2.Cal.Amo.CT'!$E$10:$E$21) -> 295709.55 | F19: =SUMIF('2.Cal.Amo.CT'!$A$10:$A$21,F$4,'2.Cal.Amo.CT'!$E$10:$E$21) -> 299159.49 | G19: =SUMIF('2.Cal.Amo.CT'!$A$10:$A$21,G$4,'2.Cal.Amo.CT'!$E$10:$E$21) -> 302649.69 | H19: =SUMIF('2.Cal.Amo.CT'!$A$10:$A$21,H$4,'2.Cal.Amo.CT'!$E$10:$E$21) -> 306180.6 | I19: =SUMIF('2.Cal.Amo.CT'!$A$10:$A$21,I$4,'2.Cal.Amo.CT'!$E$10:$E$21) -> 309752.71 | J19: =SUMIF('2.Cal.Amo.CT'!$A$10:$A$21,J$4,'2.Cal.Amo.CT'!$E$10:$E$21) -> 313366.49 | ... N19: =SUMIF('2.Cal.Amo.CT'!$A$10:$A$21,N$4,'2.Cal.Amo.CT'!$E$10:$E$21) -> 328248.17
A20: Frais d'intérêt- Concours bancaires | C20: =SUMIF('2.Cal.Amo.CT'!$A$10:$A$21,C$4,'2.Cal.Amo.CT'!$C$10:$C$21) -> 43149.177 | D20: =SUMIF('2.Cal.Amo.CT'!$A$10:$A$21,D$4,'2.Cal.Amo.CT'!$C$10:$C$21) -> 39778.344 | E20: =SUMIF('2.Cal.Amo.CT'!$A$10:$A$21,E$4,'2.Cal.Amo.CT'!$C$10:$C$21) -> 36368.184 | F20: =SUMIF('2.Cal.Amo.CT'!$A$10:$A$21,F$4,'2.Cal.Amo.CT'!$C$10:$C$21) -> 32918.239 | G20: =SUMIF('2.Cal.Amo.CT'!$A$10:$A$21,G$4,'2.Cal.Amo.CT'!$C$10:$C$21) -> 29428.045 | H20: =SUMIF('2.Cal.Amo.CT'!$A$10:$A$21,H$4,'2.Cal.Amo.CT'!$C$10:$C$21) -> 25897.132 | I20: =SUMIF('2.Cal.Amo.CT'!$A$10:$A$21,I$4,'2.Cal.Amo.CT'!$C$10:$C$21) -> 22325.025 | J20: =SUMIF('2.Cal.Amo.CT'!$A$10:$A$21,J$4,'2.Cal.Amo.CT'!$C$10:$C$21) -> 18711.244 | ... N20: =SUMIF('2.Cal.Amo.CT'!$A$10:$A$21,N$4,'2.Cal.Amo.CT'!$C$10:$C$21) -> 3829.562
A21: Remboursement estimé des emprunts à long terme | C21: =(SUMIF('3.Cal.Amo.LT'!$A:$A,"n",'3.Cal.Amo.LT'!$E:$E)+SUMIF('4.Cal.Amo.AI'!$A:$A,"n",'4.Cal.Amo.AI'!$E:$E))/12 -> 1944.7241 | D21: =(SUMIF('3.Cal.Amo.LT'!$A:$A,"n",'3.Cal.Amo.LT'!$E:$E)+SUMIF('4.Cal.Amo.AI'!$A:$A,"n",'4.Cal.Amo.AI'!$E:$E))/12 -> 1944.7241 | E21: =(SUMIF('3.Cal.Amo.LT'!$A:$A,"n",'3.Cal.Amo.LT'!$E:$E)+SUMIF('4.Cal.Amo.AI'!$A:$A,"n",'4.Cal.Amo.AI'!$E:$E))/12 -> 1944.7241 | F21: =(SUMIF('3.Cal.Amo.LT'!$A:$A,"n",'3.Cal.Amo.LT'!$E:$E)+SUMIF('4.Cal.Amo.AI'!$A:$A,"n",'4.Cal.Amo.AI'!$E:$E))/12 -> 1944.7241 | G21: =(SUMIF('3.Cal.Amo.LT'!$A:$A,"n",'3.Cal.Amo.LT'!$E:$E)+SUMIF('4.Cal.Amo.AI'!$A:$A,"n",'4.Cal.Amo.AI'!$E:$E))/12 -> 1944.7241 | H21: =(SUMIF('3.Cal.Amo.LT'!$A:$A,"n",'3.Cal.Amo.LT'!$E:$E)+SUMIF('4.Cal.Amo.AI'!$A:$A,"n",'4.Cal.Amo.AI'!$E:$E))/12 -> 1944.7241 | I21: =(SUMIF('3.Cal.Amo.LT'!$A:$A,"n",'3.Cal.Amo.LT'!$E:$E)+SUMIF('4.Cal.Amo.AI'!$A:$A,"n",'4.Cal.Amo.AI'!$E:$E))/12 -> 1944.7241 | J21: =(SUMIF('3.Cal.Amo.LT'!$A:$A,"n",'3.Cal.Amo.LT'!$E:$E)+SUMIF('4.Cal.Amo.AI'!$A:$A,"n",'4.Cal.Amo.AI'!$E:$E))/12 -> 1944.7241 | ... N21: =(SUMIF('3.Cal.Amo.LT'!$A:$A,"n",'3.Cal.Amo.LT'!$E:$E)+SUMIF('4.Cal.Amo.AI'!$A:$A,"n",'4.Cal.Amo.AI'!$E:$E))/12 -> 1944.7241
A22: Frais d'intérêt - Emprunts à long terme | C22: =(SUMIF('3.Cal.Amo.LT'!$A:$A,"n",'3.Cal.Amo.LT'!$C:$C)+SUMIF('4.Cal.Amo.AI'!$A:$A,"n",'4.Cal.Amo.AI'!$C:$C))/12 -> 573.75 | D22: =(SUMIF('3.Cal.Amo.LT'!$A:$A,"n",'3.Cal.Amo.LT'!$C:$C)+SUMIF('4.Cal.Amo.AI'!$A:$A,"n",'4.Cal.Amo.AI'!$C:$C))/12 -> 573.75 | E22: =(SUMIF('3.Cal.Amo.LT'!$A:$A,"n",'3.Cal.Amo.LT'!$C:$C)+SUMIF('4.Cal.Amo.AI'!$A:$A,"n",'4.Cal.Amo.AI'!$C:$C))/12 -> 573.75 | F22: =(SUMIF('3.Cal.Amo.LT'!$A:$A,"n",'3.Cal.Amo.LT'!$C:$C)+SUMIF('4.Cal.Amo.AI'!$A:$A,"n",'4.Cal.Amo.AI'!$C:$C))/12 -> 573.75 | G22: =(SUMIF('3.Cal.Amo.LT'!$A:$A,"n",'3.Cal.Amo.LT'!$C:$C)+SUMIF('4.Cal.Amo.AI'!$A:$A,"n",'4.Cal.Amo.AI'!$C:$C))/12 -> 573.75 | H22: =(SUMIF('3.Cal.Amo.LT'!$A:$A,"n",'3.Cal.Amo.LT'!$C:$C)+SUMIF('4.Cal.Amo.AI'!$A:$A,"n",'4.Cal.Amo.AI'!$C:$C))/12 -> 573.75 | I22: =(SUMIF('3.Cal.Amo.LT'!$A:$A,"n",'3.Cal.Amo.LT'!$C:$C)+SUMIF('4.Cal.Amo.AI'!$A:$A,"n",'4.Cal.Amo.AI'!$C:$C))/12 -> 573.75 | J22: =(SUMIF('3.Cal.Amo.LT'!$A:$A,"n",'3.Cal.Amo.LT'!$C:$C)+SUMIF('4.Cal.Amo.AI'!$A:$A,"n",'4.Cal.Amo.AI'!$C:$C))/12 -> 573.75 | ... N22: =(SUMIF('3.Cal.Amo.LT'!$A:$A,"n",'3.Cal.Amo.LT'!$C:$C)+SUMIF('4.Cal.Amo.AI'!$A:$A,"n",'4.Cal.Amo.AI'!$C:$C))/12 -> 573.75
A23: Total des remboursements (7) | C23: =SUM(C19:C22) -> 334596.21 | D23: =SUM(D19:D22) -> 334596.21 | E23: =SUM(E19:E22) -> 334596.21 | F23: =SUM(F19:F22) -> 334596.21 | G23: =SUM(G19:G22) -> 334596.21 | H23: =SUM(H19:H22) -> 334596.21 | I23: =SUM(I19:I22) -> 334596.21 | J23: =SUM(J19:J22) -> 334596.21 | ... N23: =SUM(N19:N22) -> 334596.21
A24: Total des dépenses (8) = (3) + (4) + (5) + (6) + (7) | C24: =C11+C13+C18+C23 -> #VALUE! | D24: 17850149 | E24: 5922813.9 | F24: 5922813.9 | G24: 5922813.9 | H24: 5922813.9 | I24: 5922813.9 | J24: 5922813.9 | K24: 5922813.9 | L24: 5922813.9 | M24: 5922813.9 | N24: 14421022
A25: SOLDE DE FIN DE PERIODE (9) = (1)+(2)-(8) | C25: =C5+C9-C24 -> #VALUE! | D25: =D5+D9-D24 -> #VALUE! | E25: =E5+E9-E24 -> #VALUE! | F25: =F5+F9-F24 -> #VALUE! | G25: =G5+G9-G24 -> #VALUE! | H25: =H5+H9-H24 -> #VALUE! | I25: =I5+I9-I24 -> #VALUE! | J25: =J5+J9-J24 -> #VALUE! | ... N25: =N5+N9-N24 -> #VALUE!

Sheet 16.CR
A1: COMPTE DE RESULTATS SYSCOHADA
A2: Compte de résultats
B5: Designation | C5: N | D5: N+1 | E5: N+2
A6: Chiffre d'affaires | B6: Chiffre d'affaires
A7: ='8.Prod'!A4 -> Ventes de marchandises | B7: ='8.Prod'!B4 -> CA de Tenue de luxe Homme | C7: =SUMIF('10.Vente'!$A:$A,$A7,'10.Vente'!P:P) -> #VALUE! | D7: =SUMIF('10.Vente'!$A:$A,$A7,'10.Vente'!Q:Q) -> #VALUE! | E7: =SUMIF('10.Vente'!$A:$A,$A7,'10.Vente'!R:R) -> #VALUE!
A8: ='8.Prod'!A8 -> Ventes de produits fabriqués | B8: ='8.Prod'!B8 -> 0 | C8: =SUMIF('10.Vente'!$A:$A,$A8,'10.Vente'!P:P) -> 0 | D8: =SUMIF('10.Vente'!$A:$A,$A8,'10.Vente'!Q:Q) -> 0 | E8: =SUMIF('10.Vente'!$A:$A,$A8,'10.Vente'!R:R) -> 0
A9: ='8.Prod'!A9 -> Vente de services | B9: ='8.Prod'!B9 -> 0 | C9: =SUMIF('10.Vente'!$A:$A,$A9,'10.Vente'!P:P) -> 0 | D9: =SUMIF('10.Vente'!$A:$A,$A9,'10.Vente'!Q:Q) -> 0 | E9: =SUMIF('10.Vente'!$A:$A,$A9,'10.Vente'!R:R) -> 0
A10: ='8.Prod'!A10 -> Ventes d'autre produits | B10: ='8.Prod'!B10 -> 0 | C10: =SUMIF('10.Vente'!$A:$A,$A10,'10.Vente'!P:P) -> 0 | D10: =SUMIF('10.Vente'!$A:$A,$A10,'10.Vente'!Q:Q) -> 0 | E10: =SUMIF('10.Vente'!$A:$A,$A10,'10.Vente'!R:R) -> 0
A11: Total Chiffre d'Affaires | B11: Total Chiffre d'Affaires | C11: =SUM(C7:C10) -> #VALUE! | D11: =SUM(D7:D10) -> #VALUE! | E11: =SUM(E7:E10) -> #VALUE!
A12: Consommation intermédiaires | B12: Consommation intermédiaires
A13: ='11.Charges'!A4 -> Achat de marchandises | B13: ='11.Charges'!B4 -> Achat de Tenue de luxe Homme | C13: =SUMIF('12.Char.Dir'!$A:$A,$A13,'12.Char.Dir'!P:P) -> 16200000 | D13: =SUMIF('12.Char.Dir'!$A:$A,$A13,'12.Char.Dir'!Q:Q) -> 17820000 | E13: =SUMIF('12.Char.Dir'!$A:$A,$A13,'12.Char.Dir'!R:R) -> 19602000
A14: ='11.Charges'!A8 -> Achat de MP | B14: ='11.Charges'!B8 -> 0 | C14: =SUMIF('12.Char.Dir'!$A:$A,$A14,'12.Char.Dir'!P:P) -> 0 | D14: =SUMIF('12.Char.Dir'!$A:$A,$A14,'12.Char.Dir'!Q:Q) -> 0 | E14: =SUMIF('12.Char.Dir'!$A:$A,$A14,'12.Char.Dir'!R:R) -> 0
A15: ='11.Charges'!A9 -> Main d'œuvre directe vente | B15: ='11.Charges'!B9 -> 0 | C15: =SUMIF('12.Char.Dir'!$A:$A,$A15,'12.Char.Dir'!P:P) -> 0 | D15: =SUMIF('12.Char.Dir'!$A:$A,$A15,'12.Char.Dir'!Q:Q) -> 0 | E15: =SUMIF('12.Char.Dir'!$A:$A,$A15,'12.Char.Dir'!R:R) -> 0
A16: ='11.Charges'!A10 -> Main d'œuvre directe transformation | B16: ='11.Charges'!B10 -> 0 | C16: =SUMIF('12.Char.Dir'!$A:$A,$A16,'12.Char.Dir'!P:P) -> 0 | D16: =SUMIF('12.Char.Dir'!$A:$A,$A16,'12.Char.Dir'!Q:Q) -> 0 | E16: =SUMIF('12.Char.Dir'!$A:$A,$A16,'12.Char.Dir'!R:R) -> 0
A17: ='11.Charges'!A11 -> Main d'œuvre directe vente de services | B17: ='11.Charges'!B11 -> 0 | C17: =SUMIF('12.Char.Dir'!$A:$A,$A17,'12.Char.Dir'!P:P) -> 0 | D17: =SUMIF('12.Char.Dir'!$A:$A,$A17,'12.Char.Dir'!Q:Q) -> 0 | E17: =SUMIF('12.Char.Dir'!$A:$A,$A17,'12.Char.Dir'!R:R) -> 0
A18: ='11.Charges'!A12 -> Frais indirects de transformation | B18: ='11.Charges'!B12 -> 0 | C18: =SUMIF('12.Char.Dir'!$A:$A,$A18,'12.Char.Dir'!P:P) -> 0 | D18: =SUMIF('12.Char.Dir'!$A:$A,$A18,'12.Char.Dir'!Q:Q) -> 0 | E18: =SUMIF('12.Char.Dir'!$A:$A,$A18,'12.Char.Dir'!R:R) -> 0
A19: ='11.Charges'!A13 -> Frais indirects de vente | B19: ='11.Charges'!B13 -> Logistique Tenue de luxe Homme | C19: =SUMIF('12.Char.Dir'!$A:$A,$A19,'12.Char.Dir'!P:P) -> 2160000 | D19: =SUMIF('12.Char.Dir'!$A:$A,$A19,'12.Char.Dir'!Q:Q) -> 2376000 | E19: =SUMIF('12.Char.Dir'!$A:$A,$A19,'12.Char.Dir'!R:R) -> 2613600
A20: ='11.Charges'!A25 -> Frais indirects de vente de services | B20: ='11.Charges'!B25 -> 0 | C20: =SUMIF('12.Char.Dir'!$A:$A,$A20,'12.Char.Dir'!P:P) -> 0 | D20: =SUMIF('12.Char.Dir'!$A:$A,$A20,'12.Char.Dir'!Q:Q) -> 0 | E20: =SUMIF('12.Char.Dir'!$A:$A,$A20,'12.Char.Dir'!R:R) -> 0
A21: Total consommation intermédiaires | B21: Total consommation intermédiaires | C21: =SUM(C13:C20) -> 18360000 | D21: =SUM(D13:D20) -> 20196000 | E21: =SUM(E13:E20) -> 22215600
A22: Marge brute | B22: Marge brute | C22: =C11-C21 -> #VALUE! | D22: =D11-D21 -> #VALUE! | E22: =E11-E21 -> #VALUE!
A23: Charges d'exploitation | B23: Charges d'exploitation
A24: ='11.Charges'!A29 -> Action commerciale | B24: ='11.Charges'!B29 -> Sponsoring page réseaux sociaux | C24: =SUMIF('14.Char.Ind'!$A:$A,$A24,'14.Char.Ind'!P:P) -> 1900000 | D24: =SUMIF('14.Char.Ind'!$A:$A,$A24,'14.Char.Ind'!Q:Q) -> 1900000 | E24: =SUMIF('14.Char.Ind'!$A:$A,$A24,'14.Char.Ind'!R:R) -> 1900000
A25: ='11.Charges'!A30 -> Frais Généraux | B25: ='11.Charges'!B30 -> Frais administration | C25: =SUMIF('14.Char.Ind'!$A:$A,$A25,'14.Char.Ind'!P:P) -> 300000 | D25: =SUMIF('14.Char.Ind'!$A:$A,$A25,'14.Char.Ind'!Q:Q) -> 300000 | E25: =SUMIF('14.Char.Ind'!$A:$A,$A25,'14.Char.Ind'!R:R) -> 300000
A26: ='11.Charges'!A31 -> Energie/Electricité/ Eau | B26: ='11.Charges'!B31 -> Eau | C26: =SUMIF('14.Char.Ind'!$A:$A,$A26,'14.Char.Ind'!P:P) -> 990000 | D26: =SUMIF('14.Char.Ind'!$A:$A,$A26,'14.Char.Ind'!Q:Q) -> 990000 | E26: =SUMIF('14.Char.Ind'!$A:$A,$A26,'14.Char.Ind'!R:R) -> 990000
A27: ='11.Charges'!A32 -> Frais de transport | B27: ='11.Charges'!B32 -> Carburant | C27: =SUMIF('14.Char.Ind'!$A:$A,$A27,'14.Char.Ind'!P:P) -> 600000 | D27: =SUMIF('14.Char.Ind'!$A:$A,$A27,'14.Char.Ind'!Q:Q) -> 600000 | E27: =SUMIF('14.Char.Ind'!$A:$A,$A27,'14.Char.Ind'!R:R) -> 600000
A28: ='11.Charges'!A33 -> Frais de communication | B28: ='11.Charges'!B33 -> Telephone / Internet | C28: =SUMIF('14.Char.Ind'!$A:$A,$A28,'14.Char.Ind'!P:P) -> 600000 | D28: =SUMIF('14.Char.Ind'!$A:$A,$A28,'14.Char.Ind'!Q:Q) -> 600000 | E28: =SUMIF('14.Char.Ind'!$A:$A,$A28,'14.Char.Ind'!R:R) -> 600000
A29: ='11.Charges'!A34 -> Publicité et Marketing | B29: ='11.Charges'!B34 -> 0 | C29: =SUMIF('14.Char.Ind'!$A:$A,$A29,'14.Char.Ind'!P:P) -> 0 | D29: =SUMIF('14.Char.Ind'!$A:$A,$A29,'14.Char.Ind'!Q:Q) -> 0 | E29: =SUMIF('14.Char.Ind'!$A:$A,$A29,'14.Char.Ind'!R:R) -> 0
A30: ='11.Charges'!A35 -> Location | B30: ='11.Charges'!B35 -> Loyer | C30: =SUMIF('14.Char.Ind'!$A:$A,$A30,'14.Char.Ind'!P:P) -> 3000000 | D30: =SUMIF('14.Char.Ind'!$A:$A,$A30,'14.Char.Ind'!Q:Q) -> 3000000 | E30: =SUMIF('14.Char.Ind'!$A:$A,$A30,'14.Char.Ind'!R:R) -> 3000000
A31: ='11.Charges'!A36 -> Assurance | B31: ='11.Charges'!B36 -> Assurance voiture | C31: =SUMIF('14.Char.Ind'!$A:$A,$A31,'14.Char.Ind'!P:P) -> 144000 | D31: =SUMIF('14.Char.Ind'!$A:$A,$A31,'14.Char.Ind'!Q:Q) -> 144000 | E31: =SUMIF('14.Char.Ind'!$A:$A,$A31,'14.Char.Ind'!R:R) -> 144000
A32: ='11.Charges'!A37 -> Prestations et Honoraires | B32: ='11.Charges'!B37 -> Frais Infogérance | C32: =SUMIF('14.Char.Ind'!$A:$A,$A32,'14.Char.Ind'!P:P) -> 380000 | D32: =SUMIF('14.Char.Ind'!$A:$A,$A32,'14.Char.Ind'!Q:Q) -> 380000 | E32: =SUMIF('14.Char.Ind'!$A:$A,$A32,'14.Char.Ind'!R:R) -> 380000
A33: ='11.Charges'!A38 -> Autres provisions | B33: ='11.Charges'!B38 -> 0 | C33: =SUMIF('14.Char.Ind'!$A:$A,$A33,'14.Char.Ind'!P:P) -> 0 | D33: =SUMIF('14.Char.Ind'!$A:$A,$A33,'14.Char.Ind'!Q:Q) -> 0 | E33: =SUMIF('14.Char.Ind'!$A:$A,$A33,'14.Char.Ind'!R:R) -> 0
A34: ='11.Charges'!A27 -> Taxe et redevance | B34: ='11.Charges'!B27 -> Timbre | C34: =SUMIF('12.Char.Dir'!$A:$A,$A34,'12.Char.Dir'!P:P) -> #VALUE! | D34: =SUMIF('12.Char.Dir'!$A:$A,$A34,'12.Char.Dir'!Q:Q) -> #VALUE! | E34: =SUMIF('12.Char.Dir'!$A:$A,$A34,'12.Char.Dir'!R:R) -> #VALUE!
A35: ='11.Charges'!A26 -> Salaires et Avantages | B35: ='11.Charges'!B26 -> Salaire personnel | C35: =SUMIF('12.Char.Dir'!$A:$A,$A35,'12.Char.Dir'!P:P) -> #VALUE! | D35: =SUMIF('12.Char.Dir'!$A:$A,$A35,'12.Char.Dir'!Q:Q) -> #VALUE! | E35: =SUMIF('12.Char.Dir'!$A:$A,$A35,'12.Char.Dir'!R:R) -> #VALUE!
A36: Total charges d'exploitation | B36: Total charges d'exploitation | C36: =SUM(C24:C35) -> #VALUE! | D36: =SUM(D24:D35) -> #VALUE! | E36: =SUM(E24:E35) -> #VALUE!
A38: Résultat d'activité ordinaire | B38: Résultat d'activité ordinaire | C38: =C22-C36 -> #VALUE! | D38: =D22-D36 -> #VALUE! | E38: =E22-E36 -> #VALUE!
A39: Amortissement | B39: Amortissement | C39: ='12.Char.Dir'!P29+'14.Char.Ind'!P14 -> #VALUE! | D39: ='12.Char.Dir'!Q29+'14.Char.Ind'!Q14 -> #VALUE! | E39: ='12.Char.Dir'!R29+'14.Char.Ind'!R14 -> #VALUE!
A40: Frais financier | B40: Frais financier | C40: =SUMIF('2.Cal.Amo.CT'!$G:$G,C$5,'2.Cal.Amo.CT'!$C:$C)+SUMIF('3.Cal.Amo.LT'!$A:$A,'16.CR'!C$5,'3.Cal.Amo.LT'!$C:$C)+SUMIF('4.Cal.Amo.AI'!$A:$A,'16.CR'!C$5,'4.Cal.Amo.AI'!$C:$C) -> 293316.92 | D40: =SUMIF('2.Cal.Amo.CT'!$G:$G,D$5,'2.Cal.Amo.CT'!$C:$C)+SUMIF('3.Cal.Amo.LT'!$A:$A,'16.CR'!D$5,'3.Cal.Amo.LT'!$C:$C)+SUMIF('4.Cal.Amo.AI'!$A:$A,'16.CR'!D$5,'4.Cal.Amo.AI'!$C:$C) -> 4784.698 | E40: =SUMIF('2.Cal.Amo.CT'!$G:$G,E$5,'2.Cal.Amo.CT'!$C:$C)+SUMIF('3.Cal.Amo.LT'!$A:$A,'16.CR'!E$5,'3.Cal.Amo.LT'!$C:$C)+SUMIF('4.Cal.Amo.AI'!$A:$A,'16.CR'!E$5,'4.Cal.Amo.AI'!$C:$C) -> 2495.3688
A41: Résultat d'activité avant impôts | B41: Résultat d'activité avant impôts | C41: =C38-C39-C40 -> #VALUE! | D41: =D38-D39-D40 -> #VALUE! | E41: =E38-E39-E40 -> #VALUE!
A42: Impôt sur les entreprises | B42: Impôt sur les entreprises | C42: ='12.Char.Dir'!P28 -> #VALUE! | D42: ='12.Char.Dir'!Q28 -> #VALUE! | E42: ='12.Char.Dir'!R28 -> #VALUE!
A43: Profit ou perte | B43: Profit ou perte | C43: =C41-C42 -> #VALUE! | D43: =D41-D42 -> #VALUE! | E43: =E41-E42 -> #VALUE!
A44: Taux de profitabilité | B44: Taux de profitabilité | C44: =C43/C11 -> #VALUE! | D44: =D43/D11 -> #VALUE! | E44: =E43/E11 -> #VALUE!
A45: Cash-flow | B45: Cash-flow | C45: =C43+C39 -> #VALUE! | D45: =D43+D39 -> #VALUE! | E45: =E43+E39 -> #VALUE!

Sheet 17.Tre.An
A1: TRESORERIE ANNUELLE
C3: ANNEE
A4: Montant (FCFA) | C4: N | D4: N+1 | E4: N+2
A5: SOLDE DE TRESORERIE AU DÉBUT DE PERIODE (1) | B5: CODE | C5: 0 | D5: =C25 -> #VALUE! | E5: =D25 -> #VALUE!
A6: RECETTES
A7: Emprunt, subvention ou apport personnel obtenus | C7: ='1.Var.Fin'!B5+'1.Var.Fin'!B11+'1.Var.Fin'!B17 -> 3775000.9
A8: CA global | C8: ='10.Vente'!P12 -> #VALUE! | D8: ='10.Vente'!Q12 -> #VALUE! | E8: ='10.Vente'!R12 -> #VALUE!
A9: TOTAL DES RECETTES (2) | C9: =SUM(C7:C8) -> #VALUE! | D9: =SUM(D7:D8) -> #VALUE! | E9: =SUM(E7:E8) -> #VALUE!
A10: INVESTISSEMENT
A11: Total investissement (3) | C11: ='7.Bud.Inv.'!E22 -> #VALUE! | D11: ='7.Bud.Inv.'!F22 -> #VALUE! | E11: ='7.Bud.Inv.'!P22 -> #VALUE!
A12: ACHAT ET CHARGES ASSIMILEES
A13: Total des achats et charges assimilées (4) | C13: =SUM('12.Char.Dir'!P4:P25) -> 18360000 | D13: =SUM('12.Char.Dir'!Q4:Q25) -> 20196000 | E13: =SUM('12.Char.Dir'!R4:R25) -> 22215600
A14: SERVICES EXTERIEURS ET AUTRES CHARGES
A15: Services extérieurs | C15: =SUM('14.Char.Ind'!P4:P13) -> 7914000 | D15: =SUM('14.Char.Ind'!Q4:Q13) -> 7914000 | E15: =SUM('14.Char.Ind'!R4:R13) -> 7914000
A16: Salaires et charges sociales | C16: =SUM('12.Char.Dir'!P26) -> #VALUE! | D16: =SUM('12.Char.Dir'!Q26) -> #VALUE! | E16: =SUM('12.Char.Dir'!R26) -> #VALUE!
A17: Impôts et Taxes aux entreprises | C17: =SUM('12.Char.Dir'!P27:P28) -> #VALUE! | D17: =SUM('12.Char.Dir'!Q27:Q28) -> #VALUE! | E17: =SUM('12.Char.Dir'!R27:R28) -> #VALUE!
A18: Total des services extérieurs et autres charges (6) | C18: =SUM(C15:C17) -> #VALUE! | D18: =SUM(D15:D17) -> #VALUE! | E18: =SUM(E15:E17) -> #VALUE!
A19: Remboursement estimé des emprunts à court terme | C19: =SUMIF('2.Cal.Amo.CT'!$G:$G,C$4,'2.Cal.Amo.CT'!$E:$E) -> 3698500.9 | D19: =SUMIF('2.Cal.Amo.CT'!$G:$G,D$4,'2.Cal.Amo.CT'!$E:$E) -> 0 | E19: =SUMIF('2.Cal.Amo.CT'!$G:$G,E$4,'2.Cal.Amo.CT'!$E:$E) -> 0
A20: Frais d'intérêt- Concours bancaires | C20: =SUMIF('2.Cal.Amo.CT'!$G:$G,C$4,'2.Cal.Amo.CT'!$C:$C) -> 286431.92 | D20: =SUMIF('2.Cal.Amo.CT'!$G:$G,D$4,'2.Cal.Amo.CT'!$C:$C) -> 0 | E20: =SUMIF('2.Cal.Amo.CT'!$G:$G,E$4,'2.Cal.Amo.CT'!$C:$C) -> 0
A21: Remboursement estimé des emprunts à long terme | C21: =(SUMIF('3.Cal.Amo.LT'!$A:$A,C$4,'3.Cal.Amo.LT'!$E:$E)+SUMIF('4.Cal.Amo.AI'!$A:$A,C$4,'4.Cal.Amo.AI'!$E:$E)) -> 23336.689 | D21: =(SUMIF('3.Cal.Amo.LT'!$A:$A,D$4,'3.Cal.Amo.LT'!$E:$E)+SUMIF('4.Cal.Amo.AI'!$A:$A,D$4,'4.Cal.Amo.AI'!$E:$E)) -> 25436.991 | E21: =(SUMIF('3.Cal.Amo.LT'!$A:$A,E$4,'3.Cal.Amo.LT'!$E:$E)+SUMIF('4.Cal.Amo.AI'!$A:$A,E$4,'4.Cal.Amo.AI'!$E:$E)) -> 27726.32
A22: Frais d'intérêt - Emprunts à long terme | C22: =(SUMIF('3.Cal.Amo.LT'!$A:$A,C$4,'3.Cal.Amo.LT'!$C:$C)+SUMIF('4.Cal.Amo.AI'!$A:$A,C$4,'4.Cal.Amo.AI'!$C:$C)) -> 6885 | D22: =(SUMIF('3.Cal.Amo.LT'!$A:$A,D$4,'3.Cal.Amo.LT'!$C:$C)+SUMIF('4.Cal.Amo.AI'!$A:$A,D$4,'4.Cal.Amo.AI'!$C:$C)) -> 4784.698 | E22: =(SUMIF('3.Cal.Amo.LT'!$A:$A,E$4,'3.Cal.Amo.LT'!$C:$C)+SUMIF('4.Cal.Amo.AI'!$A:$A,E$4,'4.Cal.Amo.AI'!$C:$C)) -> 2495.3688
A23: Total des remboursements (7) | C23: =SUM(C19:C22) -> 4015154.5 | D23: =SUM(D19:D22) -> 30221.689 | E23: =SUM(E19:E22) -> 30221.689
A24: Total des dépenses (8) = (3) + (4) + (5) + (6) + (7) | C24: =C11+C13+C18+C23 -> #VALUE! | D24: =D11+D13+D18+D23 -> #VALUE! | E24: =E11+E13+E18+E23 -> #VALUE! | G24: La formule n'avait pas été copiée sur n1 et n2
A25: SOLDE DE FIN DE PERIODE (9) = (1)+(2)-(8) | C25: =C5+C9-C24 -> #VALUE! | D25: =D5+D9-D24 -> #VALUE! | E25: =E5+E9-E24 -> #VALUE!

Sheet 18.Van
A1: VALEUR ACTUALISEE NETTE
B4: Année | C4: Financement | D4: CAF | E4: Total Cash Flow | F4: Valeur Actuelle | G4: VAN Cumulée
B5: 0 | C5: =-'17.Tre.An'!C7 -> -3775000.9 | E5: =C5+D5 -> -3775000.9 | F5: =E5/(1+$J$5)^$B5 -> -3775000.9 | G5: =F5 -> -3775000.9 | I5: Taux de rendement | J5: 0.1
B6: 1 | C6: =-'17.Tre.An'!D7 -> 0 | D6: {=TRANSPOSE('16.CR'!C45:E45)} -> #VALUE! | E6: =C6+D6 -> #VALUE! | F6: =E6/(1+$J$5)^$B6 -> #VALUE! | G6: =F6+G5 -> #VALUE!
B7: 2 | C7: =-'17.Tre.An'!E7 -> 0 | D7: #VALUE! | E7: =C7+D7 -> #VALUE! | F7: =E7/(1+$J$5)^$B7 -> #VALUE! | G7: =F7+G6 -> #VALUE!
B8: 3 | D8: #VALUE! | E8: =C8+D8 -> #VALUE! | F8: =E8/(1+$J$5)^$B8 -> #VALUE! | G8: =F8+G7 -> #VALUE!
B9: 4 | D9: =D8 -> #VALUE! | E9: =C9+D9 -> #VALUE! | F9: =E9/(1+$J$5)^$B9 -> #VALUE! | G9: =F9+G8 -> #VALUE!
B10: 5 | D10: =D9 -> #VALUE! | E10: =C10+D10 -> #VALUE! | F10: =E10/(1+$J$5)^$B10 -> #VALUE! | G10: =F10+G9 -> #VALUE!
E11: VAN | F11: =SUM(F5:F10) -> #VALUE!
E12: TRI | F12: =IRR(G5:G10) -> #VALUE!
E13: Délai de récupération
F15: Changé la référence à l'année

Sheet 19.Bilan
A1: BILAN
B3: Montant en FCFA | C3: N | D3: N+1 | E3: N+2
B4: Actif
C5: Net | D5: Net | E5: Net
B6: Actifs immobilisés | C6: =SUM('7.Bud.Inv.'!$Q22:Q22)-'12.Char.Dir'!P29-'14.Char.Ind'!P14 -> #VALUE! | D6: =C6-'12.Char.Dir'!Q29-'14.Char.Ind'!Q14 -> #VALUE! | E6: =D6-'12.Char.Dir'!R29-'14.Char.Ind'!R14 -> #VALUE! | G6: Les amortissements de la période sont déduits du net de la période précedente.
B7: Actif circulant | C7: ='17.Tre.An'!C25 -> #VALUE! | D7: ='17.Tre.An'!D25 -> #VALUE! | E7: ='17.Tre.An'!E25 -> #VALUE!
B8: Total | C8: =C7+C6 -> #VALUE! | D8: =D7+D6 -> #VALUE! | E8: =E7+E6 -> #VALUE!
B9: Passif
C10: Net | D10: Net | E10: Net
B11: Capitaux et résultat | C11: =SUM(C12:C14) -> #VALUE! | D11: =SUM(D12:D14) -> #VALUE! | E11: =SUM(E12:E14) -> #VALUE!
B12: Résultat net | C12: ='16.CR'!C45-'16.CR'!C39 -> #VALUE! | D12: ='16.CR'!D45-'16.CR'!D39 -> #VALUE! | E12: ='16.CR'!E45-'16.CR'!E39 -> #VALUE!
B13: Capital et avoir des actionnaires | C13: =IF('1.Var.Fin'!B$19<=0,'1.Var.Fin'!B$17,0) -> 0 | D13: =IF('1.Var.Fin'!C$19<=0,'1.Var.Fin'!C$17,0) -> 0 | E13: =IF('1.Var.Fin'!D$19<=0,'1.Var.Fin'!D$17,0) -> 0
B14: Report à nouveau | C14: 0 | D14: =C14+C12 -> #VALUE! | E14: =D14+D12 -> #VALUE!
B15: Dettes financières | C15: =SUM(C16:C16) -> 53163.311 | D15: =SUM(D16:D16) -> 27726.32 | E15: =SUM(E16:E16) -> 0
B16: Dettes à long terme | C16: ='1.Var.Fin'!$B$5-SUM('17.Tre.An'!$C21:C21) -> 53163.311 | D16: ='1.Var.Fin'!$B$5-SUM('17.Tre.An'!$C21:D21) -> 27726.32 | E16: ='1.Var.Fin'!$B$5-SUM('17.Tre.An'!$C21:E21) -> 0
B17: Passif circulant | C17: 0 | D17: 0 | E17: 0
B18: Total | C18: =C17+C15+C11 -> #VALUE! | D18: =D17+D15+D11 -> #VALUE! | E18: =E17+E15+E11 -> #VALUE!
C20: =C18-C8 -> #VALUE! | D20: =D18-D8 -> #VALUE! | E20: =E18-E8 -> #VALUE!
E21: =E20-D20 -> #VALUE!

Sheet 20.CR IFRS
A1: COMPTE DE RESULTATS IFRS
B3: Designation | C3: N | D3: N+1 | E3: N+2
A4: ='8.Prod'!A4 -> Ventes de marchandises | B4: ='8.Prod'!B4 -> CA de Tenue de luxe Homme | C4: =SUMIF('10.Vente'!$A:$A,'20.CR IFRS'!$A4,'10.Vente'!P:P) -> #VALUE! | D4: =SUMIF('10.Vente'!$A:$A,'20.CR IFRS'!$A4,'10.Vente'!Q:Q) -> #VALUE! | E4: =SUMIF('10.Vente'!$A:$A,'20.CR IFRS'!$A4,'10.Vente'!R:R) -> #VALUE!
A5: ='8.Prod'!A8 -> Ventes de produits fabriqués | B5: ='8.Prod'!B8 -> 0 | C5: =SUMIF('10.Vente'!$A:$A,'20.CR IFRS'!$A5,'10.Vente'!P:P) -> 0 | D5: =SUMIF('10.Vente'!$A:$A,'20.CR IFRS'!$A5,'10.Vente'!Q:Q) -> 0 | E5: =SUMIF('10.Vente'!$A:$A,'20.CR IFRS'!$A5,'10.Vente'!R:R) -> 0
A6: ='8.Prod'!A9 -> Vente de services | B6: ='8.Prod'!B9 -> 0 | C6: =SUMIF('10.Vente'!$A:$A,'20.CR IFRS'!$A6,'10.Vente'!P:P) -> 0 | D6: =SUMIF('10.Vente'!$A:$A,'20.CR IFRS'!$A6,'10.Vente'!Q:Q) -> 0 | E6: =SUMIF('10.Vente'!$A:$A,'20.CR IFRS'!$A6,'10.Vente'!R:R) -> 0
A7: ='8.Prod'!A10 -> Ventes d'autre produits | B7: ='8.Prod'!B10 -> 0 | C7: =SUMIF('10.Vente'!$A:$A,'20.CR IFRS'!$A7,'10.Vente'!P:P) -> 0 | D7: =SUMIF('10.Vente'!$A:$A,'20.CR IFRS'!$A7,'10.Vente'!Q:Q) -> 0 | E7: =SUMIF('10.Vente'!$A:$A,'20.CR IFRS'!$A7,'10.Vente'!R:R) -> 0
A8: Total Revenu | B8: Total Revenu | C8: =SUM(C4:C7) -> #VALUE! | D8: =SUM(D4:D7) -> #VALUE! | E8: =SUM(E4:E7) -> #VALUE!
A9: ='11.Charges'!A4 -> Achat de marchandises | B9: ='11.Charges'!B4 -> Achat de Tenue de luxe Homme | C9: =SUMIF('12.Char.Dir'!$A:$A,'20.CR IFRS'!$A9,'12.Char.Dir'!P:P) -> 16200000 | D9: =SUMIF('12.Char.Dir'!$A:$A,'20.CR IFRS'!$A9,'12.Char.Dir'!Q:Q) -> 17820000 | E9: =SUMIF('12.Char.Dir'!$A:$A,'20.CR IFRS'!$A9,'12.Char.Dir'!R:R) -> 19602000
A10: ='11.Charges'!A8 -> Achat de MP | B10: ='11.Charges'!B8 -> 0 | C10: =SUMIF('12.Char.Dir'!$A:$A,'20.CR IFRS'!$A10,'12.Char.Dir'!P:P) -> 0 | D10: =SUMIF('12.Char.Dir'!$A:$A,'20.CR IFRS'!$A10,'12.Char.Dir'!Q:Q) -> 0 | E10: =SUMIF('12.Char.Dir'!$A:$A,'20.CR IFRS'!$A10,'12.Char.Dir'!R:R) -> 0
A11: ='11.Charges'!A9 -> Main d'œuvre directe vente | B11: ='11.Charges'!B9 -> 0 | C11: =SUMIF('12.Char.Dir'!$A:$A,'20.CR IFRS'!$A11,'12.Char.Dir'!P:P) -> 0 | D11: =SUMIF('12.Char.Dir'!$A:$A,'20.CR IFRS'!$A11,'12.Char.Dir'!Q:Q) -> 0 | E11: =SUMIF('12.Char.Dir'!$A:$A,'20.CR IFRS'!$A11,'12.Char.Dir'!R:R) -> 0
A12: ='11.Charges'!A10 -> Main d'œuvre directe transformation | B12: ='11.Charges'!B10 -> 0 | C12: =SUMIF('12.Char.Dir'!$A:$A,'20.CR IFRS'!$A12,'12.Char.Dir'!P:P) -> 0 | D12: =SUMIF('12.Char.Dir'!$A:$A,'20.CR IFRS'!$A12,'12.Char.Dir'!Q:Q) -> 0 | E12: =SUMIF('12.Char.Dir'!$A:$A,'20.CR IFRS'!$A12,'12.Char.Dir'!R:R) -> 0
A13: ='11.Charges'!A11 -> Main d'œuvre directe vente de services | B13: ='11.Charges'!B11 -> 0 | C13: =SUMIF('12.Char.Dir'!$A:$A,'20.CR IFRS'!$A13,'12.Char.Dir'!P:P) -> 0 | D13: =SUMIF('12.Char.Dir'!$A:$A,'20.CR IFRS'!$A13,'12.Char.Dir'!Q:Q) -> 0 | E13: =SUMIF('12.Char.Dir'!$A:$A,'20.CR IFRS'!$A13,'12.Char.Dir'!R:R) -> 0
A14: ='11.Charges'!A12 -> Frais indirects de transformation | B14: ='11.Charges'!B12 -> 0 | C14: =SUMIF('12.Char.Dir'!$A:$A,'20.CR IFRS'!$A14,'12.Char.Dir'!P:P) -> 0 | D14: =SUMIF('12.Char.Dir'!$A:$A,'20.CR IFRS'!$A14,'12.Char.Dir'!Q:Q) -> 0 | E14: =SUMIF('12.Char.Dir'!$A:$A,'20.CR IFRS'!$A14,'12.Char.Dir'!R:R) -> 0
A15: ='11.Charges'!A13 -> Frais indirects de vente | B15: ='11.Charges'!B13 -> Logistique Tenue de luxe Homme | C15: =SUMIF('12.Char.Dir'!$A:$A,'20.CR IFRS'!$A15,'12.Char.Dir'!P:P) -> 2160000 | D15: =SUMIF('12.Char.Dir'!$A:$A,'20.CR IFRS'!$A15,'12.Char.Dir'!Q:Q) -> 2376000 | E15: =SUMIF('12.Char.Dir'!$A:$A,'20.CR IFRS'!$A15,'12.Char.Dir'!R:R) -> 2613600
A16: ='11.Charges'!A25 -> Frais indirects de vente de services | B16: ='11.Charges'!B25 -> 0 | C16: =SUMIF('12.Char.Dir'!$A:$A,'20.CR IFRS'!$A16,'12.Char.Dir'!P:P) -> 0 | D16: =SUMIF('12.Char.Dir'!$A:$A,'20.CR IFRS'!$A16,'12.Char.Dir'!Q:Q) -> 0 | E16: =SUMIF('12.Char.Dir'!$A:$A,'20.CR IFRS'!$A16,'12.Char.Dir'!R:R) -> 0
A17: Coût des Marchandises et services vendue | B17: Coût des Marchandises et services vendue | C17: =SUM(C9:C16) -> 18360000 | D17: =SUM(D9:D16) -> 20196000 | E17: =SUM(E9:E16) -> 22215600
A18: Marge brute | B18: Marge brute | C18: =C8-C17 -> #VALUE! | D18: =D8-D17 -> #VALUE! | E18: =E8-E17 -> #VALUE!
A19: Taux de Marge brute | B19: Taux de Marge brute | C19: =C18/C$8 -> #VALUE! | D19: =D18/D$8 -> #VALUE! | E19: =E18/E$8 -> #VALUE!
A20: ='11.Charges'!A29 -> Action commerciale | B20: ='11.Charges'!B29 -> Sponsoring page réseaux sociaux | C20: =SUMIF('14.Char.Ind'!$A:$A,'20.CR IFRS'!$A20,'14.Char.Ind'!P:P) -> 1900000 | D20: =SUMIF('14.Char.Ind'!$A:$A,'20.CR IFRS'!$A20,'14.Char.Ind'!Q:Q) -> 1900000 | E20: =SUMIF('14.Char.Ind'!$A:$A,'20.CR IFRS'!$A20,'14.Char.Ind'!R:R) -> 1900000
A21: ='11.Charges'!A30 -> Frais Généraux | B21: ='11.Charges'!B30 -> Frais administration | C21: =SUMIF('14.Char.Ind'!$A:$A,'20.CR IFRS'!$A21,'14.Char.Ind'!P:P) -> 300000 | D21: =SUMIF('14.Char.Ind'!$A:$A,'20.CR IFRS'!$A21,'14.Char.Ind'!Q:Q) -> 300000 | E21: =SUMIF('14.Char.Ind'!$A:$A,'20.CR IFRS'!$A21,'14.Char.Ind'!R:R) -> 300000
A22: ='11.Charges'!A31 -> Energie/Electricité/ Eau | B22: ='11.Charges'!B31 -> Eau | C22: =SUMIF('14.Char.Ind'!$A:$A,'20.CR IFRS'!$A22,'14.Char.Ind'!P:P) -> 990000 | D22: =SUMIF('14.Char.Ind'!$A:$A,'20.CR IFRS'!$A22,'14.Char.Ind'!Q:Q) -> 990000 | E22: =SUMIF('14.Char.Ind'!$A:$A,'20.CR IFRS'!$A22,'14.Char.Ind'!R:R) -> 990000
A23: ='11.Charges'!A32 -> Frais de transport | B23: ='11.Charges'!B32 -> Carburant | C23: =SUMIF('14.Char.Ind'!$A:$A,'20.CR IFRS'!$A23,'14.Char.Ind'!P:P) -> 600000 | D23: =SUMIF('14.Char.Ind'!$A:$A,'20.CR IFRS'!$A23,'14.Char.Ind'!Q:Q) -> 600000 | E23: =SUMIF('14.Char.Ind'!$A:$A,'20.CR IFRS'!$A23,'14.Char.Ind'!R:R) -> 600000
A24: ='11.Charges'!A33 -> Frais de communication | B24: ='11.Charges'!B33 -> Telephone / Internet | C24: =SUMIF('14.Char.Ind'!$A:$A,'20.CR IFRS'!$A24,'14.Char.Ind'!P:P) -> 600000 | D24: =SUMIF('14.Char.Ind'!$A:$A,'20.CR IFRS'!$A24,'14.Char.Ind'!Q:Q) -> 600000 | E24: =SUMIF('14.Char.Ind'!$A:$A,'20.CR IFRS'!$A24,'14.Char.Ind'!R:R) -> 600000
A25: ='11.Charges'!A34 -> Publicité et Marketing | B25: ='11.Charges'!B34 -> 0 | C25: =SUMIF('14.Char.Ind'!$A:$A,'20.CR IFRS'!$A25,'14.Char.Ind'!P:P) -> 0 | D25: =SUMIF('14.Char.Ind'!$A:$A,'20.CR IFRS'!$A25,'14.Char.Ind'!Q:Q) -> 0 | E25: =SUMIF('14.Char.Ind'!$A:$A,'20.CR IFRS'!$A25,'14.Char.Ind'!R:R) -> 0
A26: ='11.Charges'!A35 -> Location | B26: ='11.Charges'!B35 -> Loyer | C26: =SUMIF('14.Char.Ind'!$A:$A,'20.CR IFRS'!$A26,'14.Char.Ind'!P:P) -> 3000000 | D26: =SUMIF('14.Char.Ind'!$A:$A,'20.CR IFRS'!$A26,'14.Char.Ind'!Q:Q) -> 3000000 | E26: =SUMIF('14.Char.Ind'!$A:$A,'20.CR IFRS'!$A26,'14.Char.Ind'!R:R) -> 3000000
A27: ='11.Charges'!A36 -> Assurance | B27: ='11.Charges'!B36 -> Assurance voiture | C27: =SUMIF('14.Char.Ind'!$A:$A,'20.CR IFRS'!$A27,'14.Char.Ind'!P:P) -> 144000 | D27: =SUMIF('14.Char.Ind'!$A:$A,'20.CR IFRS'!$A27,'14.Char.Ind'!Q:Q) -> 144000 | E27: =SUMIF('14.Char.Ind'!$A:$A,'20.CR IFRS'!$A27,'14.Char.Ind'!R:R) -> 144000
A28: ='11.Charges'!A37 -> Prestations et Honoraires | B28: ='11.Charges'!B37 -> Frais Infogérance | C28: =SUMIF('14.Char.Ind'!$A:$A,'20.CR IFRS'!$A28,'14.Char.Ind'!P:P) -> 380000 | D28: =SUMIF('14.Char.Ind'!$A:$A,'20.CR IFRS'!$A28,'14.Char.Ind'!Q:Q) -> 380000 | E28: =SUMIF('14.Char.Ind'!$A:$A,'20.CR IFRS'!$A28,'14.Char.Ind'!R:R) -> 380000
A29: ='11.Charges'!A38 -> Autres provisions | B29: ='11.Charges'!B38 -> 0 | C29: =SUMIF('14.Char.Ind'!$A:$A,'20.CR IFRS'!$A29,'14.Char.Ind'!P:P) -> 0 | D29: =SUMIF('14.Char.Ind'!$A:$A,'20.CR IFRS'!$A29,'14.Char.Ind'!Q:Q) -> 0 | E29: =SUMIF('14.Char.Ind'!$A:$A,'20.CR IFRS'!$A29,'14.Char.Ind'!R:R) -> 0
A30: ='11.Charges'!A27 -> Taxe et redevance | B30: ='11.Charges'!B27 -> Timbre | C30: =SUMIF('12.Char.Dir'!$A:$A,'20.CR IFRS'!$A30,'12.Char.Dir'!P:P) -> #VALUE! | D30: =SUMIF('12.Char.Dir'!$A:$A,'20.CR IFRS'!$A30,'12.Char.Dir'!Q:Q) -> #VALUE! | E30: =SUMIF('12.Char.Dir'!$A:$A,'20.CR IFRS'!$A30,'12.Char.Dir'!R:R) -> #VALUE!
A31: ='11.Charges'!A26 -> Salaires et Avantages | B31: ='11.Charges'!B26 -> Salaire personnel | C31: =SUMIF('12.Char.Dir'!$A:$A,'20.CR IFRS'!$A31,'12.Char.Dir'!P:P) -> #VALUE! | D31: =SUMIF('12.Char.Dir'!$A:$A,'20.CR IFRS'!$A31,'12.Char.Dir'!Q:Q) -> #VALUE! | E31: =SUMIF('12.Char.Dir'!$A:$A,'20.CR IFRS'!$A31,'12.Char.Dir'!R:R) -> #VALUE!
A32: Charges d'exploitation | B32: Charges d'exploitation | C32: =SUM(C20:C31) -> #VALUE! | D32: =SUM(D20:D31) -> #VALUE! | E32: =SUM(E20:E31) -> #VALUE!
A33: EBITDA | B33: EBITDA | C33: =C18-C32 -> #VALUE! | D33: =D18-D32 -> #VALUE! | E33: =E18-E32 -> #VALUE!
A34: Taux d'EBITDA | B34: Taux d'EBITDA | C34: =C33/C$8 -> #VALUE! | D34: =D33/D$8 -> #VALUE! | E34: =E33/E$8 -> #VALUE!
A35: Amortissement et dépréciation | B35: Amortissement et dépréciation | C35: ='12.Char.Dir'!P29+'14.Char.Ind'!P14 -> #VALUE! | D35: ='12.Char.Dir'!Q29+'14.Char.Ind'!Q14 -> #VALUE! | E35: ='12.Char.Dir'!R29+'14.Char.Ind'!R14 -> #VALUE!
A36: EBIT | B36: EBIT | C36: =C33-C35 -> #VALUE! | D36: =D33-D35 -> #VALUE! | E36: =E33-E35 -> #VALUE!
A37: Charges financières | B37: Charges financières | C37: =SUMIF('2.Cal.Amo.CT'!$G:$G,'20.CR IFRS'!C$3,'2.Cal.Amo.CT'!$C:$C)+SUMIF('3.Cal.Amo.LT'!$A:$A,C$3,'3.Cal.Amo.LT'!$C:$C)+SUMIF('4.Cal.Amo.AI'!$A:$A,C$3,'4.Cal.Amo.AI'!$C:$C) -> 293316.92 | D37: =SUMIF('2.Cal.Amo.CT'!$G:$G,'20.CR IFRS'!D$3,'2.Cal.Amo.CT'!$C:$C)+SUMIF('3.Cal.Amo.LT'!$A:$A,D$3,'3.Cal.Amo.LT'!$C:$C)+SUMIF('4.Cal.Amo.AI'!$A:$A,D$3,'4.Cal.Amo.AI'!$C:$C) -> 4784.698 | E37: =SUMIF('2.Cal.Amo.CT'!$G:$G,'20.CR IFRS'!E$3,'2.Cal.Amo.CT'!$C:$C)+SUMIF('3.Cal.Amo.LT'!$A:$A,E$3,'3.Cal.Amo.LT'!$C:$C)+SUMIF('4.Cal.Amo.AI'!$A:$A,E$3,'4.Cal.Amo.AI'!$C:$C) -> 2495.3688
A38: Total des charges | B38: Total des charges | C38: =C32+C17+C35+C37 -> #VALUE! | D38: =D32+D17+D35+D37 -> #VALUE! | E38: =E32+E17+E35+E37 -> #VALUE!
A39: Résultat av. Impôt | B39: Résultat av. Impôt | C39: =C8-C38 -> #VALUE! | D39: =D8-D38 -> #VALUE! | E39: =E8-E38 -> #VALUE!
A40: Impôt sur les entreprises | B40: Impôt sur les entreprises | C40: ='12.Char.Dir'!P28 -> #VALUE! | D40: ='12.Char.Dir'!Q28 -> #VALUE! | E40: ='12.Char.Dir'!R28 -> #VALUE!
A41: Résultat net | B41: Résultat net | C41: =C39-C40 -> #VALUE! | D41: =D39-D40 -> #VALUE! | E41: =E39-E40 -> #VALUE!
A42: Taux de profitabilité | B42: Taux de profitabilité | C42: =C41/C$8 -> #VALUE! | D42: =D41/D$8 -> #VALUE! | E42: =E41/E$8 -> #VALUE!
A43: Amortissement et dépréciation | B43: Amortissement et dépréciation | C43: =C35 -> #VALUE! | D43: =D35 -> #VALUE! | E43: =E35 -> #VALUE!
A44: CAF | B44: CAF | C44: =C41+C43 -> #VALUE! | D44: =D41+D43 -> #VALUE! | E44: =E41+E43 -> #VALUE!
C46: AN1 | D46: AN2 | E46: AN3

Sheet 21.BFR
A1: BESOIN EN FONDS DE ROULEMENT
A3: Type de charges | B3: Charge | C3: Quantité | D3: Montant | E3: Nb de mois | F3: Type de financement | G3: Total
A4: ='11.Charges'!A4 -> Achat de marchandises | B4: ='11.Charges'!B4 -> Achat de Tenue de luxe Homme | C4: ='11.Charges'!D4 -> 1 | D4: ='11.Charges'!E4 -> 6000 | E4: 3 | F4: EMP1 | G4: =C4*D4*E4 -> 18000
A5: ='11.Charges'!A5 -> Achat de marchandises | B5: ='11.Charges'!B5 -> Achat de Tenue de luxe Femme | C5: ='11.Charges'!D5 -> 1 | D5: ='11.Charges'!E5 -> 12000 | E5: 3 | F5: EMP1 | G5: =C5*D5*E5 -> 36000
A6: ='11.Charges'!A6 -> Achat de marchandises | B6: ='11.Charges'!B6 -> Achat de Prêt-à-porter homme | C6: ='11.Charges'!D6 -> 1 | D6: ='11.Charges'!E6 -> 3000 | E6: 3 | F6: EMP1 | G6: =C6*D6*E6 -> 9000
A7: ='11.Charges'!A7 -> Achat de marchandises | B7: ='11.Charges'!B7 -> Achat de Prêt-à-porter femme | C7: ='11.Charges'!D7 -> 1 | D7: ='11.Charges'!E7 -> 1500 | E7: 3 | F7: EMP1 | G7: =C7*D7*E7 -> 4500
A8: ='11.Charges'!A8 -> Achat de MP | B8: ='11.Charges'!B8 -> 0 | C8: ='11.Charges'!D8 -> 1 | D8: ='11.Charges'!E8 -> 0 | E8: 3 | F8: EMP1 | G8: =C8*D8*E8 -> 0
A9: ='11.Charges'!A8 -> Achat de MP | B9: ='11.Charges'!B8 -> 0 | C9: ='11.Charges'!D8 -> 1 | D9: ='11.Charges'!E8 -> 0 | E9: 3 | F9: EMP1 | G9: =C9*D9*E9 -> 0
A10: ='11.Charges'!A9 -> Main d'œuvre directe vente | B10: ='11.Charges'!B9 -> 0 | C10: ='11.Charges'!D9 -> 1 | D10: ='11.Charges'!E9 -> 0 | E10: 3 | F10: EMP1 | G10: =C10*D10*E10 -> 0
A11: ='11.Charges'!A10 -> Main d'œuvre directe transformation | B11: ='11.Charges'!B10 -> 0 | C11: ='11.Charges'!D10 -> 1 | D11: ='11.Charges'!E10 -> 0 | E11: 3 | F11: EMP1 | G11: =C11*D11*E11 -> 0
A12: ='11.Charges'!A11 -> Main d'œuvre directe vente de services | B12: ='11.Charges'!B11 -> 0 | C12: ='11.Charges'!D11 -> 1 | D12: ='11.Charges'!E11 -> 0 | E12: 3 | F12: EMP1 | G12: =C12*D12*E12 -> 0
A13: ='11.Charges'!A12 -> Frais indirects de transformation | B13: ='11.Charges'!B12 -> 0 | C13: ='11.Charges'!D12 -> 1 | D13: ='11.Charges'!E12 -> 0 | E13: 3 | F13: EMP1 | G13: =C13*D13*E13 -> 0
A14: ='11.Charges'!A13 -> Frais indirects de vente | B14: ='11.Charges'!B13 -> Logistique Tenue de luxe Homme | C14: ='11.Charges'!D13 -> 1 | D14: ='11.Charges'!E13 -> 200 | E14: 3 | F14: EMP1 | G14: =C14*D14*E14 -> 600
A15: ='11.Charges'!A14 -> Frais indirects de vente | B15: ='11.Charges'!B14 -> Logistique Tenue de luxe Femme | C15: ='11.Charges'!D14 -> 1 | D15: ='11.Charges'!E14 -> 400 | E15: 3 | F15: EMP1 | G15: =C15*D15*E15 -> 1200
A16: ='11.Charges'!A15 -> Frais indirects de vente | B16: ='11.Charges'!B15 -> Logistique Prêt-à-porter homme | C16: ='11.Charges'!D15 -> 1 | D16: ='11.Charges'!E15 -> 100 | E16: 3 | F16: EMP1 | G16: =C16*D16*E16 -> 300
A17: ='11.Charges'!A16 -> Frais indirects de vente | B17: ='11.Charges'!B16 -> Logistique Prêt-à-porter femme | C17: ='11.Charges'!D16 -> 1 | D17: ='11.Charges'!E16 -> 50 | E17: 3 | F17: EMP1 | G17: =C17*D17*E17 -> 150
A18: ='11.Charges'!A17 -> Frais indirects de vente | B18: ='11.Charges'!B17 -> Stockage Tenue de luxe Homme | C18: ='11.Charges'!D17 -> 1 | D18: ='11.Charges'!E17 -> 400 | E18: 3 | F18: EMP1 | G18: =C18*D18*E18 -> 1200
A19: ='11.Charges'!A18 -> Frais indirects de vente | B19: ='11.Charges'!B18 -> Stockage Tenue de luxe Femme | C19: ='11.Charges'!D18 -> 1 | D19: ='11.Charges'!E18 -> 800 | E19: 3 | F19: EMP1 | G19: =C19*D19*E19 -> 2400
A20: ='11.Charges'!A19 -> Frais indirects de vente | B20: ='11.Charges'!B19 -> Stockage Prêt-à-porter homme | C20: ='11.Charges'!D19 -> 1 | D20: ='11.Charges'!E19 -> 200 | E20: 3 | F20: EMP1 | G20: =C20*D20*E20 -> 600
... A41: ='11.Charges'!A40 -> Amortissement Exploitation | B41: ='11.Charges'!B40 -> Amortissement équipement. | C41: ='11.Charges'!D40 -> 1 | D41: ='11.Charges'!E40 -> 0.0351 | E41: 3 | F41: EMP2 | G41: =C41*D41*E41 -> 0.1053
A42: TOTAL | G42: =SUM(G4:G41) -> 3775000.9
